Workbook

Sheet Clients
A1: Nom | B1: Email | C1: Phone | D1: Language | E1: Date Formulaire | F1: Date Event | G1: Heure Début | H1: Heure Fin | I1: Lieu Event | J1: Type Event | K1: Invités | L1: Pack | M1: Pack (€) | N1: Transport (€) | O1: Supplément | P1: Supplément (h) | Q1: Supplément (€) | R1: Date acompte payé | S1: Acompte | T1: Total | U1: Solde Restant | V1: Etudiant | W1: Heures Etudiant | X1: Etudiant €/Event | Y1: KM (Aller) | Z1: KM (Total) | AA1: Coût Essence | AB1: Commercial | AC1: Comm Commercial | AD1: Marge Brut (Event) | AE1: Lien Invoice | AF1: Lien Galerie | AG1: Lien ZIP | AH1: Event ID | AI1: Sync Status | AJ1: Review Status | AK1: Annual Offer Status | AL1: Acompte Facture | AM1: Solde Facture
A2: Hanan et Geoffrey - Zara | C2: 0485 70 88 23 | D2: FR | F2: 45668 | J2: B2B | L2: Premium | M2: 700 | T2: =M2 -> 700 | U2: 700 | V2: Abdel | W2: 4.5 | X2: 70 | Y2: 65 | Z2: 260 | AA2: 39 | AC2: =IF(OR(L2="", AB2=""), 0, IF(L2="Découverte", KPI!$F$2, IF(L2="Essentiel", KPI!$F$3, IF(L2="Premium", KPI!$F$4, 0) ) ) ) -> 0 | AD2: {=IF(F2="", "", (T2 / 1.21) - IF(L2="Découverte", KPI!$C$2, IF(L2="Essentiel", KPI!$C$3, IF(L2="Premium", KPI!$C$4, 0) ) ) - N(X2) - N(AA2) - N(AC2) - IFERROR(INDEX(Stats!$G:$G, MATCH(DATE(YEAR(R2), MONTH(R2), 1), Stats!$A:$A, 0)), 35) )} -> 342.0124 | AH2: 8lv5q8g0s9fm99631th446r44c@google.com | AI2: OK 2026-01-02 09:35
A3: Angélique Crucilla - Commune Fleurus | C3: 0483/12.26.35 | D3: FR | F3: 45672 | I3: Chemin de Mons 61, Fleurus | J3: B2B | L3: Essentiel | M3: 645 | T3: =M3 -> 645 | U3: 645 | V3: Abdel | W3: 4.5 | X3: 70 | Y3: 65 | Z3: 260 | AA3: 39 | AC3: =IF(OR(L3="", AB3=""), 0, IF(L3="Découverte", KPI!$F$2, IF(L3="Essentiel", KPI!$F$3, IF(L3="Premium", KPI!$F$4, 0) ) ) ) -> 0 | AD3: {=IF(F3="", "", (T3 / 1.21) - IF(L3="Découverte", KPI!$C$2, IF(L3="Essentiel", KPI!$C$3, IF(L3="Premium", KPI!$C$4, 0) ) ) - N(X3) - N(AA3) - N(AC3) - IFERROR(INDEX(Stats!$G:$G, MATCH(DATE(YEAR(R3), MONTH(R3), 1), Stats!$A:$A, 0)), 35) )} -> 342.80785 | AH3: sct6isre8vahfts4ir6u9a5jj4@google.com | AI3: OK 2025-12-01 19:15 | AM3: 2025_0001
A4: Angélique Crucilla - Commune Fleurus | D4: FR | M4: 595 | AM4: 2025_0035
A5: Stocq Marie-Christine - police Bruneau | C5: 071/820161 | D5: FR | F5: 45673 | I5: Chemin de Mons 61, Fleurus | J5: B2B | L5: Premium | M5: 545 | T5: =M5 -> 545 | U5: 545 | V5: Abdel | W5: 4.5 | X5: 70 | Y5: 65 | Z5: 260 | AA5: 39 | AC5: =IF(OR(L5="", AB5=""), 0, IF(L5="Découverte", KPI!$F$2, IF(L5="Essentiel", KPI!$F$3, IF(L5="Premium", KPI!$F$4, 0) ) ) ) -> 0 | AD5: {=IF(F5="", "", (T5 / 1.21) - IF(L5="Découverte", KPI!$C$2, IF(L5="Essentiel", KPI!$C$3, IF(L5="Premium", KPI!$C$4, 0) ) ) - N(X5) - N(AA5) - N(AC5) - IFERROR(INDEX(Stats!$G:$G, MATCH(DATE(YEAR(R5), MONTH(R5), 1), Stats!$A:$A, 0)), 35) )} -> 213.91322 | AH5: t8hfdemg2ucfctt81b1f5qn8c0@google.com | AI5: OK 2025-12-01 19:15 | AM5: 2025_0002
A6: MIFRATEL | D6: FR | J6: B2B | M6: 859.1 | AM6: 2025_0036
A7: Natacha Gallo | B7: gallonatacha509@gmail.com | C7: 0472 04 16 34 | D7: FR | F7: 45682 | I7: Prestige du clothaire, Quévy | J7: Mariage | L7: Découverte | M7: 350 | N7: 80 | T7: =SUM(M7:N7) -> 430 | U7: =T7-S7 -> 430 | V7: Abdel | W7: 5.5 | X7: 70 | Y7: 86 | Z7: 344 | AA7: 51.6 | AC7: =IF(OR(L7="", AB7=""), 0, IF(L7="Découverte", KPI!$F$2, IF(L7="Essentiel", KPI!$F$3, IF(L7="Premium", KPI!$F$4, 0) ) ) ) -> 0 | AD7: {=IF(F7="", "", (T7 / 1.21) - IF(L7="Découverte", KPI!$C$2, IF(L7="Essentiel", KPI!$C$3, IF(L7="Premium", KPI!$C$4, 0) ) ) - N(X7) - N(AA7) - N(AC7) - IFERROR(INDEX(Stats!$G:$G, MATCH(DATE(YEAR(R7), MONTH(R7), 1), Stats!$A:$A, 0)), 35) )} -> 175.6519 | AH7: qtpq6pr8uro4osq6c8j4fupa3c@google.com | AI7: OK 2025-12-01 19:14 | AM7: 2025_0003
A8: Carole Crunelle | B8: carole.crunelle@hotmail.com | C8: 0476 856 004 | D8: FR | F8: 45738 | I8: Rue de Tournai 188, 7333 Saint-Ghislain | J8: Mariage | L8: Premium | M8: 500 | N8: 80 | T8: =SUM(M8:N8) -> 580 | U8: =T8-S8 -> 580 | V8: Abdel | W8: 5 | X8: 70 | Y8: 79 | Z8: 316 | AA8: 47.4 | AC8: =IF(OR(L8="", AB8=""), 0, IF(L8="Découverte", KPI!$F$2, IF(L8="Essentiel", KPI!$F$3, IF(L8="Premium", KPI!$F$4, 0) ) ) ) -> 0 | AD8: {=IF(F8="", "", (T8 / 1.21) - IF(L8="Découverte", KPI!$C$2, IF(L8="Essentiel", KPI!$C$3, IF(L8="Premium", KPI!$C$4, 0) ) ) - N(X8) - N(AA8) - N(AC8) - IFERROR(INDEX(Stats!$G:$G, MATCH(DATE(YEAR(R8), MONTH(R8), 1), Stats!$A:$A, 0)), 35) )} -> 234.43884 | AH8: voku23g04gc3ftjs94t9njrlgo@google.com | AI8: OK 2025-12-01 19:12 | AK8: Sent | AM8: 2025_0011
A9: Catherine Onclin | B9: catherine.onclin@gmail.com | C9: 0470 50 44 32 | D9: FR | F9: 45759 | I9: Hasselt (Tiendschuur Herkenrode) | J9: Mariage | L9: Premium | M9: 500 | N9: 80 | T9: =SUM(M9:N9) -> 580 | U9: =T9-S9 -> 580 | V9: Abdel | W9: 5.5 | X9: 70 | Y9: 86 | Z9: 344 | AA9: 51.6 | AC9: =IF(OR(L9="", AB9=""), 0, IF(L9="Découverte", KPI!$F$2, IF(L9="Essentiel", KPI!$F$3, IF(L9="Premium", KPI!$F$4, 0) ) ) ) -> 0 | AD9: {=IF(F9="", "", (T9 / 1.21) - IF(L9="Découverte", KPI!$C$2, IF(L9="Essentiel", KPI!$C$3, IF(L9="Premium", KPI!$C$4, 0) ) ) - N(X9) - N(AA9) - N(AC9) - IFERROR(INDEX(Stats!$G:$G, MATCH(DATE(YEAR(R9), MONTH(R9), 1), Stats!$A:$A, 0)), 35) )} -> 230.23884 | AH9: 8siq7u4sh6ggev6knle9psg2n4@google.com | AI9: OK 2025-12-01 19:11 | AK9: Sent | AM9: 2025_0015
A10: Jordan Farias | B10: jordan.farias@verisure.be | C10: 0471621626 | D10: FR | F10: 45759 | I10: Rue Lannoy 145, 7740 Pecq | L10: Premium | M10: 200 | N10: 110 | T10: =SUM(M10:N10) -> 310 | U10: =T10-S10 -> 310 | V10: Abdel | W10: 6 | X10: 70 | Y10: 95 | Z10: 380 | AA10: 57 | AC10: =IF(OR(L10="", AB10=""), 0, IF(L10="Découverte", KPI!$F$2, IF(L10="Essentiel", KPI!$F$3, IF(L10="Premium", KPI!$F$4, 0) ) ) ) -> 0 | AD10: {=IF(F10="", "", (T10 / 1.21) - IF(L10="Découverte", KPI!$C$2, IF(L10="Essentiel", KPI!$C$3, IF(L10="Premium", KPI!$C$4, 0) ) ) - N(X10) - N(AA10) - N(AC10) - IFERROR(INDEX(Stats!$G:$G, MATCH(DATE(YEAR(R10), MONTH(R10), 1), Stats!$A:$A, 0)), 35) )} -> 1.6983471 | AH10: op3lh8589jogdlqsl3k22dgdeo@google.com | AI10: OK 2025-12-01 19:25 | AK10: Sent | AM10: 2024_0001
A11: Maeva Dos Santos | B11: maevadd2@outlook.fr | C11: 0033 6 16 02 25 29 | D11: FR | F11: 45773 | I11: salle alta ripa, Avelgem | J11: Mariage | L11: Premium | M11: 500 | N11: 100 | T11: =SUM(M11:N11) -> 600 | U11: =T11-S11 -> 600 | V11: Abdel | W11: 6 | X11: 70 | Y11: 91 | Z11: 364 | AA11: 54.6 | AC11: =IF(OR(L11="", AB11=""), 0, IF(L11="Découverte", KPI!$F$2, IF(L11="Essentiel", KPI!$F$3, IF(L11="Premium", KPI!$F$4, 0) ) ) ) -> 0 | AD11: {=IF(F11="", "", (T11 / 1.21) - IF(L11="Découverte", KPI!$C$2, IF(L11="Essentiel", KPI!$C$3, IF(L11="Premium", KPI!$C$4, 0) ) ) - N(X11) - N(AA11) - N(AC11) - IFERROR(INDEX(Stats!$G:$G, MATCH(DATE(YEAR(R11), MONTH(R11), 1), Stats!$A:$A, 0)), 35) )} -> 243.76777 | AH11: ou1tjsn0jb2u3c62dlcjg4atr4@google.com | AI11: OK 2025-12-01 19:09 | AM11: 2025_0017
A12: Lyna Botte | B12: bottelyna27@gmail.com | C12: 0485 69 22 87 | D12: FR | F12: 45780 | I12: Salle The villa Event | J12: Mariage | L12: Premium | M12: 500 | T12: =SUM(M12:N12) -> 500 | U12: =T12-S12 -> 500 | V12: Abdel | W12: 2 | X12: 70 | Y12: 8 | Z12: 32 | AA12: 4.8 | AC12: =IF(OR(L12="", AB12=""), 0, IF(L12="Découverte", KPI!$F$2, IF(L12="Essentiel", KPI!$F$3, IF(L12="Premium", KPI!$F$4, 0) ) ) ) -> 0 | AD12: {=IF(F12="", "", (T12 / 1.21) - IF(L12="Découverte", KPI!$C$2, IF(L12="Essentiel", KPI!$C$3, IF(L12="Premium", KPI!$C$4, 0) ) ) - N(X12) - N(AA12) - N(AC12) - IFERROR(INDEX(Stats!$G:$G, MATCH(DATE(YEAR(R12), MONTH(R12), 1), Stats!$A:$A, 0)), 35) )} -> 210.92314 | AH12: mju0pfaqqciofm6k92f94vibis@google.com | AI12: OK 2025-12-01 19:08 | AM12: 2025_0020
A13: Serge Skrzypek | B13: Skrzypek_s@hotmail.com | C13: 0474450223 | D13: FR | F13: 45780 | I13: 210 rue Alphonse Allard, 1420 Braine L'Alleud | J13: Mariage | L13: Premium | M13: 500 | N13: 35 | T13: =SUM(M13:N13) -> 535 | U13: =T13-S13 -> 535 | V13: Abdel | W13: 3 | X13: 70 | Y13: 27 | Z13: 108 | AA13: 16.2 | AC13: =IF(OR(L13="", AB13=""), 0, IF(L13="Découverte", KPI!$F$2, IF(L13="Essentiel", KPI!$F$3, IF(L13="Premium", KPI!$F$4, 0) ) ) ) -> 0 | AD13: {=IF(F13="", "", (T13 / 1.21) - IF(L13="Découverte", KPI!$C$2, IF(L13="Essentiel", KPI!$C$3, IF(L13="Premium", KPI!$C$4, 0) ) ) - N(X13) - N(AA13) - N(AC13) - IFERROR(INDEX(Stats!$G:$G, MATCH(DATE(YEAR(R13), MONTH(R13), 1), Stats!$A:$A, 0)), 35) )} -> 228.44876 | AH13: 0m6f00d2p66tgi3vv2cjrlvgjo@google.com | AI13: OK 2025-12-01 19:12 | AL13: 2025_0010 | AM13: 2025_0021
A14: Mike et Julie Deboeck | B14: vandenbemden_julie@outlook.com | C14: 0477783468 | D14: FR | F14: 45787 | I14: La ferme de Bertinchamps, Ophain | J14: Mariage | L14: Premium | M14: 500 | N14: 50 | T14: =SUM(M14:N14) -> 550 | U14: =T14-S14 -> 550 | V14: Abdel | W14: 3 | X14: 70 | Y14: 30 | Z14: 120 | AA14: 18 | AC14: =IF(OR(L14="", AB14=""), 0, IF(L14="Découverte", KPI!$F$2, IF(L14="Essentiel", KPI!$F$3, IF(L14="Premium", KPI!$F$4, 0) ) ) ) -> 0 | AD14: {=IF(F14="", "", (T14 / 1.21) - IF(L14="Découverte", KPI!$C$2, IF(L14="Essentiel", KPI!$C$3, IF(L14="Premium", KPI!$C$4, 0) ) ) - N(X14) - N(AA14) - N(AC14) - IFERROR(INDEX(Stats!$G:$G, MATCH(DATE(YEAR(R14), MONTH(R14), 1), Stats!$A:$A, 0)), 35) )} -> 239.04545 | AH14: dqje0kkk2d3o655gr9h2erjs5c@google.com | AI14: OK 2025-12-01 19:07 | AM14: 2025_0024
A15: Abdelrani bousnina | B15: Abdelranibousnina@gmail.com | C15: 0484 067 079 | D15: FR | F15: 45787 | I15: Hendrik Kuijpersstraat 49, 2640 Mortsel | J15: Mariage | L15: Premium | M15: 500 | N15: 80 | T15: =SUM(M15:N15) -> 580 | U15: =T15-S15 -> 580 | V15: Abdel | W15: 4 | X15: 70 | Y15: 55 | Z15: 220 | AA15: 33 | AC15: =IF(OR(L15="", AB15=""), 0, IF(L15="Découverte", KPI!$F$2, IF(L15="Essentiel", KPI!$F$3, IF(L15="Premium", KPI!$F$4, 0) ) ) ) -> 0 | AD15: {=IF(F15="", "", (T15 / 1.21) - IF(L15="Découverte", KPI!$C$2, IF(L15="Essentiel", KPI!$C$3, IF(L15="Premium", KPI!$C$4, 0) ) ) - N(X15) - N(AA15) - N(AC15) - IFERROR(INDEX(Stats!$G:$G, MATCH(DATE(YEAR(R15), MONTH(R15), 1), Stats!$A:$A, 0)), 35) )} -> 248.83884 | AH15: 8hol2v8lrsg60g2tk172hcb65k@google.com | AI15: OK 2025-12-01 19:08 | AL15: 2025_0022 | AM15: 2025_0025
A16: Annick Allard | B16: Annickallard1985@gmail.com | C16: 0471 08 94 51 | D16: FR | F16: 45801 | I16: Avenue Jean-François Debecker 54B, 1200 Woluwe-Saint-Lambert | J16: Mariage | L16: Essentiel | M16: 450 | N16: 50 | T16: =SUM(M16:N16) -> 500 | U16: =T16-S16 -> 500 | V16: Abdel | W16: 3 | X16: 70 | Y16: 15 | Z16: 60 | AA16: 9 | AC16: =IF(OR(L16="", AB16=""), 0, IF(L16="Découverte", KPI!$F$2, IF(L16="Essentiel", KPI!$F$3, IF(L16="Premium", KPI!$F$4, 0) ) ) ) -> 0 | AD16: {=IF(F16="", "", (T16 / 1.21) - IF(L16="Découverte", KPI!$C$2, IF(L16="Essentiel", KPI!$C$3, IF(L16="Premium", KPI!$C$4, 0) ) ) - N(X16) - N(AA16) - N(AC16) - IFERROR(INDEX(Stats!$G:$G, MATCH(DATE(YEAR(R16), MONTH(R16), 1), Stats!$A:$A, 0)), 35) )} -> 252.97314 | AH16: ech3tbfs4r0kljmsggbf1eq8i8@google.com | AI16: OK 2025-12-01 19:14 | AL16: 2025_0004 | AM16: 2025_0030
A17: Ioan Taziana | B17: decamk.tiziana@gmail.com | C17: 0499 32 24 98 | D17: FR | F17: 45801 | I17: rue des brasseries 10, 7170 Manage | J17: Mariage | L17: Essentiel | M17: 450 | N17: 50 | T17: =SUM(M17:N17) -> 500 | U17: =T17-S17 -> 500 | V17: Abdel | W17: 4 | X17: 70 | Y17: 52 | Z17: 208 | AA17: 31.2 | AC17: =IF(OR(L17="", AB17=""), 0, IF(L17="Découverte", KPI!$F$2, IF(L17="Essentiel", KPI!$F$3, IF(L17="Premium", KPI!$F$4, 0) ) ) ) -> 0 | AD17: {=IF(F17="", "", (T17 / 1.21) - IF(L17="Découverte", KPI!$C$2, IF(L17="Essentiel", KPI!$C$3, IF(L17="Premium", KPI!$C$4, 0) ) ) - N(X17) - N(AA17) - N(AC17) - IFERROR(INDEX(Stats!$G:$G, MATCH(DATE(YEAR(R17), MONTH(R17), 1), Stats!$A:$A, 0)), 35) )} -> 230.77314 | AH17: 2tkfj4g8sjt8obb2j0urr77598@google.com | AI17: OK 2025-12-01 19:06 | AL17: 2025_0026 | AM17: 2025_0031
A18: Didier Blesin | B18: didier.blesin@gmail.com | C18: 0497 41 14 73 | D18: FR | F18: 45801 | I18: Chaussée de bruxelles 111, 1310 La Hulpe | J18: Mariage | L18: Premium | M18: 500 | N18: 50 | T18: =SUM(M18:N18) -> 550 | U18: =T18-S18 -> 550 | V18: Abdel | W18: 4 | X18: 70 | Y18: 32 | Z18: 128 | AA18: 19.2 | AC18: =IF(OR(L18="", AB18=""), 0, IF(L18="Découverte", KPI!$F$2, IF(L18="Essentiel", KPI!$F$3, IF(L18="Premium", KPI!$F$4, 0) ) ) ) -> 0 | AD18: {=IF(F18="", "", (T18 / 1.21) - IF(L18="Découverte", KPI!$C$2, IF(L18="Essentiel", KPI!$C$3, IF(L18="Premium", KPI!$C$4, 0) ) ) - N(X18) - N(AA18) - N(AC18) - IFERROR(INDEX(Stats!$G:$G, MATCH(DATE(YEAR(R18), MONTH(R18), 1), Stats!$A:$A, 0)), 35) )} -> 237.84545 | AH18: 9k5vis2g0ic9glbnn5l0k5ior0@google.com | AI18: OK 2025-12-01 19:13 | AL18: 2025_0007 | AM18: 2025_0032
A19: Samira Natiq | B19: samiranatiq@gmail.com | C19: 0485037895 | D19: FR | F19: 45822 | I19: La Louvière | J19: Mariage | L19: Essentiel | M19: 450 | N19: 50 | T19: =SUM(M19:N19) -> 500 | U19: =T19-S19 -> 500 | V19: Abdel | W19: 4 | X19: 70 | Y19: 53 | Z19: 212 | AA19: 31.8 | AC19: =IF(OR(L19="", AB19=""), 0, IF(L19="Découverte", KPI!$F$2, IF(L19="Essentiel", KPI!$F$3, IF(L19="Premium", KPI!$F$4, 0) ) ) ) -> 0 | AD19: {=IF(F19="", "", (T19 / 1.21) - IF(L19="Découverte", KPI!$C$2, IF(L19="Essentiel", KPI!$C$3, IF(L19="Premium", KPI!$C$4, 0) ) ) - N(X19) - N(AA19) - N(AC19) - IFERROR(INDEX(Stats!$G:$G, MATCH(DATE(YEAR(R19), MONTH(R19), 1), Stats!$A:$A, 0)), 35) )} -> 230.17314 | AH19: 8eh62mlikvfitg943t7b72sctg@google.com | AI19: OK 2025-12-01 19:12 | AL19: 2025_0008 | AM19: 2025_0034
A20: Meli Meli | D20: FR | F20: 45828 | J20: B2B | L20: Premium | M20: 500 | T20: =SUM(M20:N20) -> 500 | U20: =T20-S20 -> 500 | V20: Abdel | X20: 70 | AA20: =IF(Z20=0,"", Z20 * 0.15) | AC20: =IF(OR(L20="", AB20=""), 0, IF(L20="Découverte", KPI!$F$2, IF(L20="Essentiel", KPI!$F$3, IF(L20="Premium", KPI!$F$4, 0) ) ) ) -> 0 | AD20: {=IF(F20="", "", (T20 / 1.21) - IF(L20="Découverte", KPI!$C$2, IF(L20="Essentiel", KPI!$C$3, IF(L20="Premium", KPI!$C$4, 0) ) ) - N(X20) - N(AA20) - N(AC20) - IFERROR(INDEX(Stats!$G:$G, MATCH(DATE(YEAR(R20), MONTH(R20), 1), Stats!$A:$A, 0)), 35) )} -> 215.72314 | AH20: a580dr3lnta2gc398qf7a4qeug@google.com | AI20: OK 2025-11-21 21:18
A21: Meli Meli | D21: FR | F21: 45829 | J21: B2B | L21: Premium | M21: 500 | T21: =SUM(M21:N21) -> 500 | U21: =T21-S21 -> 500 | V21: Abdel | X21: 70 | AA21: =IF(Z21=0,"", Z21 * 0.15) | AC21: =IF(OR(L21="", AB21=""), 0, IF(L21="Découverte", KPI!$F$2, IF(L21="Essentiel", KPI!$F$3, IF(L21="Premium", KPI!$F$4, 0) ) ) ) -> 0 | AD21: {=IF(F21="", "", (T21 / 1.21) - IF(L21="Découverte", KPI!$C$2, IF(L21="Essentiel", KPI!$C$3, IF(L21="Premium", KPI!$C$4, 0) ) ) - N(X21) - N(AA21) - N(AC21) - IFERROR(INDEX(Stats!$G:$G, MATCH(DATE(YEAR(R21), MONTH(R21), 1), Stats!$A:$A, 0)), 35) )} -> 215.72314 | AH21: a1vjn8877eje74j131lmvrgqks@google.com | AI21: OK 2025-11-21 21:18
A22: Fatima | B22: Tahiri-fatima@hotmail.com | C22: 0484761578 | D22: FR | F22: 45832 | I22: Oudstrijderslaan 200, 1140 Evere | J22: Mariage | L22: Découverte | M22: 350 | N22: 50 | T22: =SUM(M22:N22) -> 400 | U22: =T22-S22 -> 400 | V22: Abdel | W22: 3 | X22: 70 | Y22: 15 | Z22: 60 | AA22: 9 | AC22: =IF(OR(L22="", AB22=""), 0, IF(L22="Découverte", KPI!$F$2, IF(L22="Essentiel", KPI!$F$3, IF(L22="Premium", KPI!$F$4, 0) ) ) ) -> 0 | AD22: {=IF(F22="", "", (T22 / 1.21) - IF(L22="Découverte", KPI!$C$2, IF(L22="Essentiel", KPI!$C$3, IF(L22="Premium", KPI!$C$4, 0) ) ) - N(X22) - N(AA22) - N(AC22) - IFERROR(INDEX(Stats!$G:$G, MATCH(DATE(YEAR(R22), MONTH(R22), 1), Stats!$A:$A, 0)), 35) )} -> 193.45851 | AH22: omujkk1igs6bb0rhvimuudmhvc@google.com | AI22: OK 2025-12-01 19:26 | AM22: 2024_0002
A23: Magali Rosa Lopez | B23: lopez4781@hotmail.com | C23: 0479 84 65 30 | D23: FR | F23: 45833 | I23: Place du Mole 11, Braine-L'alleud | J23: Mariage | L23: Premium | M23: 400 | T23: =SUM(M23:N23) -> 400 | U23: =T23-S23 -> 400 | V23: Abdel | W23: 3.5 | X23: 70 | Y23: 30 | Z23: 120 | AA23: 18 | AC23: =IF(OR(L23="", AB23=""), 0, IF(L23="Découverte", KPI!$F$2, IF(L23="Essentiel", KPI!$F$3, IF(L23="Premium", KPI!$F$4, 0) ) ) ) -> 0 | AD23: {=IF(F23="", "", (T23 / 1.21) - IF(L23="Découverte", KPI!$C$2, IF(L23="Essentiel", KPI!$C$3, IF(L23="Premium", KPI!$C$4, 0) ) ) - N(X23) - N(AA23) - N(AC23) - IFERROR(INDEX(Stats!$G:$G, MATCH(DATE(YEAR(R23), MONTH(R23), 1), Stats!$A:$A, 0)), 35) )} -> 115.07851 | AH23: a7egjnkibo8vjv91ltjqklona4@google.com | AI23: OK 2025-12-01 19:26 | AL23: 2025_0027 | AM23: 2024_0003
A24: Jennifer Jacquemin | B24: jenniferjacquemin@outlook.be | C24: 0492 96 03 66 | D24: FR | F24: 45857 | I24: Rue des chapelain 6, 4000 Liège | J24: Mariage | L24: Premium | M24: 500 | N24: 100 | T24: =SUM(M24:N24) -> 600 | U24: =T24-S24 -> 600 | V24: Abdel | W24: 6.5 | X24: 70 | Y24: 103 | Z24: 412 | AA24: 61.8 | AC24: =IF(OR(L24="", AB24=""), 0, IF(L24="Découverte", KPI!$F$2, IF(L24="Essentiel", KPI!$F$3, IF(L24="Premium", KPI!$F$4, 0) ) ) ) -> 0 | AD24: {=IF(F24="", "", (T24 / 1.21) - IF(L24="Découverte", KPI!$C$2, IF(L24="Essentiel", KPI!$C$3, IF(L24="Premium", KPI!$C$4, 0) ) ) - N(X24) - N(AA24) - N(AC24) - IFERROR(INDEX(Stats!$G:$G, MATCH(DATE(YEAR(R24), MONTH(R24), 1), Stats!$A:$A, 0)), 35) )} -> 236.56777 | AH24: r94e53c6vics8vrlj4le27373o@google.com | AI24: OK 2025-12-01 19:05 | AL24: 2025_0029 | AM24: 2025_0037
A25: Mathilde Debay | B25: mathilde.debay@gmail.com | C25: 0478 92 84 07 | D25: FR | F25: 45857 | I25: Rue du parc 4, 4577 Modave | J25: Mariage | L25: Premium | M25: 500 | N25: 120 | T25: =SUM(M25:N25) -> 620 | U25: =T25-S25 -> 620 | V25: Abdel | W25: 7.5 | X25: 70 | Y25: 110 | Z25: 440 | AA25: 66 | AC25: =IF(OR(L25="", AB25=""), 0, IF(L25="Découverte", KPI!$F$2, IF(L25="Essentiel", KPI!$F$3, IF(L25="Premium", KPI!$F$4, 0) ) ) ) -> 0 | AD25: {=IF(F25="", "", (T25 / 1.21) - IF(L25="Découverte", KPI!$C$2, IF(L25="Essentiel", KPI!$C$3, IF(L25="Premium", KPI!$C$4, 0) ) ) - N(X25) - N(AA25) - N(AC25) - IFERROR(INDEX(Stats!$G:$G, MATCH(DATE(YEAR(R25), MONTH(R25), 1), Stats!$A:$A, 0)), 35) )} -> 248.89669 | AH25: ba31nuhi5p57glrmq85m8octh0@google.com | AI25: OK 2025-12-01 19:04 | AL25: 2025_0033 | AM25: 2025_0038
A26: Laura Kowalsi | B26: laura.kowalski@hotmail.fr | C26: 0033615253010 | D26: FR | F26: 45864 | I26: 214 rue Roger salengro, 59590 raismes | J26: Mariage | L26: Premium | M26: 500 | N26: 125 | T26: =SUM(M26:N26) -> 625 | U26: =T26-S26 -> 625 | V26: Abdel | W26: 6.5 | X26: 70 | Y26: 117 | Z26: 468 | AA26: 70.2 | AC26: =IF(OR(L26="", AB26=""), 0, IF(L26="Découverte", KPI!$F$2, IF(L26="Essentiel", KPI!$F$3, IF(L26="Premium", KPI!$F$4, 0) ) ) ) -> 0 | AD26: {=IF(F26="", "", (T26 / 1.21) - IF(L26="Découverte", KPI!$C$2, IF(L26="Essentiel", KPI!$C$3, IF(L26="Premium", KPI!$C$4, 0) ) ) - N(X26) - N(AA26) - N(AC26) - IFERROR(INDEX(Stats!$G:$G, MATCH(DATE(YEAR(R26), MONTH(R26), 1), Stats!$A:$A, 0)), 35) )} -> 248.82893 | AH26: 3l3p48p658l0qru1jn0fs0jomo@google.com | AI26: OK 2025-12-01 19:11 | AL26: 2025_0013 | AM26: 2025_0039
A27: Kevin Ladeuze | B27: k.ladeuze@outlook.com | C27: 0494361803 | D27: FR | F27: 45877 | I27: rue Grégoire jurion 22, 7120 vellereille-les-brayeux | J27: Mariage | L27: Premium | M27: 500 | N27: 70 | T27: =SUM(M27:N27) -> 570 | U27: =T27-S27 -> 570 | V27: Abdel | W27: 5 | X27: 70 | Y27: 69 | Z27: 276 | AA27: 41.4 | AC27: =IF(OR(L27="", AB27=""), 0, IF(L27="Découverte", KPI!$F$2, IF(L27="Essentiel", KPI!$F$3, IF(L27="Premium", KPI!$F$4, 0) ) ) ) -> 0 | AD27: {=IF(F27="", "", (T27 / 1.21) - IF(L27="Découverte", KPI!$C$2, IF(L27="Essentiel", KPI!$C$3, IF(L27="Premium", KPI!$C$4, 0) ) ) - N(X27) - N(AA27) - N(AC27) - IFERROR(INDEX(Stats!$G:$G, MATCH(DATE(YEAR(R27), MONTH(R27), 1), Stats!$A:$A, 0)), 35) )} -> 232.17438 | AH27: rqgp73fd6udgfsmc7t1738me5s@google.com | AI27: OK 2025-12-01 18:57 | AM27: 2025_0042
A28: Olivier Vanhuysse | B28: ovanhuysse@gmail.com | C28: 0473 30 16 86 | D28: FR | F28: 45878 | I28: Rue de la longue semaine, 1460 Ittre | J28: Mariage | L28: Premium | M28: 500 | N28: 70 | T28: =SUM(M28:N28) -> 570 | U28: =T28-S28 -> 570 | V28: Abdel | W28: 3 | X28: 70 | Y28: 29 | Z28: 116 | AA28: 17.4 | AC28: =IF(OR(L28="", AB28=""), 0, IF(L28="Découverte", KPI!$F$2, IF(L28="Essentiel", KPI!$F$3, IF(L28="Premium", KPI!$F$4, 0) ) ) ) -> 0 | AD28: {=IF(F28="", "", (T28 / 1.21) - IF(L28="Découverte", KPI!$C$2, IF(L28="Essentiel", KPI!$C$3, IF(L28="Premium", KPI!$C$4, 0) ) ) - N(X28) - N(AA28) - N(AC28) - IFERROR(INDEX(Stats!$G:$G, MATCH(DATE(YEAR(R28), MONTH(R28), 1), Stats!$A:$A, 0)), 35) )} -> 256.17438 | AH28: 5frs8959qd51eovoq5oltr2pvc@google.com | AI28: OK 2025-12-01 19:12 | AL28: 2025_0009 | AM28: 2025_0043
A29: Fortuna Giovanni | B29: fortunagiovanni@hotmail.com | C29: 0472261163 | D29: FR | F29: 45878 | I29: 83 voie des fosses, 4607 dalhem | J29: Mariage | L29: Premium | M29: 600 | N29: 100 | T29: =SUM(M29:N29) -> 700 | U29: =T29-S29 -> 700 | V29: Abdel | W29: 7 | X29: 70 | Y29: 115 | Z29: 460 | AA29: 69 | AC29: =IF(OR(L29="", AB29=""), 0, IF(L29="Découverte", KPI!$F$2, IF(L29="Essentiel", KPI!$F$3, IF(L29="Premium", KPI!$F$4, 0) ) ) ) -> 0 | AD29: {=IF(F29="", "", (T29 / 1.21) - IF(L29="Découverte", KPI!$C$2, IF(L29="Essentiel", KPI!$C$3, IF(L29="Premium", KPI!$C$4, 0) ) ) - N(X29) - N(AA29) - N(AC29) - IFERROR(INDEX(Stats!$G:$G, MATCH(DATE(YEAR(R29), MONTH(R29), 1), Stats!$A:$A, 0)), 35) )} -> 312.0124 | AH29: q7v7c1gh8ued6dojf497pjd7h0@google.com | AI29: OK 2025-12-01 18:56 | AL29: 2025_0044 | AM29: 2025_0045
A30: Alexia Cuffaro | C30: 0492 57 14 99 | D30: FR | F30: 45878 | I30: Rue docteur E. Neuville 17, 4530 Villers le Bouillet | J30: Mariage | L30: Premium | M30: 650 | N30: 100 | T30: =SUM(M30:N30) -> 750 | U30: =T30-S30 -> 750 | V30: Abdel | W30: 6 | X30: 70 | Y30: 88 | Z30: 352 | AA30: 52.8 | AC30: =IF(OR(L30="", AB30=""), 0, IF(L30="Découverte", KPI!$F$2, IF(L30="Essentiel", KPI!$F$3, IF(L30="Premium", KPI!$F$4, 0) ) ) ) -> 0 | AD30: {=IF(F30="", "", (T30 / 1.21) - IF(L30="Découverte", KPI!$C$2, IF(L30="Essentiel", KPI!$C$3, IF(L30="Premium", KPI!$C$4, 0) ) ) - N(X30) - N(AA30) - N(AC30) - IFERROR(INDEX(Stats!$G:$G, MATCH(DATE(YEAR(R30), MONTH(R30), 1), Stats!$A:$A, 0)), 35) )} -> 369.53471 | AH30: 45mvgl689is6kanieu791ik2nk@google.com | AI30: OK 2025-11-22 13:01
A31: Clément Picard | B31: yaelle.clement.home@gmail.com | C31: 0033 750381771 | D31: FR | F31: 45885 | I31: Château de Bac Saint Maur, Sailly sur la Lys | J31: Mariage | L31: Essentiel | M31: 450 | N31: 130 | T31: =SUM(M31:N31) -> 580 | U31: =T31-S31 -> 580 | V31: Abdel | W31: 7.5 | X31: 70 | Y31: 132 | Z31: 528 | AA31: 79.2 | AC31: =IF(OR(L31="", AB31=""), 0, IF(L31="Découverte", KPI!$F$2, IF(L31="Essentiel", KPI!$F$3, IF(L31="Premium", KPI!$F$4, 0) ) ) ) -> 0 | AD31: {=IF(F31="", "", (T31 / 1.21) - IF(L31="Découverte", KPI!$C$2, IF(L31="Essentiel", KPI!$C$3, IF(L31="Premium", KPI!$C$4, 0) ) ) - N(X31) - N(AA31) - N(AC31) - IFERROR(INDEX(Stats!$G:$G, MATCH(DATE(YEAR(R31), MONTH(R31), 1), Stats!$A:$A, 0)), 35) )} -> 248.88884 | AH31: 6mjjfbvf15rrv3i73lc7o8avm0@google.com | AI31: OK 2025-12-01 18:56 | AM31: 2025_0047
A32: Melissa Dasouza | B32: melissa.dasouza60@orange.fr | C32: 0685 63 24 67 | D32: FR | F32: 45885 | I32: Éteignières, 08260, France | J32: Mariage | L32: Premium | M32: 500 | N32: 140 | T32: =SUM(M32:N32) -> 640 | U32: =T32-S32 -> 640 | V32: Abdel | W32: 8 | X32: 70 | Y32: 133 | Z32: 532 | AA32: 79.8 | AC32: =IF(OR(L32="", AB32=""), 0, IF(L32="Découverte", KPI!$F$2, IF(L32="Essentiel", KPI!$F$3, IF(L32="Premium", KPI!$F$4, 0) ) ) ) -> 0 | AD32: {=IF(F32="", "", (T32 / 1.21) - IF(L32="Découverte", KPI!$C$2, IF(L32="Essentiel", KPI!$C$3, IF(L32="Premium", KPI!$C$4, 0) ) ) - N(X32) - N(AA32) - N(AC32) - IFERROR(INDEX(Stats!$G:$G, MATCH(DATE(YEAR(R32), MONTH(R32), 1), Stats!$A:$A, 0)), 35) )} -> 251.62562 | AH32: m2f093aot0iv83is8lb43cj08k@google.com | AI32: OK 2025-12-01 18:55 | AM32: 2025_0048
A33: Frederique Verden | B33: verden.fred@gmail.com | C33: 0493 54 56 53 | D33: FR | F33: 45885 | I33: Jozef Mertensstraat 140, 1702 Dilbeek | J33: Mariage | L33: Essentiel | M33: 450 | N33: 50 | T33: =SUM(M33:N33) -> 500 | U33: =T33-S33 -> 500 | V33: Abdel | W33: 2.5 | X33: 70 | Y33: 20 | Z33: 80 | AA33: 12 | AC33: =IF(OR(L33="", AB33=""), 0, IF(L33="Découverte", KPI!$F$2, IF(L33="Essentiel", KPI!$F$3, IF(L33="Premium", KPI!$F$4, 0) ) ) ) -> 0 | AD33: {=IF(F33="", "", (T33 / 1.21) - IF(L33="Découverte", KPI!$C$2, IF(L33="Essentiel", KPI!$C$3, IF(L33="Premium", KPI!$C$4, 0) ) ) - N(X33) - N(AA33) - N(AC33) - IFERROR(INDEX(Stats!$G:$G, MATCH(DATE(YEAR(R33), MONTH(R33), 1), Stats!$A:$A, 0)), 35) )} -> 249.97314 | AH33: d6d118gbchdm1m5qsbfjgs8qlg@google.com | AI33: OK 2025-12-01 19:26 | AM33: 2024_0003
A34: Sephora Karmaoui | C34: 0492 54 28 26 | D34: FR | F34: 45891 | J34: Mariage | L34: Premium | M34: 500 | T34: =SUM(M34:N34) -> 500 | U34: =T34-S34 -> 500 | V34: Abdel | X34: 70 | AA34: =IF(Z34=0,"", Z34 * 0.15) | AC34: =IF(OR(L34="", AB34=""), 0, IF(L34="Découverte", KPI!$F$2, IF(L34="Essentiel", KPI!$F$3, IF(L34="Premium", KPI!$F$4, 0) ) ) ) -> 0 | AD34: {=IF(F34="", "", (T34 / 1.21) - IF(L34="Découverte", KPI!$C$2, IF(L34="Essentiel", KPI!$C$3, IF(L34="Premium", KPI!$C$4, 0) ) ) - N(X34) - N(AA34) - N(AC34) - IFERROR(INDEX(Stats!$G:$G, MATCH(DATE(YEAR(R34), MONTH(R34), 1), Stats!$A:$A, 0)), 35) )} -> 215.72314 | AH34: m39hf7euq7elo338k851sng218@google.com | AI34: OK 2025-11-21 21:18
A35: Juliette Gomis | B35: juliette.gomis26@gmail.com | C35: 0033784727595 | D35: FR | F35: 45892 | I35: Gasthuisstraat 57, 8970 Poperinge | J35: Mariage | L35: Essentiel | M35: 450 | N35: 130 | T35: =SUM(M35:N35) -> 580 | U35: =T35-S35 -> 580 | V35: Abdel | W35: 7.5 | X35: 70 | Y35: 134 | Z35: 536 | AA35: 80.4 | AC35: =IF(OR(L35="", AB35=""), 0, IF(L35="Découverte", KPI!$F$2, IF(L35="Essentiel", KPI!$F$3, IF(L35="Premium", KPI!$F$4, 0) ) ) ) -> 0 | AD35: {=IF(F35="", "", (T35 / 1.21) - IF(L35="Découverte", KPI!$C$2, IF(L35="Essentiel", KPI!$C$3, IF(L35="Premium", KPI!$C$4, 0) ) ) - N(X35) - N(AA35) - N(AC35) - IFERROR(INDEX(Stats!$G:$G, MATCH(DATE(YEAR(R35), MONTH(R35), 1), Stats!$A:$A, 0)), 35) )} -> 247.68884 | AH35: j6q8gdnrjlfc97l4mu3aic711o@google.com | AI35: OK 2025-12-01 19:10 | AL35: 2025_0016 | AM35: 2025_0049
A36: Israa AL OUBAYDI | B36: isra.aloubaydi@gmail.com | C36: 0483 26 51 63 | D36: FR | F36: 45893 | I36: Broekstraat 77, 1831 Machelen | J36: Mariage | L36: Essentiel | M36: 450 | N36: 90 | T36: =SUM(M36:N36) -> 540 | U36: =T36-S36 -> 540 | V36: Abdel | W36: 3 | X36: 70 | Y36: 22 | Z36: 88 | AA36: 13.2 | AC36: =IF(OR(L36="", AB36=""), 0, IF(L36="Découverte", KPI!$F$2, IF(L36="Essentiel", KPI!$F$3, IF(L36="Premium", KPI!$F$4, 0) ) ) ) -> 0 | AD36: {=IF(F36="", "", (T36 / 1.21) - IF(L36="Découverte", KPI!$C$2, IF(L36="Essentiel", KPI!$C$3, IF(L36="Premium", KPI!$C$4, 0) ) ) - N(X36) - N(AA36) - N(AC36) - IFERROR(INDEX(Stats!$G:$G, MATCH(DATE(YEAR(R36), MONTH(R36), 1), Stats!$A:$A, 0)), 35) )} -> 281.83099 | AH36: 17k7k7fb7qni1mra3cb07qft9g@google.com | AI36: OK 2025-12-01 18:56 | AL36: 2025_0046 | AM36: 2025_0050
A37: Melanie Amichi | B37: Defretinmelanie@gmail.com | C37: 06 020 703 40 | D37: FR | F37: 45899 | I37: Domaine de la cendrée, Harnes | J37: Mariage | L37: Decouverte | M37: 400 | N37: 100 | T37: =SUM(M37:N37) -> 500 | U37: =T37-S37 -> 500 | V37: Abdel | W37: 7 | X37: 70 | Y37: 128 | Z37: 512 | AA37: 76.8 | AC37: =IF(OR(L37="", AB37=""), 0, IF(L37="Découverte", KPI!$F$2, IF(L37="Essentiel", KPI!$F$3, IF(L37="Premium", KPI!$F$4, 0) ) ) ) -> 0 | AD37: {=IF(F37="", "", (T37 / 1.21) - IF(L37="Découverte", KPI!$C$2, IF(L37="Essentiel", KPI!$C$3, IF(L37="Premium", KPI!$C$4, 0) ) ) - N(X37) - N(AA37) - N(AC37) - IFERROR(INDEX(Stats!$G:$G, MATCH(DATE(YEAR(R37), MONTH(R37), 1), Stats!$A:$A, 0)), 35) )} -> 231.42314 | AH37: reklrh78v49ma6isa41j25eg44@google.com | AI37: OK 2025-12-01 18:55 | AM37: 2025_0052
A38: Fracassi Celine | B38: Celinefracassi@icloud.com | C38: 0495 46 63 54 | D38: FR | F38: 45906 | I38: Rte de Mons 54, 6560 Erquelinnes | J38: Mariage | L38: Premium | M38: 500 | N38: 120 | T38: =SUM(M38:N38) -> 620 | U38: =T38-S38 -> 620 | V38: Abdel | W38: 6 | X38: 70 | Y38: 89 | Z38: 356 | AA38: 53.4 | AC38: =IF(OR(L38="", AB38=""), 0, IF(L38="Découverte", KPI!$F$2, IF(L38="Essentiel", KPI!$F$3, IF(L38="Premium", KPI!$F$4, 0) ) ) ) -> 0 | AD38: {=IF(F38="", "", (T38 / 1.21) - IF(L38="Découverte", KPI!$C$2, IF(L38="Essentiel", KPI!$C$3, IF(L38="Premium", KPI!$C$4, 0) ) ) - N(X38) - N(AA38) - N(AC38) - IFERROR(INDEX(Stats!$G:$G, MATCH(DATE(YEAR(R38), MONTH(R38), 1), Stats!$A:$A, 0)), 35) )} -> 261.49669 | AH38: u5aa3qd1glcpv29ir1roqf6650@google.com | AI38: OK 2025-12-01 18:54 | AM38: 2025_0053
A39: Emma Mabille | B39: Emmamabille8@gmail.com | C39: 0033644373939 | D39: FR | F39: 45906 | I39: 274 allée des marronniers, 59114 Eecke | J39: Mariage | L39: Premium | M39: 500 | N39: 120 | T39: =SUM(M39:N39) -> 620 | U39: =T39-S39 -> 620 | V39: Abdel | W39: 8.5 | X39: 70 | Y39: 156 | Z39: 624 | AA39: 93.6 | AC39: =IF(OR(L39="", AB39=""), 0, IF(L39="Découverte", KPI!$F$2, IF(L39="Essentiel", KPI!$F$3, IF(L39="Premium", KPI!$F$4, 0) ) ) ) -> 0 | AD39: {=IF(F39="", "", (T39 / 1.21) - IF(L39="Découverte", KPI!$C$2, IF(L39="Essentiel", KPI!$C$3, IF(L39="Premium", KPI!$C$4, 0) ) ) - N(X39) - N(AA39) - N(AC39) - IFERROR(INDEX(Stats!$G:$G, MATCH(DATE(YEAR(R39), MONTH(R39), 1), Stats!$A:$A, 0)), 35) )} -> 221.29669 | AH39: 9s7qloq0eke2ovcjqu00jfqjkg@google.com | AI39: OK 2025-12-01 19:11 | AL39: 2025_0014 | AM39: 2025_0055
A40: Eléni & Charel Schroeder | B40: epolissiou@gmail.com | C40: 0493861149 | D40: FR | F40: 45913 | I40: Rue du Village 50 , 5380 Franc-Warêt | J40: Mariage | L40: Essentiel | M40: 450 | N40: 100 | T40: =SUM(M40:N40) -> 550 | U40: =T40-S40 -> 550 | V40: Abdel | W40: 5.5 | X40: 70 | Y40: 78 | Z40: 312 | AA40: 46.8 | AC40: =IF(OR(L40="", AB40=""), 0, IF(L40="Découverte", KPI!$F$2, IF(L40="Essentiel", KPI!$F$3, IF(L40="Premium", KPI!$F$4, 0) ) ) ) -> 0 | AD40: {=IF(F40="", "", (T40 / 1.21) - IF(L40="Découverte", KPI!$C$2, IF(L40="Essentiel", KPI!$C$3, IF(L40="Premium", KPI!$C$4, 0) ) ) - N(X40) - N(AA40) - N(AC40) - IFERROR(INDEX(Stats!$G:$G, MATCH(DATE(YEAR(R40), MONTH(R40), 1), Stats!$A:$A, 0)), 35) )} -> 256.49545 | AH40: f9b76qpo5f67sue5d5n8embq1k@google.com | AI40: OK 2025-12-01 18:54 | AM40: 2025_0056
A41: Sarah Quintaes | B41: quintaes@telenet.be | C41: 0483585806 ou 0492462442 | D41: FR | F41: 45913 | I41: paleizenlaan, 3080 Tervuren | J41: Mariage | L41: Essentiel | M41: 450 | N41: 80 | T41: =SUM(M41:N41) -> 530 | U41: =T41-S41 -> 530 | V41: Abdel | W41: 3.5 | X41: 70 | Y41: 24 | Z41: 96 | AA41: 14.4 | AC41: =IF(OR(L41="", AB41=""), 0, IF(L41="Découverte", KPI!$F$2, IF(L41="Essentiel", KPI!$F$3, IF(L41="Premium", KPI!$F$4, 0) ) ) ) -> 0 | AD41: {=IF(F41="", "", (T41 / 1.21) - IF(L41="Découverte", KPI!$C$2, IF(L41="Essentiel", KPI!$C$3, IF(L41="Premium", KPI!$C$4, 0) ) ) - N(X41) - N(AA41) - N(AC41) - IFERROR(INDEX(Stats!$G:$G, MATCH(DATE(YEAR(R41), MONTH(R41), 1), Stats!$A:$A, 0)), 35) )} -> 272.36653 | AH41: 3484d8prb2al2u74i6s7chg12s@google.com | AI41: OK 2025-12-01 18:57 | AL41: 2025_0041 | AM41: 2025_0057
A42: Karine Mahieu | B42: Mahieu.karine@hotmail.com | C42: 0489 04 15 49 | D42: FR | F42: 45913 | I42: Place de cuesmes 10 , 7033 cuesmes | J42: Mariage | L42: Premium | M42: 500 | N42: 100 | T42: =SUM(M42:N42) -> 600 | U42: =T42-S42 -> 600 | V42: Abdel | W42: 5 | X42: 70 | Y42: 75 | Z42: 300 | AA42: 45 | AC42: =IF(OR(L42="", AB42=""), 0, IF(L42="Découverte", KPI!$F$2, IF(L42="Essentiel", KPI!$F$3, IF(L42="Premium", KPI!$F$4, 0) ) ) ) -> 0 | AD42: {=IF(F42="", "", (T42 / 1.21) - IF(L42="Découverte", KPI!$C$2, IF(L42="Essentiel", KPI!$C$3, IF(L42="Premium", KPI!$C$4, 0) ) ) - N(X42) - N(AA42) - N(AC42) - IFERROR(INDEX(Stats!$G:$G, MATCH(DATE(YEAR(R42), MONTH(R42), 1), Stats!$A:$A, 0)), 35) )} -> 253.36777 | AH42: dej48kv2pjnbp7jm11vrid9qvo@google.com | AI42: OK 2025-12-01 19:09 | AL42: 2025_0018 | AM42: 2025_0058
A43: Mathieu BYD | C43: 0472 45 38 83 | D43: FR | F43: 45913 | I43: Leuvensesteenweg | J43: B2B | L43: Premium | M43: 1270.5 | T43: =SUM(M43:N43) -> 1270.5 | U43: =T43-S43 -> 1270.5 | V43: Abdel | W43: 3.5 | X43: 70 | Y43: 36 | Z43: 144 | AA43: 21.6 | AC43: =IF(OR(L43="", AB43=""), 0, IF(L43="Découverte", KPI!$F$2, IF(L43="Essentiel", KPI!$F$3, IF(L43="Premium", KPI!$F$4, 0) ) ) ) -> 0 | AD43: {=IF(F43="", "", (T43 / 1.21) - IF(L43="Découverte", KPI!$C$2, IF(L43="Essentiel", KPI!$C$3, IF(L43="Premium", KPI!$C$4, 0) ) ) - N(X43) - N(AA43) - N(AC43) - IFERROR(INDEX(Stats!$G:$G, MATCH(DATE(YEAR(R43), MONTH(R43), 1), Stats!$A:$A, 0)), 35) )} -> 830.9 | AH43: lpmp5vnf3atdr4qfko8ab70qjk@google.com | AI43: OK 2025-12-01 18:53 | AM43: 2025_0059
A44: Restaurant Vincent | C44: 32491888549 | D44: FR | E44: 45870 | F44: 45918 | I44: Rue des Dominicains, Bruxelles | J44: B2B | L44: Premium | M44: 726 | N44: 60.5 | S44: 0 | T44: =SUM(M44:N44) -> 786.5 | U44: =T44-S44 -> 786.5 | V44: Abdel | W44: 2.5 | X44: 70 | Y44: 8 | Z44: 32 | AA44: 4.8 | AC44: =IF(OR(L44="", AB44=""), 0, IF(L44="Découverte", KPI!$F$2, IF(L44="Essentiel", KPI!$F$3, IF(L44="Premium", KPI!$F$4, 0) ) ) ) -> 0 | AD44: {=IF(F44="", "", (T44 / 1.21) - IF(L44="Découverte", KPI!$C$2, IF(L44="Essentiel", KPI!$C$3, IF(L44="Premium", KPI!$C$4, 0) ) ) - N(X44) - N(AA44) - N(AC44) - IFERROR(INDEX(Stats!$G:$G, MATCH(DATE(YEAR(R44), MONTH(R44), 1), Stats!$A:$A, 0)), 35) )} -> 447.7 | AH44: qapqssm5pdj9dkcp3ip3id8hf4@google.com | AI44: OK 2025-12-01 18:52 | AM44: 2025_0062
A45: Aurore Labelle | B45: labelleaurore13@gmail.com | C45: 32495698239 | D45: FR | E45: 45870 | F45: 46578 | I45: Rue de l'Église, 59740 Hestrud, France | J45: Mariage | L45: Essentiel | M45: 450 | N45: 100 | S45: 150 | T45: 550 | U45: 400 | W45: 6.5 | X45: =IF(W45=0, " ",W45*14) -> 91 | Y45: 100 | Z45: 400 | AA45: 60 | AC45: =IF(OR(L45="", AB45=""), 0, IF(L45="Découverte", KPI!$F$2, IF(L45="Essentiel", KPI!$F$3, IF(L45="Premium", KPI!$F$4, 0) ) ) ) -> 0 | AD45: {=IF(F45="", "", (T45 / 1.21) - IF(L45="Découverte", KPI!$C$2, IF(L45="Essentiel", KPI!$C$3, IF(L45="Premium", KPI!$C$4, 0) ) ) - N(X45) - N(AA45) - N(AC45) - IFERROR(INDEX(Stats!$G:$G, MATCH(DATE(YEAR(R45), MONTH(R45), 1), Stats!$A:$A, 0)), 35) )} -> 222.29545 | AH45: 7lmjl38sthautk62bfhk781gtc@google.com | AI45: OK 2025-11-22 13:39
A46: Esmeralda Gallo | B46: esme1901@hotmail.fr | C46: 32465884793 | D46: FR | E46: 45870 | F46: 46291 | I46: Salle Petit Versailles, Rue Pont-à-Migneloux 18, 6041 Gosselies | J46: Mariage | L46: Premium | M46: 500 | N46: 65 | S46: 0 | T46: 565 | U46: 565 | W46: 4 | X46: =IF(W46=0, " ",W46*14) -> 56 | Y46: 57 | Z46: 228 | AA46: 34.2 | AC46: =IF(OR(L46="", AB46=""), 0, IF(L46="Découverte", KPI!$F$2, IF(L46="Essentiel", KPI!$F$3, IF(L46="Premium", KPI!$F$4, 0) ) ) ) -> 0 | AD46: {=IF(F46="", "", (T46 / 1.21) - IF(L46="Découverte", KPI!$C$2, IF(L46="Essentiel", KPI!$C$3, IF(L46="Premium", KPI!$C$4, 0) ) ) - N(X46) - N(AA46) - N(AC46) - IFERROR(INDEX(Stats!$G:$G, MATCH(DATE(YEAR(R46), MONTH(R46), 1), Stats!$A:$A, 0)), 35) )} -> 249.24215 | AH46: drf528ck6rihn3c58b8s4tgb54@google.com | AI46: OK 2025-11-22 13:37
A47: Valerie Depasse | B47: valerie_depasse@hotmail.com | C47: 32474220987 | D47: FR | E47: 45870 | F47: 46284 | I47: Fleurus, Rue de la chapelle 72, 6224 Wanfercee-baulet | J47: Mariage | L47: Premium | M47: 500 | N47: 85 | S47: 150 | T47: 585 | U47: 435 | W47: 4.5 | X47: =IF(W47=0, " ",W47*14) -> 63 | Y47: 70 | Z47: 280 | AA47: 42 | AC47: =IF(OR(L47="", AB47=""), 0, IF(L47="Découverte", KPI!$F$2, IF(L47="Essentiel", KPI!$F$3, IF(L47="Premium", KPI!$F$4, 0) ) ) ) -> 0 | AD47: {=IF(F47="", "", (T47 / 1.21) - IF(L47="Découverte", KPI!$C$2, IF(L47="Essentiel", KPI!$C$3, IF(L47="Premium", KPI!$C$4, 0) ) ) - N(X47) - N(AA47) - N(AC47) - IFERROR(INDEX(Stats!$G:$G, MATCH(DATE(YEAR(R47), MONTH(R47), 1), Stats!$A:$A, 0)), 35) )} -> 250.97107 | AH47: nemneslgbspnemhvl3hmquidk0@google.com | AI47: OK 2025-12-01 19:13 | AL47: 2025_0005
A48: Aurélie Faudeux | B48: faudeudaurelie87@gmail.com | C48: 32491870045 | D48: FR | E48: 45870 | F48: 46271 | I48: Place louis Debrouckère 3, 6200 Châtelineau | J48: Mariage | L48: Premium | M48: 500 | N48: 70 | S48: 150 | T48: 570 | U48: 420 | W48: 4.5 | X48: =IF(W48=0, " ",W48*14) -> 63 | Y48: 67 | Z48: 268 | AA48: 40.2 | AC48: =IF(OR(L48="", AB48=""), 0, IF(L48="Découverte", KPI!$F$2, IF(L48="Essentiel", KPI!$F$3, IF(L48="Premium", KPI!$F$4, 0) ) ) ) -> 0 | AD48: {=IF(F48="", "", (T48 / 1.21) - IF(L48="Découverte", KPI!$C$2, IF(L48="Essentiel", KPI!$C$3, IF(L48="Premium", KPI!$C$4, 0) ) ) - N(X48) - N(AA48) - N(AC48) - IFERROR(INDEX(Stats!$G:$G, MATCH(DATE(YEAR(R48), MONTH(R48), 1), Stats!$A:$A, 0)), 35) )} -> 240.37438 | AH48: 3ml303s1308fupf8iltv08slf4@google.com | AI48: OK 2025-12-01 19:07 | AL48: 2025_0023 | AM48: 2025_0054
A49: Laura Glorieux | B49: laura.glorieux@avocat.be | C49: 320494 87 15 63 | D49: FR | E49: 45870 | F49: 46269 | I49: Chateau d'avondance Rue des chasseurs 29 ,7100 La Louvière | J49: Mariage | L49: Essentiel | M49: 450 | N49: 80 | S49: 150 | T49: 530 | U49: 380 | W49: 4.5 | X49: =IF(W49=0, " ",W49*14) -> 63 | Y49: 60 | Z49: 240 | AA49: 36 | AC49: =IF(OR(L49="", AB49=""), 0, IF(L49="Découverte", KPI!$F$2, IF(L49="Essentiel", KPI!$F$3, IF(L49="Premium", KPI!$F$4, 0) ) ) ) -> 0 | AD49: {=IF(F49="", "", (T49 / 1.21) - IF(L49="Découverte", KPI!$C$2, IF(L49="Essentiel", KPI!$C$3, IF(L49="Premium", KPI!$C$4, 0) ) ) - N(X49) - N(AA49) - N(AC49) - IFERROR(INDEX(Stats!$G:$G, MATCH(DATE(YEAR(R49), MONTH(R49), 1), Stats!$A:$A, 0)), 35) )} -> 257.76653 | AH49: 8ku6mjc9gq3j7023nr9celor8g@google.com | AI49: OK 2025-12-01 18:57 | AL49: 2025_0040
A50: Vanessa Vanvlaenderen | B50: Vanessavvldn@gmail.com | C50: 320471 91 30 77 | D50: FR | E50: 45870 | F50: 46249 | I50: Dilbeek | J50: Mariage | L50: Premium | M50: 500 | S50: 150 | T50: 500 | U50: 350 | W50: 2 | X50: =IF(W50=0, " ",W50*14) -> 28 | Y50: 4 | Z50: 16 | AA50: 2.4 | AC50: =IF(OR(L50="", AB50=""), 0, IF(L50="Découverte", KPI!$F$2, IF(L50="Essentiel", KPI!$F$3, IF(L50="Premium", KPI!$F$4, 0) ) ) ) -> 0 | AD50: {=IF(F50="", "", (T50 / 1.21) - IF(L50="Découverte", KPI!$C$2, IF(L50="Essentiel", KPI!$C$3, IF(L50="Premium", KPI!$C$4, 0) ) ) - N(X50) - N(AA50) - N(AC50) - IFERROR(INDEX(Stats!$G:$G, MATCH(DATE(YEAR(R50), MONTH(R50), 1), Stats!$A:$A, 0)), 35) )} -> 255.32314 | AH50: hmjbc3gm1nmak838bnm3uviuug@google.com | AI50: OK 2025-11-22 13:38
A51: Allemeersch Océane | B51: oceaneallemeersch@outlook.com | C51: 320471 79 85 24 | D51: FR | E51: 45870 | F51: 46235 | J51: Mariage | L51: Premium | M51: 500 | N51: 100 | S51: 0 | T51: 600 | U51: 600 | X51: =IF(W51=0, " ",W51*14) | Z51: =IF(Y51=0,"", Y51 * 4) | AA51: =IF(Z51=0,"", Z51 * 0.15) -> 0 | AC51: =IF(OR(L51="", AB51=""), 0, IF(L51="Découverte", KPI!$F$2, IF(L51="Essentiel", KPI!$F$3, IF(L51="Premium", KPI!$F$4, 0) ) ) ) -> 0 | AD51: {=IF(F51="", "", (T51 / 1.21) - IF(L51="Découverte", KPI!$C$2, IF(L51="Essentiel", KPI!$C$3, IF(L51="Premium", KPI!$C$4, 0) ) ) - N(X51) - N(AA51) - N(AC51) - IFERROR(INDEX(Stats!$G:$G, MATCH(DATE(YEAR(R51), MONTH(R51), 1), Stats!$A:$A, 0)), 35) )} -> 368.36777 | AH51: u6jrtejugh1b90rt481gicqv2s@google.com | AI51: OK 2025-11-21 21:19
A52: Leatitia Finet | B52: titafinet@hotmail.com | C52: 320471 74 41 70 | D52: FR | E52: 45870 | F52: 46164 | I52: Rue du Soir Paisible 2, 4540 Amay | J52: Mariage | L52: Essentiel | M52: 450 | N52: 90 | S52: 0 | T52: 540 | U52: 540 | W52: 7 | X52: =IF(W52=0, " ",W52*14) -> 98 | Y52: 99 | Z52: 396 | AA52: 59.4 | AC52: =IF(OR(L52="", AB52=""), 0, IF(L52="Découverte", KPI!$F$2, IF(L52="Essentiel", KPI!$F$3, IF(L52="Premium", KPI!$F$4, 0) ) ) ) -> 0 | AD52: {=IF(F52="", "", (T52 / 1.21) - IF(L52="Découverte", KPI!$C$2, IF(L52="Essentiel", KPI!$C$3, IF(L52="Premium", KPI!$C$4, 0) ) ) - N(X52) - N(AA52) - N(AC52) - IFERROR(INDEX(Stats!$G:$G, MATCH(DATE(YEAR(R52), MONTH(R52), 1), Stats!$A:$A, 0)), 35) )} -> 207.63099 | AH52: 0sen6bg9q5i2e8h6ll3e6ccn7s@google.com | AI52: OK 2025-11-22 13:38
A53: Vanessa Altruy | B53: altruy.vanessa@hotmail.com | C53: 32488157867 | D53: FR | E53: 45870 | F53: 46223 | G53: 0.83333333 | H53: 0.95833333 | I53: Boulevard de la paix 2, Auchel | J53: Mariage | L53: Premium | M53: 400 | N53: 100 | R53: 45930 | S53: 150 | T53: 500 | U53: 350 | W53: 9 | X53: =IF(W53=0, " ",W53*14) -> 126 | Y53: 170 | Z53: 680 | AA53: 102 | AC53: =IF(OR(L53="", AB53=""), 0, IF(L53="Découverte", KPI!$F$2, IF(L53="Essentiel", KPI!$F$3, IF(L53="Premium", KPI!$F$4, 0) ) ) ) -> 0 | AD53: {=IF(F53="", "", (T53 / 1.21) - IF(L53="Découverte", KPI!$C$2, IF(L53="Essentiel", KPI!$C$3, IF(L53="Premium", KPI!$C$4, 0) ) ) - N(X53) - N(AA53) - N(AC53) - IFERROR(INDEX(Stats!$G:$G, MATCH(DATE(YEAR(R53), MONTH(R53), 1), Stats!$A:$A, 0)), 35) )} -> 60.173807 | AG53: dcr06efnph0crb67ivt3d400r4@google,com | AH53: q3f8e829u70b0q296v1hhm3bls@google.com | AI53: OK 2025-12-01 18:46 | AL53: 2025_0077
A54: Stéphanie Ferrara | B54: kevinmoraux@hotmail.com | C54: 32477938698 | D54: NL | E54: 45870 | F54: 46046 | I54: Koeweideblock 4, 1485 Merchtem | L54: Premium | M54: 450 | N54: 50 | R54: 45896 | S54: 0 | T54: 500 | U54: 500 | W54: 3 | X54: =IF(W54=0, " ",W54*14) -> 42 | Y54: 18 | Z54: 72 | AA54: 10.8 | AC54: =IF(OR(L54="", AB54=""), 0, IF(L54="Découverte", KPI!$F$2, IF(L54="Essentiel", KPI!$F$3, IF(L54="Premium", KPI!$F$4, 0) ) ) ) -> 0 | AD54: {=IF(F54="", "", (T54 / 1.21) - IF(L54="Découverte", KPI!$C$2, IF(L54="Essentiel", KPI!$C$3, IF(L54="Premium", KPI!$C$4, 0) ) ) - N(X54) - N(AA54) - N(AC54) - IFERROR(INDEX(Stats!$G:$G, MATCH(DATE(YEAR(R54), MONTH(R54), 1), Stats!$A:$A, 0)), 35) )} -> 232.92314 | AH54: hm3dr8h985lnn0ojbeja21h16o@google.com | AI54: OK 2025-12-01 18:55 | AL54: 2025_0051
A55: Maria & Walter | B55: nettodelmonte@hotmail.com | C55: 32476360841 | D55: FR | E55: 45870 | F55: 46018 | I55: Perksesteenweg 37, 1820 Melsbroek | L55: Essentiel | M55: 450 | N55: 50 | R55: 45926 | S55: 150 | T55: 500 | U55: 350 | V55: Mouad | W55: 3 | X55: 70 | Y55: 26 | Z55: 104 | AA55: 15.6 | AC55: =IF(OR(L55="", AB55=""), 0, IF(L55="Découverte", KPI!$F$2, IF(L55="Essentiel", KPI!$F$3, IF(L55="Premium", KPI!$F$4, 0) ) ) ) -> 0 | AD55: {=IF(F55="", "", (T55 / 1.21) - IF(L55="Découverte", KPI!$C$2, IF(L55="Essentiel", KPI!$C$3, IF(L55="Premium", KPI!$C$4, 0) ) ) - N(X55) - N(AA55) - N(AC55) - IFERROR(INDEX(Stats!$G:$G, MATCH(DATE(YEAR(R55), MONTH(R55), 1), Stats!$A:$A, 0)), 35) )} -> 248.82381 | AH55: uj423ig8dqjuobtr4j2rj0i384@google.com | AI55: OK 2026-01-02 09:35 | AJ55: Reminder Sent | AL55: 2025_0069 | AM55: 2026_0001
A56: Catherine | B56: catherinedutron0506@gmail.com | C56: 32468362964 | D56: FR | E56: 45870 | F56: 45940 | I56: Rue Emile Vandervelde 275, 6534 Thuin | L56: Premium | M56: 500 | N56: 80 | S56: 0 | T56: 580 | U56: 580 | V56: Abdel | W56: 5 | X56: 70 | Y56: 76 | Z56: 304 | AA56: 45.6 | AC56: =IF(OR(L56="", AB56=""), 0, IF(L56="Découverte", KPI!$F$2, IF(L56="Essentiel", KPI!$F$3, IF(L56="Premium", KPI!$F$4, 0) ) ) ) -> 0 | AD56: {=IF(F56="", "", (T56 / 1.21) - IF(L56="Découverte", KPI!$C$2, IF(L56="Essentiel", KPI!$C$3, IF(L56="Premium", KPI!$C$4, 0) ) ) - N(X56) - N(AA56) - N(AC56) - IFERROR(INDEX(Stats!$G:$G, MATCH(DATE(YEAR(R56), MONTH(R56), 1), Stats!$A:$A, 0)), 35) )} -> 236.23884 | AH56: 04libqmp5897givrr0ud0ciadc@google.com | AI56: OK 2025-12-01 19:11 | AL56: 2025_0012 | AM56: 2025_0092
A57: Eline Le Dieu | B57: eline.ledieu@hotmail.be | C57: 32489438210 | D57: FR | E57: 45870 | F57: 45934 | I57: Salle Praesenti à Saintes - Rue de tubize 1, 1480 | J57: Mariage | L57: Premium | M57: 500 | N57: 50 | S57: 150 | T57: 550 | U57: 400 | V57: Abdel | W57: 3 | X57: 70 | Y57: 28 | Z57: 112 | AA57: 16.8 | AC57: =IF(OR(L57="", AB57=""), 0, IF(L57="Découverte", KPI!$F$2, IF(L57="Essentiel", KPI!$F$3, IF(L57="Premium", KPI!$F$4, 0) ) ) ) -> 0 | AD57: {=IF(F57="", "", (T57 / 1.21) - IF(L57="Découverte", KPI!$C$2, IF(L57="Essentiel", KPI!$C$3, IF(L57="Premium", KPI!$C$4, 0) ) ) - N(X57) - N(AA57) - N(AC57) - IFERROR(INDEX(Stats!$G:$G, MATCH(DATE(YEAR(R57), MONTH(R57), 1), Stats!$A:$A, 0)), 35) )} -> 240.24545 | AH57: ku6fu7r6mm9hsbm56r4nkg5a68@google.com | AI57: OK 2025-12-01 19:13 | AL57: 2025_0006 | AM57: 2025_0081
A58: Aljbek Sheripov | B58: r783@hotmail.com | C58: 32496393928 | D58: FR | E58: 45870 | F58: 45934 | I58: Rue du village 50, 5380 Franc-Waret | J58: Mariage | L58: Essentiel | M58: 450 | N58: 110 | S58: 0 | T58: 560 | U58: 560 | V58: Abdel | W58: 5.5 | X58: 70 | Y58: 78 | Z58: 312 | AA58: 46.8 | AC58: =IF(OR(L58="", AB58=""), 0, IF(L58="Découverte", KPI!$F$2, IF(L58="Essentiel", KPI!$F$3, IF(L58="Premium", KPI!$F$4, 0) ) ) ) -> 0 | AD58: {=IF(F58="", "", (T58 / 1.21) - IF(L58="Découverte", KPI!$C$2, IF(L58="Essentiel", KPI!$C$3, IF(L58="Premium", KPI!$C$4, 0) ) ) - N(X58) - N(AA58) - N(AC58) - IFERROR(INDEX(Stats!$G:$G, MATCH(DATE(YEAR(R58), MONTH(R58), 1), Stats!$A:$A, 0)), 35) )} -> 264.75992 | AH58: e9h5ebuvuks5t0cct63mr66oao@google.com | AI58: OK 2025-12-01 19:05 | AL58: 2025_0028 | AM58: 2025_0082
A59: Ahmed Secteur7 | C59: 33635172271 | D59: FR | E59: 45870 | F59: 45927 | I59: La bourse Bruxelles | J59: B2B | L59: Premium | M59: 500 | Q59: 100 | S59: 0 | T59: 600 | U59: 600 | V59: Abdel | W59: 2.5 | X59: 70 | Y59: 5 | Z59: 20 | AA59: 3 | AC59: =IF(OR(L59="", AB59=""), 0, IF(L59="Découverte", KPI!$F$2, IF(L59="Essentiel", KPI!$F$3, IF(L59="Premium", KPI!$F$4, 0) ) ) ) -> 0 | AD59: {=IF(F59="", "", (T59 / 1.21) - IF(L59="Découverte", KPI!$C$2, IF(L59="Essentiel", KPI!$C$3, IF(L59="Premium", KPI!$C$4, 0) ) ) - N(X59) - N(AA59) - N(AC59) - IFERROR(INDEX(Stats!$G:$G, MATCH(DATE(YEAR(R59), MONTH(R59), 1), Stats!$A:$A, 0)), 35) )} -> 295.36777 | AH59: 4t6kcss884f03uce4h5v3na5vg@google.com | AI59: OK 2025-12-01 18:48 | AM59: 2025_0072
A60: Happe Holyanna | B60: holyanna.happe2@gmail.com | C60: 33661542072 | D60: FR | E60: 45870 | F60: 45920 | I60: Pl, de bourgogne 1, 7730 Estaimpuis | J60: Mariage | L60: Essentiel | M60: 450 | N60: 120 | S60: 150 | T60: 570 | U60: 420 | V60: Abdel | W60: 6 | X60: 70 | Y60: 96 | Z60: 384 | AA60: 57.6 | AC60: =IF(OR(L60="", AB60=""), 0, IF(L60="Découverte", KPI!$F$2, IF(L60="Essentiel", KPI!$F$3, IF(L60="Premium", KPI!$F$4, 0) ) ) ) -> 0 | AD60: {=IF(F60="", "", (T60 / 1.21) - IF(L60="Découverte", KPI!$C$2, IF(L60="Essentiel", KPI!$C$3, IF(L60="Premium", KPI!$C$4, 0) ) ) - N(X60) - N(AA60) - N(AC60) - IFERROR(INDEX(Stats!$G:$G, MATCH(DATE(YEAR(R60), MONTH(R60), 1), Stats!$A:$A, 0)), 35) )} -> 262.22438 | AH60: 3t62aq4spgh7cda1c99fbba9fk@google.com | AI60: OK 2025-12-01 19:09 | AL60: 2025_0019 | AM60: 2025_0063
A61: Virginie Fred Perona | B61: peronavirgi@hotmail.com | C61: 32498468057 | D61: FR | E61: 45908 | F61: 46032 | I61: Rue Jules Empain 20, 7170 Manage | J61: Anniversaire | L61: Découverte | M61: 250 | N61: 70 | R61: 45917 | S61: 150 | T61: 320 | U61: 170 | V61: Abdel | W61: 4 | X61: =IF(W61=0, " ",W61*14) -> 56 | Y61: 49 | Z61: 196 | AA61: 29.4 | AC61: =IF(OR(L61="", AB61=""), 0, IF(L61="Découverte", KPI!$F$2, IF(L61="Essentiel", KPI!$F$3, IF(L61="Premium", KPI!$F$4, 0) ) ) ) -> 0 | AD61: {=IF(F61="", "", (T61 / 1.21) - IF(L61="Découverte", KPI!$C$2, IF(L61="Essentiel", KPI!$C$3, IF(L61="Premium", KPI!$C$4, 0) ) ) - N(X61) - N(AA61) - N(AC61) - IFERROR(INDEX(Stats!$G:$G, MATCH(DATE(YEAR(R61), MONTH(R61), 1), Stats!$A:$A, 0)), 35) )} -> 123.39348 | AH61: 2utu0j721jih61poeqaml13l0c@google.com | AI61: OK 2026-01-09 19:45 | AJ61: Reminder Sent | AL61: 2025_0061 | AM61: 2026_0004
A62: Mohamed | B62: boghabamomo@gmail.com | C62: 32486609221 | D62: FR | E62: 45912 | F62: 45935 | I62: Bruxelles | J62: Mariage | L62: Découverte | M62: 250 | N62: 50 | S62: 150 | T62: 300 | U62: 150 | V62: Abdel | W62: 2.5 | X62: 70 | Y62: 7 | Z62: 28 | AA62: 4.2 | AC62: =IF(OR(L62="", AB62=""), 0, IF(L62="Découverte", KPI!$F$2, IF(L62="Essentiel", KPI!$F$3, IF(L62="Premium", KPI!$F$4, 0) ) ) ) -> 0 | AD62: {=IF(F62="", "", (T62 / 1.21) - IF(L62="Découverte", KPI!$C$2, IF(L62="Essentiel", KPI!$C$3, IF(L62="Premium", KPI!$C$4, 0) ) ) - N(X62) - N(AA62) - N(AC62) - IFERROR(INDEX(Stats!$G:$G, MATCH(DATE(YEAR(R62), MONTH(R62), 1), Stats!$A:$A, 0)), 35) )} -> 115.61388 | AH62: 2v2d8lefl71n8scfnk5v6975os@google.com | AI62: OK 2025-12-01 18:45 | AL62: 2025_0083 | AM62: 2025_0084
A63: Ludovic | B63: hanlud@hotmail.com | C63: 32477834109 | D63: FR | E63: 45913 | F63: 45934 | I63: 6534 Thuin | J63: Mariage | L63: Découverte | M63: 250 | N63: 75 | R63: 45921 | S63: 150 | T63: 325 | U63: 175 | V63: Abdel | W63: 5 | X63: 70 | Y63: 76 | Z63: 304 | AA63: 45.6 | AC63: =IF(OR(L63="", AB63=""), 0, IF(L63="Découverte", KPI!$F$2, IF(L63="Essentiel", KPI!$F$3, IF(L63="Premium", KPI!$F$4, 0) ) ) ) -> 0 | AD63: {=IF(F63="", "", (T63 / 1.21) - IF(L63="Découverte", KPI!$C$2, IF(L63="Essentiel", KPI!$C$3, IF(L63="Premium", KPI!$C$4, 0) ) ) - N(X63) - N(AA63) - N(AC63) - IFERROR(INDEX(Stats!$G:$G, MATCH(DATE(YEAR(R63), MONTH(R63), 1), Stats!$A:$A, 0)), 35) )} -> 97.325708 | AH63: 7vrlh5c1t3s4ec293bqscadvrc@google.com | AI63: OK 2025-12-01 18:51 | AL63: 2025_0064 | AM63: 2025_0080
A64: Marie-Charlotte | B64: m0243243c.112m@gmail.com | C64: 32455103223 | D64: FR | E64: 45914 | F64: 46277 | I64: Namur | J64: Mariage | L64: Essentiel | M64: 350 | N64: 75 | R64: 45926 | S64: 150 | T64: 425 | U64: 275 | W64: 5.5 | X64: =IF(W64=0, " ",W64*14) -> 77 | Y64: 77 | Z64: 308 | AA64: 46.2 | AC64: =IF(OR(L64="", AB64=""), 0, IF(L64="Découverte", KPI!$F$2, IF(L64="Essentiel", KPI!$F$3, IF(L64="Premium", KPI!$F$4, 0) ) ) ) -> 0 | AD64: {=IF(F64="", "", (T64 / 1.21) - IF(L64="Découverte", KPI!$C$2, IF(L64="Essentiel", KPI!$C$3, IF(L64="Premium", KPI!$C$4, 0) ) ) - N(X64) - N(AA64) - N(AC64) - IFERROR(INDEX(Stats!$G:$G, MATCH(DATE(YEAR(R64), MONTH(R64), 1), Stats!$A:$A, 0)), 35) )} -> 149.24034 | AH64: gtnnob709nb06ejai97kioei08@google.com | AI64: OK 2025-12-01 18:49 | AL64: 2025_0070
A65: Elodie | B65: collet-elodie@hotmail.com | C65: 32479743507 | D65: FR | E65: 45915 | F65: 46186 | I65: coq boulevard du coq n 44 la Louvière 7100 | J65: Mariage | K65: 150 | L65: Essentiel | M65: 350 | N65: 70 | R65: 45917 | S65: 150 | T65: 420 | U65: 270 | W65: 4 | X65: =IF(W65=0, " ",W65*14) -> 56 | Y65: 58 | Z65: 232 | AA65: 34.8 | AC65: =IF(OR(L65="", AB65=""), 0, IF(L65="Découverte", KPI!$F$2, IF(L65="Essentiel", KPI!$F$3, IF(L65="Premium", KPI!$F$4, 0) ) ) ) -> 0 | AD65: {=IF(F65="", "", (T65 / 1.21) - IF(L65="Découverte", KPI!$C$2, IF(L65="Essentiel", KPI!$C$3, IF(L65="Premium", KPI!$C$4, 0) ) ) - N(X65) - N(AA65) - N(AC65) - IFERROR(INDEX(Stats!$G:$G, MATCH(DATE(YEAR(R65), MONTH(R65), 1), Stats!$A:$A, 0)), 35) )} -> 177.5081 | AH65: bdv8q2kbu97n112esi660254f4@google.com | AI65: OK 2025-12-01 18:52 | AL65: 2025_0060
A66: Marine | B66: gvn.marine@gmail.com | C66: 33647588181 | D66: FR | E66: 45916 | F66: 46256 | I66: Arras | J66: Mariage | K66: 180 | L66: Essentiel | M66: 350 | N66: 70 | R66: 45916 | S66: 150 | T66: 420 | U66: 270 | W66: 8 | X66: =IF(W66=0, " ",W66*14) -> 112 | Y66: 153 | Z66: 612 | AA66: 91.8 | AC66: =IF(OR(L66="", AB66=""), 0, IF(L66="Découverte", KPI!$F$2, IF(L66="Essentiel", KPI!$F$3, IF(L66="Premium", KPI!$F$4, 0) ) ) ) -> 0 | AD66: {=IF(F66="", "", (T66 / 1.21) - IF(L66="Découverte", KPI!$C$2, IF(L66="Essentiel", KPI!$C$3, IF(L66="Premium", KPI!$C$4, 0) ) ) - N(X66) - N(AA66) - N(AC66) - IFERROR(INDEX(Stats!$G:$G, MATCH(DATE(YEAR(R66), MONTH(R66), 1), Stats!$A:$A, 0)), 35) )} -> 64.508105 | AH66: nube6qeu7mkkt1d1qccfa3j7js@google.com | AI66: OK 2025-12-01 18:50 | AL66: 2025_0066
A67: Rani | B67: rani_diependaele@hotmail.com | C67: 32497656334 | D67: FR | E67: 45917 | F67: 46227 | I67: Ophasselt | J67: Mariage | K67: 140 | L67: Essentiel | M67: 450 | N67: 50 | R67: 45927 | S67: 150 | T67: 500 | U67: 350 | W67: 4 | X67: =IF(W67=0, " ",W67*14) -> 56 | Y67: 42 | Z67: 168 | AA67: 25.2 | AC67: =IF(OR(L67="", AB67=""), 0, IF(L67="Découverte", KPI!$F$2, IF(L67="Essentiel", KPI!$F$3, IF(L67="Premium", KPI!$F$4, 0) ) ) ) -> 0 | AD67: {=IF(F67="", "", (T67 / 1.21) - IF(L67="Découverte", KPI!$C$2, IF(L67="Essentiel", KPI!$C$3, IF(L67="Premium", KPI!$C$4, 0) ) ) - N(X67) - N(AA67) - N(AC67) - IFERROR(INDEX(Stats!$G:$G, MATCH(DATE(YEAR(R67), MONTH(R67), 1), Stats!$A:$A, 0)), 35) )} -> 253.22381 | AH67: mcjh2l6f9plsmrt68rr8q9ggjs@google.com | AI67: OK 2025-12-01 18:47 | AL67: 2025_0073
A68: Matilde Gravano | B68: matilde.gravano@gmail.com | C68: 32477816691 | D68: FR | E68: 45917 | F68: 46158 | I68: Beaurieux court saint etienne Belgique | J68: Mariage | K68: 80 | L68: Découverte | M68: 250 | N68: 70 | R68: 45932 | S68: 150 | T68: 320 | U68: 170 | W68: 4 | X68: =IF(W68=0, " ",W68*14) -> 56 | Y68: 55 | Z68: 220 | AA68: 33 | AC68: =IF(OR(L68="", AB68=""), 0, IF(L68="Découverte", KPI!$F$2, IF(L68="Essentiel", KPI!$F$3, IF(L68="Premium", KPI!$F$4, 0) ) ) ) -> 0 | AD68: {=IF(F68="", "", (T68 / 1.21) - IF(L68="Découverte", KPI!$C$2, IF(L68="Essentiel", KPI!$C$3, IF(L68="Premium", KPI!$C$4, 0) ) ) - N(X68) - N(AA68) - N(AC68) - IFERROR(INDEX(Stats!$G:$G, MATCH(DATE(YEAR(R68), MONTH(R68), 1), Stats!$A:$A, 0)), 35) )} -> 110.01977 | AH68: q6vlmgvhkrk2gpak5mmuvdvflg@google.com | AI68: OK 2025-12-01 18:43 | AL68: 2025_0087
A69: Salma Feraaouni | B69: salma.feraaouni@hotmail.com | C69: 32491118984 | D69: FR | E69: 45920 | F69: 46136 | I69: Saint-Vaast, 7100 La Louvière | J69: Mariage | K69: 50 | L69: Découverte | M69: 250 | N69: 90 | R69: 45925 | S69: 150 | T69: 340 | U69: 190 | W69: 4 | X69: =IF(W69=0, " ",W69*14) -> 56 | Y69: 58 | Z69: 232 | AA69: 34.8 | AC69: =IF(OR(L69="", AB69=""), 0, IF(L69="Découverte", KPI!$F$2, IF(L69="Essentiel", KPI!$F$3, IF(L69="Premium", KPI!$F$4, 0) ) ) ) -> 0 | AD69: {=IF(F69="", "", (T69 / 1.21) - IF(L69="Découverte", KPI!$C$2, IF(L69="Essentiel", KPI!$C$3, IF(L69="Premium", KPI!$C$4, 0) ) ) - N(X69) - N(AA69) - N(AC69) - IFERROR(INDEX(Stats!$G:$G, MATCH(DATE(YEAR(R69), MONTH(R69), 1), Stats!$A:$A, 0)), 35) )} -> 134.5224 | AH69: eo6mulcdtnal9f8hfvid322mfo@google.com | AI69: OK 2025-12-01 18:50 | AL69: 2025_0067
A70: Jihane Najem | B70: jihane.njm@gmail.com | C70: 32494325456 | D70: FR | E70: 45920 | F70: 46137 | I70: Bruxelles | J70: Mariage | K70: 300 | L70: Essentiel | M70: 350 | N70: 90 | R70: 45921 | S70: 150 | T70: 440 | U70: 290 | W70: 2.5 | X70: =IF(W70=0, " ",W70*14) -> 35 | Y70: 7 | Z70: 28 | AA70: 4.2 | AC70: =IF(OR(L70="", AB70=""), 0, IF(L70="Découverte", KPI!$F$2, IF(L70="Essentiel", KPI!$F$3, IF(L70="Premium", KPI!$F$4, 0) ) ) ) -> 0 | AD70: {=IF(F70="", "", (T70 / 1.21) - IF(L70="Découverte", KPI!$C$2, IF(L70="Essentiel", KPI!$C$3, IF(L70="Premium", KPI!$C$4, 0) ) ) - N(X70) - N(AA70) - N(AC70) - IFERROR(INDEX(Stats!$G:$G, MATCH(DATE(YEAR(R70), MONTH(R70), 1), Stats!$A:$A, 0)), 35) )} -> 245.63703 | AH70: pd64uv86lbgkis2imgssjpqjoo@google.com | AI70: OK 2025-12-01 18:51 | AL70: 2025_0065
A71: Raphaelle Nino | B71: raphthib@hotmail.com | C71: 32483412150 | D71: FR | E71: 45921 | F71: 46242 | I71: Jurbise | J71: Mariage | K71: 100 | L71: Essentiel | M71: 350 | N71: 90 | R71: 45929 | S71: 150 | T71: 440 | U71: 290 | W71: 5 | X71: =IF(W71=0, " ",W71*14) -> 70 | Y71: 72 | Z71: 288 | AA71: 43.2 | AC71: =IF(OR(L71="", AB71=""), 0, IF(L71="Découverte", KPI!$F$2, IF(L71="Essentiel", KPI!$F$3, IF(L71="Premium", KPI!$F$4, 0) ) ) ) -> 0 | AD71: {=IF(F71="", "", (T71 / 1.21) - IF(L71="Découverte", KPI!$C$2, IF(L71="Essentiel", KPI!$C$3, IF(L71="Premium", KPI!$C$4, 0) ) ) - N(X71) - N(AA71) - N(AC71) - IFERROR(INDEX(Stats!$G:$G, MATCH(DATE(YEAR(R71), MONTH(R71), 1), Stats!$A:$A, 0)), 35) )} -> 171.63703 | AH71: h7lguo445nvnlereinct5dedls@google.com | AI71: OK 2025-12-01 18:48 | AL71: 2025_0074
A72: Dorine Shops | B72: dorine.shops@icloud.com | D72: FR | E72: 45922 | F72: 46368 | I72: Flaumont Waubrechie | J72: Mariage | L72: Premium | M72: 450 | N72: 90 | R72: 45927 | S72: 150 | T72: 540 | U72: 390 | W72: 7.5 | X72: =IF(W72=0, " ",W72*14) -> 105 | Y72: 115 | Z72: 460 | AA72: 69 | AC72: =IF(OR(L72="", AB72=""), 0, IF(L72="Découverte", KPI!$F$2, IF(L72="Essentiel", KPI!$F$3, IF(L72="Premium", KPI!$F$4, 0) ) ) ) -> 0 | AD72: {=IF(F72="", "", (T72 / 1.21) - IF(L72="Découverte", KPI!$C$2, IF(L72="Essentiel", KPI!$C$3, IF(L72="Premium", KPI!$C$4, 0) ) ) - N(X72) - N(AA72) - N(AC72) - IFERROR(INDEX(Stats!$G:$G, MATCH(DATE(YEAR(R72), MONTH(R72), 1), Stats!$A:$A, 0)), 35) )} -> 147.23166 | AH72: 4kjm76rp1p9o4u8d78a250f6qc@google.com | AI72: OK 2025-12-01 18:46 | AL72: 2025_0079
A73: Tifany SINNAEVE | B73: tifa_360@hotmail.com | C73: 32488157867 | D73: FR | E73: 45922 | F73: 46221 | I73: Courcelles | J73: Mariage | K73: 60 | L73: Découverte | M73: 250 | N73: 90 | R73: 45930 | S73: 150 | T73: 340 | U73: 190 | V73: Mouad | W73: 4 | X73: =IF(W73=0, " ",W73*14) -> 56 | Y73: 57 | Z73: 228 | AA73: 34.2 | AC73: =IF(OR(L73="", AB73=""), 0, IF(L73="Découverte", KPI!$F$2, IF(L73="Essentiel", KPI!$F$3, IF(L73="Premium", KPI!$F$4, 0) ) ) ) -> 0 | AD73: {=IF(F73="", "", (T73 / 1.21) - IF(L73="Découverte", KPI!$C$2, IF(L73="Essentiel", KPI!$C$3, IF(L73="Premium", KPI!$C$4, 0) ) ) - N(X73) - N(AA73) - N(AC73) - IFERROR(INDEX(Stats!$G:$G, MATCH(DATE(YEAR(R73), MONTH(R73), 1), Stats!$A:$A, 0)), 35) )} -> 135.1224 | AH73: 1ipg47249bribmdbqek13icj0o@google.com | AI73: OK 2025-12-24 13:59 | AL73: 2025_0075
A74: Sophie Willems | B74: sophiewillems20@gmail.com | C74: 32479956405 | D74: FR | E74: 45922 | F74: 46256 | I74: Battice | J74: Mariage | K74: 200 | L74: Premium | M74: 450 | N74: 90 | R74: 45931 | S74: 150 | T74: 540 | U74: 390 | W74: 7 | X74: =IF(W74=0, " ",W74*14) -> 98 | Y74: 124 | Z74: 496 | AA74: 74.4 | AC74: =IF(OR(L74="", AB74=""), 0, IF(L74="Découverte", KPI!$F$2, IF(L74="Essentiel", KPI!$F$3, IF(L74="Premium", KPI!$F$4, 0) ) ) ) -> 0 | AD74: {=IF(F74="", "", (T74 / 1.21) - IF(L74="Découverte", KPI!$C$2, IF(L74="Essentiel", KPI!$C$3, IF(L74="Premium", KPI!$C$4, 0) ) ) - N(X74) - N(AA74) - N(AC74) - IFERROR(INDEX(Stats!$G:$G, MATCH(DATE(YEAR(R74), MONTH(R74), 1), Stats!$A:$A, 0)), 35) )} -> 139.05795 | AH74: vcou1mlq6qfdohobrdgeuckfhk@google.com | AI74: OK 2025-12-01 18:46 | AL74: 2025_0078
A75: Mandelier Cathy | B75: cathy.manderlier@brucity.education | D75: FR | E75: 45923 | F75: 45940 | I75: La bourse Bruxelles | J75: B2B | L75: Premium | M75: 450 | P75: 5 | Q75: 150 | S75: 0 | T75: 600 | U75: 600 | V75: Abdel | W75: 2.5 | X75: 70 | Y75: 5 | Z75: 20 | AA75: 3 | AC75: =IF(OR(L75="", AB75=""), 0, IF(L75="Découverte", KPI!$F$2, IF(L75="Essentiel", KPI!$F$3, IF(L75="Premium", KPI!$F$4, 0) ) ) ) -> 0 | AD75: {=IF(F75="", "", (T75 / 1.21) - IF(L75="Découverte", KPI!$C$2, IF(L75="Essentiel", KPI!$C$3, IF(L75="Premium", KPI!$C$4, 0) ) ) - N(X75) - N(AA75) - N(AC75) - IFERROR(INDEX(Stats!$G:$G, MATCH(DATE(YEAR(R75), MONTH(R75), 1), Stats!$A:$A, 0)), 35) )} -> 295.36777 | AH75: hnm6n0ks0vp8fueknspgr5r04g@google.com | AI75: OK 2025-12-01 18:36 | AM75: 2025_0101
A76: Fathy Vercamer | B76: fathy.vercamer@hilton.com | D76: FR | E76: 45924 | F76: 45926 | I76: Carrefour de l’europe 3, 1000 bruxelles | J76: B2B | L76: Découverte | M76: 300 | S76: 0 | T76: 363 | U76: 363 | V76: Abdel | W76: 2.5 | X76: 70 | Y76: 6 | Z76: 24 | AA76: 3.6 | AC76: =IF(OR(L76="", AB76=""), 0, IF(L76="Découverte", KPI!$F$2, IF(L76="Essentiel", KPI!$F$3, IF(L76="Premium", KPI!$F$4, 0) ) ) ) -> 0 | AD76: {=IF(F76="", "", (T76 / 1.21) - IF(L76="Découverte", KPI!$C$2, IF(L76="Essentiel", KPI!$C$3, IF(L76="Premium", KPI!$C$4, 0) ) ) - N(X76) - N(AA76) - N(AC76) - IFERROR(INDEX(Stats!$G:$G, MATCH(DATE(YEAR(R76), MONTH(R76), 1), Stats!$A:$A, 0)), 35) )} -> 168.28 | AH76: evr52db53s1ikk83a1n24vjjhc@google.com | AI76: OK 2025-12-01 19:35 | AM76: 2025_0071
A77: Gioeli Pina | B77: gioeli.demaret@gmail.com | D77: FR | E77: 45924 | F77: 46191 | I77: La Louvière | J77: Mariage | K77: 120 | L77: Premium | M77: 450 | N77: 70 | R77: 45925 | S77: 150 | T77: 520 | U77: 370 | W77: 4 | X77: =IF(W77=0, " ",W77*14) -> 56 | Y77: 53 | Z77: 212 | AA77: 31.8 | AC77: =IF(OR(L77="", AB77=""), 0, IF(L77="Découverte", KPI!$F$2, IF(L77="Essentiel", KPI!$F$3, IF(L77="Premium", KPI!$F$4, 0) ) ) ) -> 0 | AD77: {=IF(F77="", "", (T77 / 1.21) - IF(L77="Découverte", KPI!$C$2, IF(L77="Essentiel", KPI!$C$3, IF(L77="Premium", KPI!$C$4, 0) ) ) - N(X77) - N(AA77) - N(AC77) - IFERROR(INDEX(Stats!$G:$G, MATCH(DATE(YEAR(R77), MONTH(R77), 1), Stats!$A:$A, 0)), 35) )} -> 216.90273 | AH77: vd15u73hjak1upa93o96tm6ni4@google.com | AI77: OK 2025-12-01 18:50 | AL77: 2025_0068
A78: Cindy Vandenrewegs | B78: cindyasmine212@gmail.com | C78: 32465650382 | D78: FR | E78: 45924 | F78: 46228 | I78: Flemalle | J78: Mariage | K78: 70 | L78: Essentiel | M78: 350 | N78: 70 | R78: 45930 | S78: 150 | T78: 420 | U78: 270 | W78: 6.5 | X78: =IF(W78=0, " ",W78*14) -> 91 | Y78: 108 | Z78: 432 | AA78: 64.8 | AC78: =IF(OR(L78="", AB78=""), 0, IF(L78="Découverte", KPI!$F$2, IF(L78="Essentiel", KPI!$F$3, IF(L78="Premium", KPI!$F$4, 0) ) ) ) -> 0 | AD78: {=IF(F78="", "", (T78 / 1.21) - IF(L78="Découverte", KPI!$C$2, IF(L78="Essentiel", KPI!$C$3, IF(L78="Premium", KPI!$C$4, 0) ) ) - N(X78) - N(AA78) - N(AC78) - IFERROR(INDEX(Stats!$G:$G, MATCH(DATE(YEAR(R78), MONTH(R78), 1), Stats!$A:$A, 0)), 35) )} -> 112.5081 | AH78: sfjq9j6bjbmkbun16r0jtoajl0@google.com | AI78: OK 2025-12-01 18:47 | AL78: 2025_0076
A79: Marie Wathelet | B79: marie.wathelet.mw@gmail.com | C79: 32471905609 | D79: FR | E79: 45924 | F79: 46151 | I79: Floreffe | J79: Mariage | K79: 80 | L79: Essentiel | M79: 350 | N79: 90 | R79: 45942 | S79: 150 | T79: 440 | U79: 290 | W79: 5.5 | X79: =IF(W79=0, " ",W79*14) -> 77 | Y79: 85 | Z79: 340 | AA79: 51 | AB79: Maxime | AC79: =IF(OR(L79="", AB79=""), 0, IF(L79="Découverte", KPI!$F$2, IF(L79="Essentiel", KPI!$F$3, IF(L79="Premium", KPI!$F$4, 0) ) ) ) -> 45 | AD79: {=IF(F79="", "", (T79 / 1.21) - IF(L79="Découverte", KPI!$C$2, IF(L79="Essentiel", KPI!$C$3, IF(L79="Premium", KPI!$C$4, 0) ) ) - N(X79) - N(AA79) - N(AC79) - IFERROR(INDEX(Stats!$G:$G, MATCH(DATE(YEAR(R79), MONTH(R79), 1), Stats!$A:$A, 0)), 35) )} -> 102.06332 | AH79: ppm1hnecis9m5k7sqeorqas2ks@google.com | AI79: OK 2025-12-01 18:39 | AL79: 2025_0093
A80: Emma Valis | B80: emmavalis2105@gmail.com | C80: 32478515095 | D80: FR | E80: 45924 | F80: 45990 | I80: Anderlecht | J80: Anniversaire | K80: 50 | L80: Découverte | M80: 250 | N80: 50 | R80: 45936 | S80: 150 | T80: 300 | U80: 150 | V80: Mouad | W80: 2 | X80: =IF(W80=0, " ",W80*14) -> 28 | Y80: 4 | Z80: 16 | AA80: 2.4 | AC80: =IF(OR(L80="", AB80=""), 0, IF(L80="Découverte", KPI!$F$2, IF(L80="Essentiel", KPI!$F$3, IF(L80="Premium", KPI!$F$4, 0) ) ) ) -> 0 | AD80: {=IF(F80="", "", (T80 / 1.21) - IF(L80="Découverte", KPI!$C$2, IF(L80="Essentiel", KPI!$C$3, IF(L80="Premium", KPI!$C$4, 0) ) ) - N(X80) - N(AA80) - N(AC80) - IFERROR(INDEX(Stats!$G:$G, MATCH(DATE(YEAR(R80), MONTH(R80), 1), Stats!$A:$A, 0)), 35) )} -> 152.09084 | AH80: p661f0fgl5qv4piu0ghh5tlfe4@google.com | AI80: OK 2025-12-02 22:06 | AJ80: Link Missing | AL80: 2025_0091 | AM80: 2025_0133
A81: Amandine Begon | B81: loic-begon557@outlook.com | C81: 32494337758 | D81: FR | E81: 45926 | F81: 45961 | I81: Thon-Samson | J81: Anniversaire | K81: 50 | L81: Découverte | M81: 250 | N81: 70 | R81: 45938 | S81: 150 | T81: 320 | U81: 170 | V81: Mouad | W81: 6 | X81: =IF(W81=0, " ",W81*14) -> 84 | Y81: 104 | Z81: =IF(Y81=0,"", Y81 * 4) -> 416 | AA81: =IF(Z81=0, " ", Z81*0.15) -> 62.4 | AC81: =IF(OR(L81="", AB81=""), 0, IF(L81="Découverte", KPI!$F$2, IF(L81="Essentiel", KPI!$F$3, IF(L81="Premium", KPI!$F$4, 0) ) ) ) -> 0 | AD81: {=IF(F81="", "", (T81 / 1.21) - IF(L81="Découverte", KPI!$C$2, IF(L81="Essentiel", KPI!$C$3, IF(L81="Premium", KPI!$C$4, 0) ) ) - N(X81) - N(AA81) - N(AC81) - IFERROR(INDEX(Stats!$G:$G, MATCH(DATE(YEAR(R81), MONTH(R81), 1), Stats!$A:$A, 0)), 35) )} -> 52.619766 | AH81: kncb1df8bge4tncu4r0vgfd7c0@google.com | AI81: OK 2025-12-01 18:43 | AL81: 2025_0086 | AM81: 2025_0111
A82: Morgane Lefebvre | B82: morgane.lefebvre.lhoir1474@gmail.com | C82: 32456791801 | D82: FR | E82: 45927 | F82: 46158 | I82: Nieuwpoort | J82: Mariage | K82: 100 | L82: Découverte | M82: 250 | N82: 90 | R82: 45939 | S82: 150 | T82: 340 | U82: 190 | W82: 6.5 | X82: =IF(W82=0, " ",W82*14) -> 91 | Y82: 125 | Z82: 500 | AA82: 75 | AC82: =IF(OR(L82="", AB82=""), 0, IF(L82="Découverte", KPI!$F$2, IF(L82="Essentiel", KPI!$F$3, IF(L82="Premium", KPI!$F$4, 0) ) ) ) -> 0 | AD82: {=IF(F82="", "", (T82 / 1.21) - IF(L82="Découverte", KPI!$C$2, IF(L82="Essentiel", KPI!$C$3, IF(L82="Premium", KPI!$C$4, 0) ) ) - N(X82) - N(AA82) - N(AC82) - IFERROR(INDEX(Stats!$G:$G, MATCH(DATE(YEAR(R82), MONTH(R82), 1), Stats!$A:$A, 0)), 35) )} -> 49.548692 | AH82: vmupqc92o0ssrb6t1in3ju6a2o@google.com | AI82: OK 2025-12-01 18:40 | AL82: 2025_0089
A83: Sarah Ben Ali | B83: info@okadarchitects.com | C83: 32483359730 | D83: FR | E83: 45929 | F83: 45947 | I83: Château de Ruisbroek, Karel Gilonstraat 15, 1601 Sint-Pieters-Leeuw | J83: B2B | K83: 100 | L83: Découverte | M83: 250 | N83: 70 | R83: 45941 | S83: 150 | T83: 320 | U83: 170 | W83: 2 | X83: =IF(W83=0, " ",W83*14) -> 28 | Y83: 10 | Z83: 40 | AA83: 6 | AC83: =IF(OR(L83="", AB83=""), 0, IF(L83="Découverte", KPI!$F$2, IF(L83="Essentiel", KPI!$F$3, IF(L83="Premium", KPI!$F$4, 0) ) ) ) -> 0 | AD83: {=IF(F83="", "", (T83 / 1.21) - IF(L83="Découverte", KPI!$C$2, IF(L83="Essentiel", KPI!$C$3, IF(L83="Premium", KPI!$C$4, 0) ) ) - N(X83) - N(AA83) - N(AC83) - IFERROR(INDEX(Stats!$G:$G, MATCH(DATE(YEAR(R83), MONTH(R83), 1), Stats!$A:$A, 0)), 35) )} -> 165.01977 | AH83: lod0k5oh5tpve5rcc2iiii9i10@google.com | AI83: OK 2025-12-01 18:37 | AL83: 2025_0098 | AM83: 2025_0099
A84: Myriam Basisua | B84: myriambsa90@gmail.com | C84: 32471011315 | D84: FR | E84: 45929 | F84: 45969 | I84: Bruxelles | J84: Mariage | K84: 300 | L84: Découverte | M84: 250 | N84: 90 | R84: 45940 | S84: 150 | T84: 340 | U84: 190 | V84: Mouad | W84: 3 | X84: =IF(W84=0, " ",W84*14) -> 42 | Y84: 3 | Z84: =IF(Y84=0,"", Y84 * 4) -> 12 | AA84: =IF(Z84=0,"", Z84 * 0.15) -> 1.8 | AC84: =IF(OR(L84="", AB84=""), 0, IF(L84="Découverte", KPI!$F$2, IF(L84="Essentiel", KPI!$F$3, IF(L84="Premium", KPI!$F$4, 0) ) ) ) -> 0 | AD84: {=IF(F84="", "", (T84 / 1.21) - IF(L84="Découverte", KPI!$C$2, IF(L84="Essentiel", KPI!$C$3, IF(L84="Premium", KPI!$C$4, 0) ) ) - N(X84) - N(AA84) - N(AC84) - IFERROR(INDEX(Stats!$G:$G, MATCH(DATE(YEAR(R84), MONTH(R84), 1), Stats!$A:$A, 0)), 35) )} -> 171.74869 | AH84: kpjjq0vbcnb57t4dqd53vb2k34@google.com | AI84: OK 2025-12-01 19:29 | AL84: 2025_0090 | AM84: 2025_0120
A85: Manon Tshikuna | B85: manontsk@hotmail.com | C85: 32492048709 | D85: FR | E85: 45930 | F85: 45955 | I85: Perwez | J85: Mariage | K85: 400 | L85: Essentiel | M85: 350 | N85: 90 | R85: 45940 | S85: 150 | T85: 440 | U85: 290 | V85: Mouad | W85: 5 | X85: =IF(W85=0, " ",W85*14) -> 70 | Y85: 60 | Z85: =IF(Y85=0,"", Y85 * 4) -> 240 | AA85: =IF(Z85=0,"", Z85 * 0.15) -> 36 | AC85: =IF(OR(L85="", AB85=""), 0, IF(L85="Découverte", KPI!$F$2, IF(L85="Essentiel", KPI!$F$3, IF(L85="Premium", KPI!$F$4, 0) ) ) ) -> 0 | AD85: {=IF(F85="", "", (T85 / 1.21) - IF(L85="Découverte", KPI!$C$2, IF(L85="Essentiel", KPI!$C$3, IF(L85="Premium", KPI!$C$4, 0) ) ) - N(X85) - N(AA85) - N(AC85) - IFERROR(INDEX(Stats!$G:$G, MATCH(DATE(YEAR(R85), MONTH(R85), 1), Stats!$A:$A, 0)), 35) )} -> 169.06332 | AH85: h83vpfm0cupei42v97tr17to6g@google.com | AI85: OK 2025-12-01 18:37 | AL85: 2025_0097 | AM85: 2025-0106
A86: Nisrine Eslama | B86: niniisrine18@gmail.com | C86: 32467775714 | D86: FR | E86: 45930 | F86: 45962 | I86: Halle | J86: Bapteme | K86: 80 | L86: Découverte | M86: 250 | N86: 50 | R86: 45933 | S86: 150 | T86: 300 | U86: 150 | V86: Mouad | W86: 2 | X86: =IF(W86=0, " ",W86*14) -> 28 | Y86: 20 | Z86: =IF(Y86=0,"", Y86 * 4) -> 80 | AA86: =IF(Z86=0,"", Z86 * 0.15) -> 12 | AC86: =IF(OR(L86="", AB86=""), 0, IF(L86="Découverte", KPI!$F$2, IF(L86="Essentiel", KPI!$F$3, IF(L86="Premium", KPI!$F$4, 0) ) ) ) -> 0 | AD86: {=IF(F86="", "", (T86 / 1.21) - IF(L86="Découverte", KPI!$C$2, IF(L86="Essentiel", KPI!$C$3, IF(L86="Premium", KPI!$C$4, 0) ) ) - N(X86) - N(AA86) - N(AC86) - IFERROR(INDEX(Stats!$G:$G, MATCH(DATE(YEAR(R86), MONTH(R86), 1), Stats!$A:$A, 0)), 35) )} -> 142.49084 | AH86: ldi7uui9bcuvdtivbpqkn4uqsk@google.com | AI86: OK 2025-12-01 19:28 | AL86: 2025_0088 | AM86: 2025_0112
A87: Adeline Dubois | B87: adelinedubois@live.fr | C87: 32496259513 | D87: FR | E87: 45931 | F87: 45977 | I87: Audregnies | J87: Bapteme | K87: 50 | L87: Essentiel | M87: 350 | N87: 90 | R87: 45945 | S87: 150 | T87: 440 | U87: 290 | V87: Mouad | W87: 6 | X87: =IF(W87=0, " ",W87*14) -> 84 | Y87: 90 | Z87: =IF(Y87=0,"", Y87 * 4) -> 360 | AA87: =IF(Z87=0,"", Z87 * 0.15) -> 54 | AC87: =IF(OR(L87="", AB87=""), 0, IF(L87="Découverte", KPI!$F$2, IF(L87="Essentiel", KPI!$F$3, IF(L87="Premium", KPI!$F$4, 0) ) ) ) -> 0 | AD87: {=IF(F87="", "", (T87 / 1.21) - IF(L87="Découverte", KPI!$C$2, IF(L87="Essentiel", KPI!$C$3, IF(L87="Premium", KPI!$C$4, 0) ) ) - N(X87) - N(AA87) - N(AC87) - IFERROR(INDEX(Stats!$G:$G, MATCH(DATE(YEAR(R87), MONTH(R87), 1), Stats!$A:$A, 0)), 35) )} -> 137.06332 | AH87: 6nql5e162sndug040rdi0niea8@google.com | AI87: OK 2025-12-01 18:38 | AL87: 2025_0096 | AM87: 2025_0127
A88: Tracy Bouchain | B88: tracylmpr190693@gmail.com | C88: 32471522461 | D88: FR | E88: 45935 | F88: 46256 | I88: Angre | J88: Mariage | K88: 100 | L88: Essentiel | M88: 390 | N88: 90 | R88: 45937 | S88: 150 | T88: 480 | U88: 330 | W88: 6 | X88: =IF(W88=0, " ",W88*14) -> 84 | Y88: 94 | Z88: 376 | AA88: 56.4 | AC88: =IF(OR(L88="", AB88=""), 0, IF(L88="Découverte", KPI!$F$2, IF(L88="Essentiel", KPI!$F$3, IF(L88="Premium", KPI!$F$4, 0) ) ) ) -> 0 | AD88: {=IF(F88="", "", (T88 / 1.21) - IF(L88="Découverte", KPI!$C$2, IF(L88="Essentiel", KPI!$C$3, IF(L88="Premium", KPI!$C$4, 0) ) ) - N(X88) - N(AA88) - N(AC88) - IFERROR(INDEX(Stats!$G:$G, MATCH(DATE(YEAR(R88), MONTH(R88), 1), Stats!$A:$A, 0)), 35) )} -> 167.72117 | AH88: 843qe4frmp2dh2j4d3rq2ah2rk@google.com | AI88: OK 2025-12-01 18:44 | AL88: 2025_0085
A89: Sylvin Kalala | B89: sylvin.ks@hotmail.com | C89: 32485523059 | D89: FR | E89: 45936 | F89: 46255 | I89: Ophain | J89: Mariage | K89: 250 | L89: Premium | M89: 490 | N89: 90 | R89: 45939 | S89: 150 | T89: 580 | U89: 430 | W89: 3 | X89: =IF(W89=0, " ",W89*14) -> 42 | Y89: 30 | Z89: 120 | AA89: 18 | AC89: =IF(OR(L89="", AB89=""), 0, IF(L89="Découverte", KPI!$F$2, IF(L89="Essentiel", KPI!$F$3, IF(L89="Premium", KPI!$F$4, 0) ) ) ) -> 0 | AD89: {=IF(F89="", "", (T89 / 1.21) - IF(L89="Découverte", KPI!$C$2, IF(L89="Essentiel", KPI!$C$3, IF(L89="Premium", KPI!$C$4, 0) ) ) - N(X89) - N(AA89) - N(AC89) - IFERROR(INDEX(Stats!$G:$G, MATCH(DATE(YEAR(R89), MONTH(R89), 1), Stats!$A:$A, 0)), 35) )} -> 284.5158 | AH89: jonm7dng0eam90ivr7cms56034@google.com | AI89: OK 2025-12-01 18:44 | AL89: 2025_0095
A90: Mariya Nkolo | B90: nkolomariya7@gmail.com | C90: 33751260062 | D90: FR | E90: 45939 | F90: 46228 | I90: Les jardins du vert bois à bondues - Tourcoing | J90: Mariage | K90: 70 | L90: Découverte | M90: 290 | N90: 90 | R90: 45945 | S90: 150 | T90: 380 | U90: 230 | W90: 6.5 | X90: =IF(W90=0, " ",W90*14) -> 91 | Y90: 107 | Z90: 428 | AA90: 64.2 | AC90: =IF(OR(L90="", AB90=""), 0, IF(L90="Découverte", KPI!$F$2, IF(L90="Essentiel", KPI!$F$3, IF(L90="Premium", KPI!$F$4, 0) ) ) ) -> 0 | AD90: {=IF(F90="", "", (T90 / 1.21) - IF(L90="Découverte", KPI!$C$2, IF(L90="Essentiel", KPI!$C$3, IF(L90="Premium", KPI!$C$4, 0) ) ) - N(X90) - N(AA90) - N(AC90) - IFERROR(INDEX(Stats!$G:$G, MATCH(DATE(YEAR(R90), MONTH(R90), 1), Stats!$A:$A, 0)), 35) )} -> 93.406543 | AH90: 7thc4jdvoegivngi346q8hbk2g@google.com | AI90: OK 2025-12-01 18:35 | AL90: 2025_0102
A91: Clémence Munier | B91: munier.clemence@outlook.com | D91: FR | E91: 45870 | F91: 46599 | I91: Espace Aimé Césaire - 19 Bd de Metz, 54350 Mont-Saint-Martin | J91: Mariage | L91: Essentiel | M91: 350 | N91: 250 | P91: 8 | Q91: 150 | R91: 45938 | S91: 150 | T91: 750 | U91: 600 | W91: 11 | X91: =IF(W91=0, " ",W91*14) -> 154 | Y91: 215 | Z91: 860 | AA91: 129 | AC91: =IF(OR(L91="", AB91=""), 0, IF(L91="Découverte", KPI!$F$2, IF(L91="Essentiel", KPI!$F$3, IF(L91="Premium", KPI!$F$4, 0) ) ) ) -> 0 | AD91: {=IF(F91="", "", (T91 / 1.21) - IF(L91="Découverte", KPI!$C$2, IF(L91="Essentiel", KPI!$C$3, IF(L91="Premium", KPI!$C$4, 0) ) ) - N(X91) - N(AA91) - N(AC91) - IFERROR(INDEX(Stats!$G:$G, MATCH(DATE(YEAR(R91), MONTH(R91), 1), Stats!$A:$A, 0)), 35) )} -> 248.26167 | AH91: 8qv4463tn3nuqh9t1etjcsue0k@google.com | AI91: OK 2025-12-01 18:38 | AL91: 2025_0094
A92: Audrey Duvinage | B92: audrey.duvinage@hotmail.com | C92: 32484918399 | D92: FR | E92: 45943 | F92: 46228 | I92: Estaimbourg | J92: Mariage | K92: 200 | L92: Premium | M92: 490 | N92: 90 | R92: 45948 | S92: 150 | T92: 580 | U92: 430 | W92: 6 | X92: =IF(W92=0, " ",W92*14) -> 84 | Y92: 95 | Z92: 380 | AA92: 57 | AB92: Maxime | AC92: =IF(OR(L92="", AB92=""), 0, IF(L92="Découverte", KPI!$F$2, IF(L92="Essentiel", KPI!$F$3, IF(L92="Premium", KPI!$F$4, 0) ) ) ) -> 55 | AD92: {=IF(F92="", "", (T92 / 1.21) - IF(L92="Découverte", KPI!$C$2, IF(L92="Essentiel", KPI!$C$3, IF(L92="Premium", KPI!$C$4, 0) ) ) - N(X92) - N(AA92) - N(AC92) - IFERROR(INDEX(Stats!$G:$G, MATCH(DATE(YEAR(R92), MONTH(R92), 1), Stats!$A:$A, 0)), 35) )} -> 148.5158 | AH92: roc5b3bn31b96n1fe1jtv24ss4@google.com | AI92: OK 2025-12-01 18:37 | AL92: 2025_0100
A93: Audrey Mallié | B93: audreymallie99@gmail.com | C93: 32493624265 | D93: FR | E93: 45945 | F93: 46235 | I93: Marcinelle | J93: Mariage | K93: 35 | L93: Découverte | M93: 290 | N93: 90 | R93: 45951 | S93: 150 | T93: 380 | U93: 230 | W93: 4.5 | X93: =IF(W93=0, " ",W93*14) -> 63 | Y93: 64 | Z93: 256 | AA93: 38.4 | AB93: Maxime | AC93: =IF(OR(L93="", AB93=""), 0, IF(L93="Découverte", KPI!$F$2, IF(L93="Essentiel", KPI!$F$3, IF(L93="Premium", KPI!$F$4, 0) ) ) ) -> 35 | AD93: {=IF(F93="", "", (T93 / 1.21) - IF(L93="Découverte", KPI!$C$2, IF(L93="Essentiel", KPI!$C$3, IF(L93="Premium", KPI!$C$4, 0) ) ) - N(X93) - N(AA93) - N(AC93) - IFERROR(INDEX(Stats!$G:$G, MATCH(DATE(YEAR(R93), MONTH(R93), 1), Stats!$A:$A, 0)), 35) )} -> 112.20654 | AH93: 5ooggpftrahmk7lfi08nripd00@google.com | AI93: OK 2025-12-01 19:29 | AL93: 2025_0108
A94: Nassira Bakkouche | B94: nassirabakkouche123@hotmail.com | C94: 32470369387 | D94: FR | E94: 45951 | F94: 45997 | I94: Rue du Louvy 11, 6060 Charleroi, Belgique | J94: Anniversaire | K94: 100 | L94: Essentiel | M94: 390 | N94: 90 | R94: 45953 | S94: 150 | T94: 480 | U94: 330 | V94: Mouad | W94: 4.5 | X94: =IF(W94=0, " ",W94*14) -> 63 | Y94: 61 | Z94: 244 | AA94: 36.6 | AC94: =IF(OR(L94="", AB94=""), 0, IF(L94="Découverte", KPI!$F$2, IF(L94="Essentiel", KPI!$F$3, IF(L94="Premium", KPI!$F$4, 0) ) ) ) -> 0 | AD94: {=IF(F94="", "", (T94 / 1.21) - IF(L94="Découverte", KPI!$C$2, IF(L94="Essentiel", KPI!$C$3, IF(L94="Premium", KPI!$C$4, 0) ) ) - N(X94) - N(AA94) - N(AC94) - IFERROR(INDEX(Stats!$G:$G, MATCH(DATE(YEAR(R94), MONTH(R94), 1), Stats!$A:$A, 0)), 35) )} -> 208.52117 | AF94: https://fotoshare.co/e/uiL9GDehG8dbEVR4Sdu7h | AH94: aock9rssohl2op0qul4k7s89cc@google.com | AI94: OK 2025-12-20 12:35 | AJ94: Link Missing | AL94: 2025_0104 | AM94: 2025_0137
A95: JustineDecarnoncle | B95: j.decarnoncle@gmail.com | C95: 32472853159 | D95: FR | E95: 45947 | F95: 46312 | I95: Kain, Tournai | J95: Mariage | K95: 100 | L95: Essentiel | M95: 390 | N95: 90 | R95: 45955 | S95: 150 | T95: 480 | U95: 330 | W95: 5.5 | X95: =IF(W95=0, " ",W95*14) -> 77 | Y95: 88 | Z95: 352 | AA95: 52.8 | AC95: =IF(OR(L95="", AB95=""), 0, IF(L95="Découverte", KPI!$F$2, IF(L95="Essentiel", KPI!$F$3, IF(L95="Premium", KPI!$F$4, 0) ) ) ) -> 0 | AD95: {=IF(F95="", "", (T95 / 1.21) - IF(L95="Découverte", KPI!$C$2, IF(L95="Essentiel", KPI!$C$3, IF(L95="Premium", KPI!$C$4, 0) ) ) - N(X95) - N(AA95) - N(AC95) - IFERROR(INDEX(Stats!$G:$G, MATCH(DATE(YEAR(R95), MONTH(R95), 1), Stats!$A:$A, 0)), 35) )} -> 178.32117 | AH95: 4vls0nuguve4iht5mi1pp56b2g@google.com | AI95: OK 2025-12-01 18:34 | AL95: 2025_0105
A96: Andreana Lyphout | B96: andreana.lyphout@outlook.fr | C96: 33771219222 | D96: FR | E96: 45957 | F96: 46221 | I96: Hordain | J96: Mariage | K96: 150 | L96: Premium | M96: 490 | N96: 110 | R96: 45957 | S96: 150 | T96: 600 | U96: 450 | V96: Mouad | W96: 7 | X96: =IF(W96=0, " ",W96*14) -> 98 | Y96: 124 | Z96: 496 | AA96: 74.4 | AC96: =IF(OR(L96="", AB96=""), 0, IF(L96="Découverte", KPI!$F$2, IF(L96="Essentiel", KPI!$F$3, IF(L96="Premium", KPI!$F$4, 0) ) ) ) -> 0 | AD96: {=IF(F96="", "", (T96 / 1.21) - IF(L96="Découverte", KPI!$C$2, IF(L96="Essentiel", KPI!$C$3, IF(L96="Premium", KPI!$C$4, 0) ) ) - N(X96) - N(AA96) - N(AC96) - IFERROR(INDEX(Stats!$G:$G, MATCH(DATE(YEAR(R96), MONTH(R96), 1), Stats!$A:$A, 0)), 35) )} -> 188.64473 | AH96: 3lsbigdre0dfff6vbm0fnpqdeo@google.com | AI96: OK 2025-12-24 13:59 | AL96: 2025_0110
A97: Audrey Hombert | B97: audrey_hombert@msn.com | C97: 32477077065 | D97: FR | E97: 45954 | F97: 45969 | I97: Quevaucamps | J97: Mariage | K97: 69 | L97: Essentiel | M97: 390 | N97: 90 | R97: 45956 | S97: 150 | T97: 480 | U97: 330 | V97: Mouad | W97: 5.5 | X97: =IF(W97=0, " ",W97*14) -> 77 | Y97: 91 | Z97: 364 | AA97: 54.6 | AC97: =IF(OR(L97="", AB97=""), 0, IF(L97="Découverte", KPI!$F$2, IF(L97="Essentiel", KPI!$F$3, IF(L97="Premium", KPI!$F$4, 0) ) ) ) -> 0 | AD97: {=IF(F97="", "", (T97 / 1.21) - IF(L97="Découverte", KPI!$C$2, IF(L97="Essentiel", KPI!$C$3, IF(L97="Premium", KPI!$C$4, 0) ) ) - N(X97) - N(AA97) - N(AC97) - IFERROR(INDEX(Stats!$G:$G, MATCH(DATE(YEAR(R97), MONTH(R97), 1), Stats!$A:$A, 0)), 35) )} -> 176.52117 | AH97: 1ubp95doge4kkev4avras1plh4@google.com | AI97: OK 2025-12-01 19:29 | AL97: 2025_0107 | AM97: 2025_0121
A98: Cynthia Blondeau | B98: cynthia.blondeau@hotmail.com | C98: 33682439908 | D98: FR | E98: 45947 | F98: 46144 | I98: Bry, France | J98: Mariage | K98: 50 | L98: Découverte | M98: 290 | N98: 90 | R98: 45954 | S98: 150 | T98: 380 | U98: 230 | W98: 6.5 | X98: =IF(W98=0, " ",W98*14) -> 91 | Y98: 106 | Z98: 424 | AA98: 63.6 | AB98: Maxime | AC98: =IF(OR(L98="", AB98=""), 0, IF(L98="Découverte", KPI!$F$2, IF(L98="Essentiel", KPI!$F$3, IF(L98="Premium", KPI!$F$4, 0) ) ) ) -> 35 | AD98: {=IF(F98="", "", (T98 / 1.21) - IF(L98="Découverte", KPI!$C$2, IF(L98="Essentiel", KPI!$C$3, IF(L98="Premium", KPI!$C$4, 0) ) ) - N(X98) - N(AA98) - N(AC98) - IFERROR(INDEX(Stats!$G:$G, MATCH(DATE(YEAR(R98), MONTH(R98), 1), Stats!$A:$A, 0)), 35) )} -> 59.006543 | AH98: b3slqpeb7tk4jl3thg6ponfje8@google.com | AI98: OK 2025-12-01 19:29 | AL98: 2025_0109
A99: Samia Hamdani | B99: samiasam.cha@gmail.com | C99: 33610598211 | D99: FR | E99: 45962 | F99: 46117 | I99: Anvers | J99: Mariage | K99: 200 | L99: Premium | M99: 490 | N99: 90 | R99: 45962 | S99: 150 | T99: 580 | U99: 430 | W99: 5 | X99: =IF(W99=0, " ",W99*14) -> 70 | Y99: 51 | Z99: 204 | AA99: 30.6 | AC99: =IF(OR(L99="", AB99=""), 0, IF(L99="Découverte", KPI!$F$2, IF(L99="Essentiel", KPI!$F$3, IF(L99="Premium", KPI!$F$4, 0) ) ) ) -> 0 | AD99: {=IF(F99="", "", (T99 / 1.21) - IF(L99="Découverte", KPI!$C$2, IF(L99="Essentiel", KPI!$C$3, IF(L99="Premium", KPI!$C$4, 0) ) ) - N(X99) - N(AA99) - N(AC99) - IFERROR(INDEX(Stats!$G:$G, MATCH(DATE(YEAR(R99), MONTH(R99), 1), Stats!$A:$A, 0)), 35) )} -> 232.58147 | AH99: k187662q2a8c1t4kra08l69alg@google.com | AI99: OK 2025-11-22 13:43 | AL99: 2025_0113
A100: KellyHennen | B100: kelly_hennen@hotmail.com | C100: 32470520195 | D100: FR | E100: 45960 | F100: 46235 | I100: Sart lez Spa | J100: Mariage | K100: 100 | L100: Essentiel | M100: 390 | N100: 100 | R100: 45960 | S100: 150 | T100: 490 | U100: 340 | W100: 8 | X100: =IF(W100=0, " ",W100*14) -> 112 | Y100: 141 | Z100: 564 | AA100: 84.6 | AC100: =IF(OR(L100="", AB100=""), 0, IF(L100="Découverte", KPI!$F$2, IF(L100="Essentiel", KPI!$F$3, IF(L100="Premium", KPI!$F$4, 0) ) ) ) -> 0 | AD100: {=IF(F100="", "", (T100 / 1.21) - IF(L100="Découverte", KPI!$C$2, IF(L100="Essentiel", KPI!$C$3, IF(L100="Premium", KPI!$C$4, 0) ) ) - N(X100) - N(AA100) - N(AC100) - IFERROR(INDEX(Stats!$G:$G, MATCH(DATE(YEAR(R100), MONTH(R100), 1), Stats!$A:$A, 0)), 35) )} -> 119.78563 | AH100: f9gofa8l3ldtrq9ng2h7c3klrg@google.com | AI100: OK 2025-12-01 18:35 | AL100: 2025_0103
...

Sheet Stats
A1: Date | B1: # Leads META | C1: Spent META | D1: CPL META | E1: # closing META | F1: Conversion (%) META | G1: CPA META | H1: # Leads Total | I1: CPL Total | J1: # closing Total | K1: Conversion (%) total | L1: CPA G | M1: # C.Découverte | N1: # C.Essentiel | O1: # C.Premium | P1: Acomptes (payés) | Q1: # Events | R1: # E.Découverte | S1: # E.Essentiel | T1: # E.Premium | U1: Total (event) | V1: Acomptes (event) | W1: Restants (event) | X1: CA (Acomptes + Restants) | Y1: CA généré (Event + Transport) | Z1: € transport (Ev. Réalisés) | AA1: Coût packs (Ev. Réalisés) | AB1: Heures étudiants | AC1: Coût staff étudiants | AD1: Essence | AE1: Comm Commerciaux | AF1: Charges fixes mensuelles | AG1: Marge brute opé. (Events) | AH1: Marge nette opé. (Events) | AI1: Cashflow Brut (mensuel) | AJ1: Cashflow Net (mensuel)
A2: 45658 | C2: 750 | D2: =IF(B2=0, 0, C2/B2) -> 0 | E2: =COUNTIFS( Clients!$R:$R, ">="&A2, Clients!$R:$R, "<"&DATE(YEAR(A2), MONTH(A2)+1, 1) ) -> 0 | F2: =IF(B2=0, 0, E2/B2) -> 0 | G2: 35 | I2: =IF(H2=0, 0, #REF!/H2) -> 0 | M2: =COUNTIFS( Clients!$R:$R, ">="&A2, Clients!$R:$R, "<"&DATE(YEAR(A2), MONTH(A2)+1, 1), Clients!$L:$L, "Découverte" ) -> 0 | N2: =COUNTIFS( Clients!$R:$R, ">="&A2, Clients!$R:$R, "<"&DATE(YEAR(A2), MONTH(A2)+1, 1), Clients!$L:$L, "Essentiel" ) -> 0 | O2: =COUNTIFS( Clients!$R:$R, ">="&A2, Clients!$R:$R, "<"&DATE(YEAR(A2), MONTH(A2)+1, 1), Clients!$L:$L, "Premium" ) -> 0 | P2: =SUMIFS( Clients!$S:$S, Clients!$R:$R, ">="&A2, Clients!$R:$R, "<"&DATE(YEAR(A2), MONTH(A2)+1, 1) ) -> 0 | Q2: =COUNTIFS( Clients!$F:$F, ">="&A2, Clients!$F:$F, "<"&DATE(YEAR(A2), MONTH(A2)+1, 1) ) -> 4 | R2: =COUNTIFS( Clients!$F:$F, ">="&A2, Clients!$F:$F, "<"&DATE(YEAR(A2), MONTH(A2)+1, 1), Clients!$L:$L, "Découverte" ) -> 1 | S2: =COUNTIFS( Clients!$F:$F, ">="&A2, Clients!$F:$F, "<"&DATE(YEAR(A2), MONTH(A2)+1, 1), Clients!$L:$L, "Essentiel" ) -> 1 | T2: =COUNTIFS( Clients!$F:$F, ">="&A2, Clients!$F:$F, "<"&DATE(YEAR(A2), MONTH(A2)+1, 1), Clients!$L:$L, "Premium" ) -> 2 | U2: =SUMIFS( Clients!$T:$T, Clients!$F:$F, ">="&A2, Clients!$F:$F, "<"&DATE(YEAR(A2), MONTH(A2)+1, 1) ) -> 2320 | V2: =SUMIFS( Clients!$S:$S, Clients!$F:$F, ">="&A2, Clients!$F:$F, "<"&DATE(YEAR(A2), MONTH(A2)+1, 1) ) -> 0 | W2: =SUMIFS( Clients!$U:$U, Clients!$F:$F, ">="&A2, Clients!$F:$F, "<"&DATE(YEAR(A2), MONTH(A2)+1, 1) ) -> 2320 | X2: =P2 + W2 -> 2320 | Z2: =SUMIFS( Clients!$N:$N, Clients!$F:$F,">="&$A2, Clients!$F:$F,"<"&DATE(YEAR($A2),MONTH($A2)+1,1) ) -> 80 | AA2: =R2 * KPI!$C$2 + S2 * KPI!$C$3 + T2 * KPI!$C$4 -> 254.37 | AB2: =SUMIFS( Clients!$W:$W, Clients!$F:$F,">="&A2, Clients!$F:$F,"<"&DATE(YEAR(A2),MONTH(A2)+1,1) ) -> 19 | AC2: =SUMIFS( Clients!$X:$X, Clients!$F:$F,">="&A2, Clients!$F:$F,"<"&DATE(YEAR(A2),MONTH(A2)+1,1) ) -> 280 | AD2: =SUMIFS( Clients!$AA:$AA, Clients!$F:$F,">="&$A2, Clients!$F:$F,"<"&DATE(YEAR($A2),MONTH($A2)+1,1) ) -> 168.6 | AE2: =SUMIFS( Clients!$AC:$AC, Clients!$R:$R,">="&$A2, Clients!$R:$R,"<"&DATE(YEAR($A2),MONTH($A2)+1,1) ) -> 0 | AF2: =KPI!$B$29 -> 441.64 | AH2: =U2 - AA2 - Z2 - AC2 - AD2 -> 1537.03 | AI2: =(P2 + W2 + Z2) - AA2 - AC2 - AD2 - AE2 -> 1697.03 | AJ2: =AI2 - C2 - AF2 -> 505.39
A3: 45689 | C3: 750 | D3: =IF(B3=0, 0, C3/B3) -> 0 | E3: =COUNTIFS( Clients!$R:$R, ">="&A3, Clients!$R:$R, "<"&DATE(YEAR(A3), MONTH(A3)+1, 1) ) -> 0 | F3: =IF(B3=0, 0, E3/B3) -> 0 | G3: 35 | I3: =IF(H3=0, 0, #REF!/H3) -> 0 | M3: =COUNTIFS( Clients!$R:$R, ">="&A3, Clients!$R:$R, "<"&DATE(YEAR(A3), MONTH(A3)+1, 1), Clients!$L:$L, "Découverte" ) -> 0 | N3: =COUNTIFS( Clients!$R:$R, ">="&A3, Clients!$R:$R, "<"&DATE(YEAR(A3), MONTH(A3)+1, 1), Clients!$L:$L, "Essentiel" ) -> 0 | O3: =COUNTIFS( Clients!$R:$R, ">="&A3, Clients!$R:$R, "<"&DATE(YEAR(A3), MONTH(A3)+1, 1), Clients!$L:$L, "Premium" ) -> 0 | P3: =SUMIFS( Clients!$S:$S, Clients!$R:$R, ">="&A3, Clients!$R:$R, "<"&DATE(YEAR(A3), MONTH(A3)+1, 1) ) -> 0 | Q3: =COUNTIFS( Clients!$F:$F, ">="&A3, Clients!$F:$F, "<"&DATE(YEAR(A3), MONTH(A3)+1, 1) ) -> 0 | R3: =COUNTIFS( Clients!$F:$F, ">="&A3, Clients!$F:$F, "<"&DATE(YEAR(A3), MONTH(A3)+1, 1), Clients!$L:$L, "Découverte" ) -> 0 | S3: =COUNTIFS( Clients!$F:$F, ">="&A3, Clients!$F:$F, "<"&DATE(YEAR(A3), MONTH(A3)+1, 1), Clients!$L:$L, "Essentiel" ) -> 0 | T3: =COUNTIFS( Clients!$F:$F, ">="&A3, Clients!$F:$F, "<"&DATE(YEAR(A3), MONTH(A3)+1, 1), Clients!$L:$L, "Premium" ) -> 0 | U3: =SUMIFS( Clients!$T:$T, Clients!$F:$F, ">="&A3, Clients!$F:$F, "<"&DATE(YEAR(A3), MONTH(A3)+1, 1) ) -> 0 | V3: =SUMIFS( Clients!$S:$S, Clients!$F:$F, ">="&A3, Clients!$F:$F, "<"&DATE(YEAR(A3), MONTH(A3)+1, 1) ) -> 0 | W3: =SUMIFS( Clients!$U:$U, Clients!$F:$F, ">="&A3, Clients!$F:$F, "<"&DATE(YEAR(A3), MONTH(A3)+1, 1) ) -> 0 | X3: =P3 + W3 -> 0 | Z3: =SUMIFS( Clients!$N:$N, Clients!$F:$F,">="&$A3, Clients!$F:$F,"<"&DATE(YEAR($A3),MONTH($A3)+1,1) ) -> 0 | AA3: =R3 * KPI!$C$2 + S3 * KPI!$C$3 + T3 * KPI!$C$4 -> 0 | AB3: =SUMIFS( Clients!$W:$W, Clients!$F:$F,">="&A3, Clients!$F:$F,"<"&DATE(YEAR(A3),MONTH(A3)+1,1) ) -> 0 | AC3: =SUMIFS( Clients!$X:$X, Clients!$F:$F,">="&A3, Clients!$F:$F,"<"&DATE(YEAR(A3),MONTH(A3)+1,1) ) -> 0 | AD3: =SUMIFS( Clients!$AA:$AA, Clients!$F:$F,">="&$A3, Clients!$F:$F,"<"&DATE(YEAR($A3),MONTH($A3)+1,1) ) -> 0 | AE3: =SUMIFS( Clients!$AC:$AC, Clients!$R:$R,">="&$A3, Clients!$R:$R,"<"&DATE(YEAR($A3),MONTH($A3)+1,1) ) -> 0 | AF3: =KPI!$B$29 -> 441.64 | AH3: =U3 - AA3 - Z3 - AC3 - AD3 -> 0 | AI3: =(P3 + W3 + Z3) - AA3 - AC3 - AD3 - AE3 -> 0 | AJ3: =AI3 - C3 - AF3 -> -1191.64
A4: 45717 | C4: 750 | D4: =IF(B4=0, 0, C4/B4) -> 0 | E4: =COUNTIFS( Clients!$R:$R, ">="&A4, Clients!$R:$R, "<"&DATE(YEAR(A4), MONTH(A4)+1, 1) ) -> 0 | F4: =IF(B4=0, 0, E4/B4) -> 0 | G4: 35 | I4: =IF(H4=0, 0, #REF!/H4) -> 0 | M4: =COUNTIFS( Clients!$R:$R, ">="&A4, Clients!$R:$R, "<"&DATE(YEAR(A4), MONTH(A4)+1, 1), Clients!$L:$L, "Découverte" ) -> 0 | N4: =COUNTIFS( Clients!$R:$R, ">="&A4, Clients!$R:$R, "<"&DATE(YEAR(A4), MONTH(A4)+1, 1), Clients!$L:$L, "Essentiel" ) -> 0 | O4: =COUNTIFS( Clients!$R:$R, ">="&A4, Clients!$R:$R, "<"&DATE(YEAR(A4), MONTH(A4)+1, 1), Clients!$L:$L, "Premium" ) -> 0 | P4: =SUMIFS( Clients!$S:$S, Clients!$R:$R, ">="&A4, Clients!$R:$R, "<"&DATE(YEAR(A4), MONTH(A4)+1, 1) ) -> 0 | Q4: =COUNTIFS( Clients!$F:$F, ">="&A4, Clients!$F:$F, "<"&DATE(YEAR(A4), MONTH(A4)+1, 1) ) -> 1 | R4: =COUNTIFS( Clients!$F:$F, ">="&A4, Clients!$F:$F, "<"&DATE(YEAR(A4), MONTH(A4)+1, 1), Clients!$L:$L, "Découverte" ) -> 0 | S4: =COUNTIFS( Clients!$F:$F, ">="&A4, Clients!$F:$F, "<"&DATE(YEAR(A4), MONTH(A4)+1, 1), Clients!$L:$L, "Essentiel" ) -> 0 | T4: =COUNTIFS( Clients!$F:$F, ">="&A4, Clients!$F:$F, "<"&DATE(YEAR(A4), MONTH(A4)+1, 1), Clients!$L:$L, "Premium" ) -> 1 | U4: =SUMIFS( Clients!$T:$T, Clients!$F:$F, ">="&A4, Clients!$F:$F, "<"&DATE(YEAR(A4), MONTH(A4)+1, 1) ) -> 580 | V4: =SUMIFS( Clients!$S:$S, Clients!$F:$F, ">="&A4, Clients!$F:$F, "<"&DATE(YEAR(A4), MONTH(A4)+1, 1) ) -> 0 | W4: =SUMIFS( Clients!$U:$U, Clients!$F:$F, ">="&A4, Clients!$F:$F, "<"&DATE(YEAR(A4), MONTH(A4)+1, 1) ) -> 580 | X4: =P4 + W4 -> 580 | Z4: =SUMIFS( Clients!$N:$N, Clients!$F:$F,">="&$A4, Clients!$F:$F,"<"&DATE(YEAR($A4),MONTH($A4)+1,1) ) -> 80 | AA4: =R4 * KPI!$C$2 + S4 * KPI!$C$3 + T4 * KPI!$C$4 -> 92.5 | AB4: =SUMIFS( Clients!$W:$W, Clients!$F:$F,">="&A4, Clients!$F:$F,"<"&DATE(YEAR(A4),MONTH(A4)+1,1) ) -> 5 | AC4: =SUMIFS( Clients!$X:$X, Clients!$F:$F,">="&A4, Clients!$F:$F,"<"&DATE(YEAR(A4),MONTH(A4)+1,1) ) -> 70 | AD4: =SUMIFS( Clients!$AA:$AA, Clients!$F:$F,">="&$A4, Clients!$F:$F,"<"&DATE(YEAR($A4),MONTH($A4)+1,1) ) -> 47.4 | AE4: =SUMIFS( Clients!$AC:$AC, Clients!$R:$R,">="&$A4, Clients!$R:$R,"<"&DATE(YEAR($A4),MONTH($A4)+1,1) ) -> 0 | AF4: =KPI!$B$29 -> 441.64 | AH4: =U4 - AA4 - Z4 - AC4 - AD4 -> 290.1 | AI4: =(P4 + W4 + Z4) - AA4 - AC4 - AD4 - AE4 -> 450.1 | AJ4: =AI4 - C4 - AF4 -> -741.54
A5: 45748 | C5: 750 | D5: =IF(B5=0, 0, C5/B5) -> 0 | E5: =COUNTIFS( Clients!$R:$R, ">="&A5, Clients!$R:$R, "<"&DATE(YEAR(A5), MONTH(A5)+1, 1) ) -> 0 | F5: =IF(B5=0, 0, E5/B5) -> 0 | G5: 35 | I5: =IF(H5=0, 0, #REF!/H5) -> 0 | M5: =COUNTIFS( Clients!$R:$R, ">="&A5, Clients!$R:$R, "<"&DATE(YEAR(A5), MONTH(A5)+1, 1), Clients!$L:$L, "Découverte" ) -> 0 | N5: =COUNTIFS( Clients!$R:$R, ">="&A5, Clients!$R:$R, "<"&DATE(YEAR(A5), MONTH(A5)+1, 1), Clients!$L:$L, "Essentiel" ) -> 0 | O5: =COUNTIFS( Clients!$R:$R, ">="&A5, Clients!$R:$R, "<"&DATE(YEAR(A5), MONTH(A5)+1, 1), Clients!$L:$L, "Premium" ) -> 0 | P5: =SUMIFS( Clients!$S:$S, Clients!$R:$R, ">="&A5, Clients!$R:$R, "<"&DATE(YEAR(A5), MONTH(A5)+1, 1) ) -> 0 | Q5: =COUNTIFS( Clients!$F:$F, ">="&A5, Clients!$F:$F, "<"&DATE(YEAR(A5), MONTH(A5)+1, 1) ) -> 3 | R5: =COUNTIFS( Clients!$F:$F, ">="&A5, Clients!$F:$F, "<"&DATE(YEAR(A5), MONTH(A5)+1, 1), Clients!$L:$L, "Découverte" ) -> 0 | S5: =COUNTIFS( Clients!$F:$F, ">="&A5, Clients!$F:$F, "<"&DATE(YEAR(A5), MONTH(A5)+1, 1), Clients!$L:$L, "Essentiel" ) -> 0 | T5: =COUNTIFS( Clients!$F:$F, ">="&A5, Clients!$F:$F, "<"&DATE(YEAR(A5), MONTH(A5)+1, 1), Clients!$L:$L, "Premium" ) -> 3 | U5: =SUMIFS( Clients!$T:$T, Clients!$F:$F, ">="&A5, Clients!$F:$F, "<"&DATE(YEAR(A5), MONTH(A5)+1, 1) ) -> 1490 | V5: =SUMIFS( Clients!$S:$S, Clients!$F:$F, ">="&A5, Clients!$F:$F, "<"&DATE(YEAR(A5), MONTH(A5)+1, 1) ) -> 0 | W5: =SUMIFS( Clients!$U:$U, Clients!$F:$F, ">="&A5, Clients!$F:$F, "<"&DATE(YEAR(A5), MONTH(A5)+1, 1) ) -> 1490 | X5: =P5 + W5 -> 1490 | Z5: =SUMIFS( Clients!$N:$N, Clients!$F:$F,">="&$A5, Clients!$F:$F,"<"&DATE(YEAR($A5),MONTH($A5)+1,1) ) -> 290 | AA5: =R5 * KPI!$C$2 + S5 * KPI!$C$3 + T5 * KPI!$C$4 -> 277.5 | AB5: =SUMIFS( Clients!$W:$W, Clients!$F:$F,">="&A5, Clients!$F:$F,"<"&DATE(YEAR(A5),MONTH(A5)+1,1) ) -> 17.5 | AC5: =SUMIFS( Clients!$X:$X, Clients!$F:$F,">="&A5, Clients!$F:$F,"<"&DATE(YEAR(A5),MONTH(A5)+1,1) ) -> 210 | AD5: =SUMIFS( Clients!$AA:$AA, Clients!$F:$F,">="&$A5, Clients!$F:$F,"<"&DATE(YEAR($A5),MONTH($A5)+1,1) ) -> 163.2 | AE5: =SUMIFS( Clients!$AC:$AC, Clients!$R:$R,">="&$A5, Clients!$R:$R,"<"&DATE(YEAR($A5),MONTH($A5)+1,1) ) -> 0 | AF5: =KPI!$B$29 -> 441.64 | AH5: =U5 - AA5 - Z5 - AC5 - AD5 -> 549.3 | AI5: =(P5 + W5 + Z5) - AA5 - AC5 - AD5 - AE5 -> 1129.3 | AJ5: =AI5 - C5 - AF5 -> -62.34
A6: 45778 | C6: 750 | D6: =IF(B6=0, 0, C6/B6) -> 0 | E6: =COUNTIFS( Clients!$R:$R, ">="&A6, Clients!$R:$R, "<"&DATE(YEAR(A6), MONTH(A6)+1, 1) ) -> 0 | F6: =IF(B6=0, 0, E6/B6) -> 0 | G6: 35 | I6: =IF(H6=0, 0, #REF!/H6) -> 0 | M6: =COUNTIFS( Clients!$R:$R, ">="&A6, Clients!$R:$R, "<"&DATE(YEAR(A6), MONTH(A6)+1, 1), Clients!$L:$L, "Découverte" ) -> 0 | N6: =COUNTIFS( Clients!$R:$R, ">="&A6, Clients!$R:$R, "<"&DATE(YEAR(A6), MONTH(A6)+1, 1), Clients!$L:$L, "Essentiel" ) -> 0 | O6: =COUNTIFS( Clients!$R:$R, ">="&A6, Clients!$R:$R, "<"&DATE(YEAR(A6), MONTH(A6)+1, 1), Clients!$L:$L, "Premium" ) -> 0 | P6: =SUMIFS( Clients!$S:$S, Clients!$R:$R, ">="&A6, Clients!$R:$R, "<"&DATE(YEAR(A6), MONTH(A6)+1, 1) ) -> 0 | Q6: =COUNTIFS( Clients!$F:$F, ">="&A6, Clients!$F:$F, "<"&DATE(YEAR(A6), MONTH(A6)+1, 1) ) -> 7 | R6: =COUNTIFS( Clients!$F:$F, ">="&A6, Clients!$F:$F, "<"&DATE(YEAR(A6), MONTH(A6)+1, 1), Clients!$L:$L, "Découverte" ) -> 0 | S6: =COUNTIFS( Clients!$F:$F, ">="&A6, Clients!$F:$F, "<"&DATE(YEAR(A6), MONTH(A6)+1, 1), Clients!$L:$L, "Essentiel" ) -> 2 | T6: =COUNTIFS( Clients!$F:$F, ">="&A6, Clients!$F:$F, "<"&DATE(YEAR(A6), MONTH(A6)+1, 1), Clients!$L:$L, "Premium" ) -> 5 | U6: =SUMIFS( Clients!$T:$T, Clients!$F:$F, ">="&A6, Clients!$F:$F, "<"&DATE(YEAR(A6), MONTH(A6)+1, 1) ) -> 3715 | V6: =SUMIFS( Clients!$S:$S, Clients!$F:$F, ">="&A6, Clients!$F:$F, "<"&DATE(YEAR(A6), MONTH(A6)+1, 1) ) -> 0 | W6: =SUMIFS( Clients!$U:$U, Clients!$F:$F, ">="&A6, Clients!$F:$F, "<"&DATE(YEAR(A6), MONTH(A6)+1, 1) ) -> 3715 | X6: =P6 + W6 -> 3715 | Z6: =SUMIFS( Clients!$N:$N, Clients!$F:$F,">="&$A6, Clients!$F:$F,"<"&DATE(YEAR($A6),MONTH($A6)+1,1) ) -> 315 | AA6: =R6 * KPI!$C$2 + S6 * KPI!$C$3 + T6 * KPI!$C$4 -> 555 | AB6: =SUMIFS( Clients!$W:$W, Clients!$F:$F,">="&A6, Clients!$F:$F,"<"&DATE(YEAR(A6),MONTH(A6)+1,1) ) -> 23 | AC6: =SUMIFS( Clients!$X:$X, Clients!$F:$F,">="&A6, Clients!$F:$F,"<"&DATE(YEAR(A6),MONTH(A6)+1,1) ) -> 490 | AD6: =SUMIFS( Clients!$AA:$AA, Clients!$F:$F,">="&$A6, Clients!$F:$F,"<"&DATE(YEAR($A6),MONTH($A6)+1,1) ) -> 131.4 | AE6: =SUMIFS( Clients!$AC:$AC, Clients!$R:$R,">="&$A6, Clients!$R:$R,"<"&DATE(YEAR($A6),MONTH($A6)+1,1) ) -> 0 | AF6: =KPI!$B$29 -> 441.64 | AH6: =U6 - AA6 - Z6 - AC6 - AD6 -> 2223.6 | AI6: =(P6 + W6 + Z6) - AA6 - AC6 - AD6 - AE6 -> 2853.6 | AJ6: =AI6 - C6 - AF6 -> 1661.96
A7: 45809 | C7: 750 | D7: =IF(B7=0, 0, C7/B7) -> 0 | E7: =COUNTIFS( Clients!$R:$R, ">="&A7, Clients!$R:$R, "<"&DATE(YEAR(A7), MONTH(A7)+1, 1) ) -> 0 | F7: =IF(B7=0, 0, E7/B7) -> 0 | G7: 35 | I7: =IF(H7=0, 0, #REF!/H7) -> 0 | M7: =COUNTIFS( Clients!$R:$R, ">="&A7, Clients!$R:$R, "<"&DATE(YEAR(A7), MONTH(A7)+1, 1), Clients!$L:$L, "Découverte" ) -> 0 | N7: =COUNTIFS( Clients!$R:$R, ">="&A7, Clients!$R:$R, "<"&DATE(YEAR(A7), MONTH(A7)+1, 1), Clients!$L:$L, "Essentiel" ) -> 0 | O7: =COUNTIFS( Clients!$R:$R, ">="&A7, Clients!$R:$R, "<"&DATE(YEAR(A7), MONTH(A7)+1, 1), Clients!$L:$L, "Premium" ) -> 0 | P7: =SUMIFS( Clients!$S:$S, Clients!$R:$R, ">="&A7, Clients!$R:$R, "<"&DATE(YEAR(A7), MONTH(A7)+1, 1) ) -> 0 | Q7: =COUNTIFS( Clients!$F:$F, ">="&A7, Clients!$F:$F, "<"&DATE(YEAR(A7), MONTH(A7)+1, 1) ) -> 5 | R7: =COUNTIFS( Clients!$F:$F, ">="&A7, Clients!$F:$F, "<"&DATE(YEAR(A7), MONTH(A7)+1, 1), Clients!$L:$L, "Découverte" ) -> 1 | S7: =COUNTIFS( Clients!$F:$F, ">="&A7, Clients!$F:$F, "<"&DATE(YEAR(A7), MONTH(A7)+1, 1), Clients!$L:$L, "Essentiel" ) -> 1 | T7: =COUNTIFS( Clients!$F:$F, ">="&A7, Clients!$F:$F, "<"&DATE(YEAR(A7), MONTH(A7)+1, 1), Clients!$L:$L, "Premium" ) -> 3 | U7: =SUMIFS( Clients!$T:$T, Clients!$F:$F, ">="&A7, Clients!$F:$F, "<"&DATE(YEAR(A7), MONTH(A7)+1, 1) ) -> 2300 | V7: =SUMIFS( Clients!$S:$S, Clients!$F:$F, ">="&A7, Clients!$F:$F, "<"&DATE(YEAR(A7), MONTH(A7)+1, 1) ) -> 0 | W7: =SUMIFS( Clients!$U:$U, Clients!$F:$F, ">="&A7, Clients!$F:$F, "<"&DATE(YEAR(A7), MONTH(A7)+1, 1) ) -> 2300 | X7: =P7 + W7 -> 2300 | Z7: =SUMIFS( Clients!$N:$N, Clients!$F:$F,">="&$A7, Clients!$F:$F,"<"&DATE(YEAR($A7),MONTH($A7)+1,1) ) -> 100 | AA7: =R7 * KPI!$C$2 + S7 * KPI!$C$3 + T7 * KPI!$C$4 -> 346.87 | AB7: =SUMIFS( Clients!$W:$W, Clients!$F:$F,">="&A7, Clients!$F:$F,"<"&DATE(YEAR(A7),MONTH(A7)+1,1) ) -> 10.5 | AC7: =SUMIFS( Clients!$X:$X, Clients!$F:$F,">="&A7, Clients!$F:$F,"<"&DATE(YEAR(A7),MONTH(A7)+1,1) ) -> 350 | AD7: =SUMIFS( Clients!$AA:$AA, Clients!$F:$F,">="&$A7, Clients!$F:$F,"<"&DATE(YEAR($A7),MONTH($A7)+1,1) ) -> 58.8 | AE7: =SUMIFS( Clients!$AC:$AC, Clients!$R:$R,">="&$A7, Clients!$R:$R,"<"&DATE(YEAR($A7),MONTH($A7)+1,1) ) -> 0 | AF7: =KPI!$B$29 -> 441.64 | AH7: =U7 - AA7 - Z7 - AC7 - AD7 -> 1444.33 | AI7: =(P7 + W7 + Z7) - AA7 - AC7 - AD7 - AE7 -> 1644.33 | AJ7: =AI7 - C7 - AF7 -> 452.69
A8: 45839 | C8: 750 | D8: =IF(B8=0, 0, C8/B8) -> 0 | E8: =COUNTIFS( Clients!$R:$R, ">="&A8, Clients!$R:$R, "<"&DATE(YEAR(A8), MONTH(A8)+1, 1) ) -> 0 | F8: =IF(B8=0, 0, E8/B8) -> 0 | G8: 35 | I8: =IF(H8=0, 0, #REF!/H8) -> 0 | M8: =COUNTIFS( Clients!$R:$R, ">="&A8, Clients!$R:$R, "<"&DATE(YEAR(A8), MONTH(A8)+1, 1), Clients!$L:$L, "Découverte" ) -> 0 | N8: =COUNTIFS( Clients!$R:$R, ">="&A8, Clients!$R:$R, "<"&DATE(YEAR(A8), MONTH(A8)+1, 1), Clients!$L:$L, "Essentiel" ) -> 0 | O8: =COUNTIFS( Clients!$R:$R, ">="&A8, Clients!$R:$R, "<"&DATE(YEAR(A8), MONTH(A8)+1, 1), Clients!$L:$L, "Premium" ) -> 0 | P8: =SUMIFS( Clients!$S:$S, Clients!$R:$R, ">="&A8, Clients!$R:$R, "<"&DATE(YEAR(A8), MONTH(A8)+1, 1) ) -> 0 | Q8: =COUNTIFS( Clients!$F:$F, ">="&A8, Clients!$F:$F, "<"&DATE(YEAR(A8), MONTH(A8)+1, 1) ) -> 3 | R8: =COUNTIFS( Clients!$F:$F, ">="&A8, Clients!$F:$F, "<"&DATE(YEAR(A8), MONTH(A8)+1, 1), Clients!$L:$L, "Découverte" ) -> 0 | S8: =COUNTIFS( Clients!$F:$F, ">="&A8, Clients!$F:$F, "<"&DATE(YEAR(A8), MONTH(A8)+1, 1), Clients!$L:$L, "Essentiel" ) -> 0 | T8: =COUNTIFS( Clients!$F:$F, ">="&A8, Clients!$F:$F, "<"&DATE(YEAR(A8), MONTH(A8)+1, 1), Clients!$L:$L, "Premium" ) -> 3 | U8: =SUMIFS( Clients!$T:$T, Clients!$F:$F, ">="&A8, Clients!$F:$F, "<"&DATE(YEAR(A8), MONTH(A8)+1, 1) ) -> 1845 | V8: =SUMIFS( Clients!$S:$S, Clients!$F:$F, ">="&A8, Clients!$F:$F, "<"&DATE(YEAR(A8), MONTH(A8)+1, 1) ) -> 0 | W8: =SUMIFS( Clients!$U:$U, Clients!$F:$F, ">="&A8, Clients!$F:$F, "<"&DATE(YEAR(A8), MONTH(A8)+1, 1) ) -> 1845 | X8: =P8 + W8 -> 1845 | Z8: =SUMIFS( Clients!$N:$N, Clients!$F:$F,">="&$A8, Clients!$F:$F,"<"&DATE(YEAR($A8),MONTH($A8)+1,1) ) -> 345 | AA8: =R8 * KPI!$C$2 + S8 * KPI!$C$3 + T8 * KPI!$C$4 -> 277.5 | AB8: =SUMIFS( Clients!$W:$W, Clients!$F:$F,">="&A8, Clients!$F:$F,"<"&DATE(YEAR(A8),MONTH(A8)+1,1) ) -> 20.5 | AC8: =SUMIFS( Clients!$X:$X, Clients!$F:$F,">="&A8, Clients!$F:$F,"<"&DATE(YEAR(A8),MONTH(A8)+1,1) ) -> 210 | AD8: =SUMIFS( Clients!$AA:$AA, Clients!$F:$F,">="&$A8, Clients!$F:$F,"<"&DATE(YEAR($A8),MONTH($A8)+1,1) ) -> 198 | AE8: =SUMIFS( Clients!$AC:$AC, Clients!$R:$R,">="&$A8, Clients!$R:$R,"<"&DATE(YEAR($A8),MONTH($A8)+1,1) ) -> 0 | AF8: =KPI!$B$29 -> 441.64 | AH8: =U8 - AA8 - Z8 - AC8 - AD8 -> 814.5 | AI8: =(P8 + W8 + Z8) - AA8 - AC8 - AD8 - AE8 -> 1504.5 | AJ8: =AI8 - C8 - AF8 -> 312.86
A9: 45870 | C9: 750 | D9: =IF(B9=0, 0, C9/B9) -> 0 | E9: =COUNTIFS( Clients!$R:$R, ">="&A9, Clients!$R:$R, "<"&DATE(YEAR(A9), MONTH(A9)+1, 1) ) -> 1 | F9: =IF(B9=0, 0, E9/B9) -> 0 | G9: 35 | I9: =IF(H9=0, 0, #REF!/H9) -> 0 | M9: =COUNTIFS( Clients!$R:$R, ">="&A9, Clients!$R:$R, "<"&DATE(YEAR(A9), MONTH(A9)+1, 1), Clients!$L:$L, "Découverte" ) -> 0 | N9: =COUNTIFS( Clients!$R:$R, ">="&A9, Clients!$R:$R, "<"&DATE(YEAR(A9), MONTH(A9)+1, 1), Clients!$L:$L, "Essentiel" ) -> 0 | O9: =COUNTIFS( Clients!$R:$R, ">="&A9, Clients!$R:$R, "<"&DATE(YEAR(A9), MONTH(A9)+1, 1), Clients!$L:$L, "Premium" ) -> 1 | P9: =SUMIFS( Clients!$S:$S, Clients!$R:$R, ">="&A9, Clients!$R:$R, "<"&DATE(YEAR(A9), MONTH(A9)+1, 1) ) -> 0 | Q9: =COUNTIFS( Clients!$F:$F, ">="&A9, Clients!$F:$F, "<"&DATE(YEAR(A9), MONTH(A9)+1, 1) ) -> 11 | R9: =COUNTIFS( Clients!$F:$F, ">="&A9, Clients!$F:$F, "<"&DATE(YEAR(A9), MONTH(A9)+1, 1), Clients!$L:$L, "Découverte" ) -> 0 | S9: =COUNTIFS( Clients!$F:$F, ">="&A9, Clients!$F:$F, "<"&DATE(YEAR(A9), MONTH(A9)+1, 1), Clients!$L:$L, "Essentiel" ) -> 4 | T9: =COUNTIFS( Clients!$F:$F, ">="&A9, Clients!$F:$F, "<"&DATE(YEAR(A9), MONTH(A9)+1, 1), Clients!$L:$L, "Premium" ) -> 6 | U9: =SUMIFS( Clients!$T:$T, Clients!$F:$F, ">="&A9, Clients!$F:$F, "<"&DATE(YEAR(A9), MONTH(A9)+1, 1) ) -> 6430 | V9: =SUMIFS( Clients!$S:$S, Clients!$F:$F, ">="&A9, Clients!$F:$F, "<"&DATE(YEAR(A9), MONTH(A9)+1, 1) ) -> 0 | W9: =SUMIFS( Clients!$U:$U, Clients!$F:$F, ">="&A9, Clients!$F:$F, "<"&DATE(YEAR(A9), MONTH(A9)+1, 1) ) -> 6430 | X9: =P9 + W9 -> 6430 | Z9: =SUMIFS( Clients!$N:$N, Clients!$F:$F,">="&$A9, Clients!$F:$F,"<"&DATE(YEAR($A9),MONTH($A9)+1,1) ) -> 980 | AA9: =R9 * KPI!$C$2 + S9 * KPI!$C$3 + T9 * KPI!$C$4 -> 740 | AB9: =SUMIFS( Clients!$W:$W, Clients!$F:$F,">="&A9, Clients!$F:$F,"<"&DATE(YEAR(A9),MONTH(A9)+1,1) ) -> 56.5 | AC9: =SUMIFS( Clients!$X:$X, Clients!$F:$F,">="&A9, Clients!$F:$F,"<"&DATE(YEAR(A9),MONTH(A9)+1,1) ) -> 770 | AD9: =SUMIFS( Clients!$AA:$AA, Clients!$F:$F,">="&$A9, Clients!$F:$F,"<"&DATE(YEAR($A9),MONTH($A9)+1,1) ) -> 522 | AE9: =SUMIFS( Clients!$AC:$AC, Clients!$R:$R,">="&$A9, Clients!$R:$R,"<"&DATE(YEAR($A9),MONTH($A9)+1,1) ) -> 0 | AF9: =KPI!$B$29 -> 441.64 | AH9: =U9 - AA9 - Z9 - AC9 - AD9 -> 3418 | AI9: =(P9 + W9 + Z9) - AA9 - AC9 - AD9 - AE9 -> 5378 | AJ9: =AI9 - C9 - AF9 -> 4186.36
A10: 45901 | B10: 217 | C10: =294.23 + 95.34 + 59.01 + 34.72 + 4.94 -> 488.24 | D10: =IF(B10=0, 0, C10/B10) -> 2.2499539 | E10: =COUNTIFS( Clients!$R:$R, ">="&A10, Clients!$R:$R, "<"&DATE(YEAR(A10), MONTH(A10)+1, 1) ) -> 15 | F10: =IF(B10=0, 0, E10/B10) -> 0.069124424 | G10: =IF(E10=0, 0, C10/E10) -> 32.549333 | I10: =IF(H10=0, 0, #REF!/H10) -> 0 | K10: =IF(H10=0, 0, J10/H10) -> 0 | L10: =IF(J10=0, 0, #REF!/J10) -> 0 | M10: =COUNTIFS( Clients!$R:$R, ">="&A10, Clients!$R:$R, "<"&DATE(YEAR(A10), MONTH(A10)+1, 1), Clients!$L:$L, "Découverte" ) -> 4 | N10: =COUNTIFS( Clients!$R:$R, ">="&A10, Clients!$R:$R, "<"&DATE(YEAR(A10), MONTH(A10)+1, 1), Clients!$L:$L, "Essentiel" ) -> 8 | O10: =COUNTIFS( Clients!$R:$R, ">="&A10, Clients!$R:$R, "<"&DATE(YEAR(A10), MONTH(A10)+1, 1), Clients!$L:$L, "Premium" ) -> 3 | P10: =SUMIFS( Clients!$S:$S, Clients!$R:$R, ">="&A10, Clients!$R:$R, "<"&DATE(YEAR(A10), MONTH(A10)+1, 1) ) -> 2250 | Q10: =COUNTIFS( Clients!$F:$F, ">="&A10, Clients!$F:$F, "<"&DATE(YEAR(A10), MONTH(A10)+1, 1) ) -> 10 | R10: =COUNTIFS( Clients!$F:$F, ">="&A10, Clients!$F:$F, "<"&DATE(YEAR(A10), MONTH(A10)+1, 1), Clients!$L:$L, "Découverte" ) -> 1 | S10: =COUNTIFS( Clients!$F:$F, ">="&A10, Clients!$F:$F, "<"&DATE(YEAR(A10), MONTH(A10)+1, 1), Clients!$L:$L, "Essentiel" ) -> 3 | T10: =COUNTIFS( Clients!$F:$F, ">="&A10, Clients!$F:$F, "<"&DATE(YEAR(A10), MONTH(A10)+1, 1), Clients!$L:$L, "Premium" ) -> 6 | U10: =SUMIFS( Clients!$T:$T, Clients!$F:$F, ">="&A10, Clients!$F:$F, "<"&DATE(YEAR(A10), MONTH(A10)+1, 1) ) -> 6510 | V10: =SUMIFS( Clients!$S:$S, Clients!$F:$F, ">="&A10, Clients!$F:$F, "<"&DATE(YEAR(A10), MONTH(A10)+1, 1) ) -> 150 | W10: =SUMIFS( Clients!$U:$U, Clients!$F:$F, ">="&A10, Clients!$F:$F, "<"&DATE(YEAR(A10), MONTH(A10)+1, 1) ) -> 6360 | X10: =P10 + W10 -> 8610 | Y10: =SUMIFS( Clients!T:T, Clients!R:R, ">=" & DATE(YEAR(A10), MONTH(A10), 1), Clients!R:R, "<" & DATE(YEAR(A10), MONTH(A10)+1, 1) ) -> 6450 | Z10: =SUMIFS( Clients!$N:$N, Clients!$F:$F,">="&$A10, Clients!$F:$F,"<"&DATE(YEAR($A10),MONTH($A10)+1,1) ) -> 700.5 | AA10: =R10 * KPI!$C$2 + S10 * KPI!$C$3 + T10 * KPI!$C$4 -> 716.87 | AB10: =SUMIFS( Clients!$W:$W, Clients!$F:$F,">="&A10, Clients!$F:$F,"<"&DATE(YEAR(A10),MONTH(A10)+1,1) ) -> 45.5 | AC10: =SUMIFS( Clients!$X:$X, Clients!$F:$F,">="&A10, Clients!$F:$F,"<"&DATE(YEAR(A10),MONTH(A10)+1,1) ) -> 700 | AD10: =SUMIFS( Clients!$AA:$AA, Clients!$F:$F,">="&$A10, Clients!$F:$F,"<"&DATE(YEAR($A10),MONTH($A10)+1,1) ) -> 343.8 | AE10: =SUMIFS( Clients!$AC:$AC, Clients!$R:$R,">="&$A10, Clients!$R:$R,"<"&DATE(YEAR($A10),MONTH($A10)+1,1) ) -> 0 | AF10: =KPI!$B$29 -> 441.64 | AG10: =U10 - AA10 -> 5793.13 | AH10: =U10 - AA10 - AC10 - AD10 -> 4749.33 | AI10: =(P10 + W10 + Z10) - AA10 - AC10 - AD10 - AE10 -> 7549.83 | AJ10: =AI10 - C10 - AF10 -> 6619.95
A11: 45931 | B11: 278 | C11: =94.42+2.56+16.72+827.63+32.1 -> 973.43 | D11: =IF(B11=0, 0, C11/B11) -> 3.5015468 | E11: =COUNTIFS( Clients!$R:$R, ">="&A11, Clients!$R:$R, "<"&DATE(YEAR(A11), MONTH(A11)+1, 1) ) -> 23 | F11: =IF(B11=0, 0, E11/B11) -> 0.082733813 | G11: =IF(E11=0, 0, C11/E11) -> 42.323043 | I11: =IF(H11=0, 0, #REF!/H11) -> 0 | K11: =IF(H11=0, 0, J11/H11) -> 0 | L11: =IF(J11=0, 0, #REF!/J11) -> 0 | M11: =COUNTIFS( Clients!$R:$R, ">="&A11, Clients!$R:$R, "<"&DATE(YEAR(A11), MONTH(A11)+1, 1), Clients!$L:$L, "Découverte" ) -> 10 | N11: =COUNTIFS( Clients!$R:$R, ">="&A11, Clients!$R:$R, "<"&DATE(YEAR(A11), MONTH(A11)+1, 1), Clients!$L:$L, "Essentiel" ) -> 9 | O11: =COUNTIFS( Clients!$R:$R, ">="&A11, Clients!$R:$R, "<"&DATE(YEAR(A11), MONTH(A11)+1, 1), Clients!$L:$L, "Premium" ) -> 4 | P11: =SUMIFS( Clients!$S:$S, Clients!$R:$R, ">="&A11, Clients!$R:$R, "<"&DATE(YEAR(A11), MONTH(A11)+1, 1) ) -> 3450 | Q11: =COUNTIFS( Clients!$F:$F, ">="&A11, Clients!$F:$F, "<"&DATE(YEAR(A11), MONTH(A11)+1, 1) ) -> 9 | R11: =COUNTIFS( Clients!$F:$F, ">="&A11, Clients!$F:$F, "<"&DATE(YEAR(A11), MONTH(A11)+1, 1), Clients!$L:$L, "Découverte" ) -> 4 | S11: =COUNTIFS( Clients!$F:$F, ">="&A11, Clients!$F:$F, "<"&DATE(YEAR(A11), MONTH(A11)+1, 1), Clients!$L:$L, "Essentiel" ) -> 2 | T11: =COUNTIFS( Clients!$F:$F, ">="&A11, Clients!$F:$F, "<"&DATE(YEAR(A11), MONTH(A11)+1, 1), Clients!$L:$L, "Premium" ) -> 3 | U11: =SUMIFS( Clients!$T:$T, Clients!$F:$F, ">="&A11, Clients!$F:$F, "<"&DATE(YEAR(A11), MONTH(A11)+1, 1) ) -> 3995 | V11: =SUMIFS( Clients!$S:$S, Clients!$F:$F, ">="&A11, Clients!$F:$F, "<"&DATE(YEAR(A11), MONTH(A11)+1, 1) ) -> 900 | W11: =SUMIFS( Clients!$U:$U, Clients!$F:$F, ">="&A11, Clients!$F:$F, "<"&DATE(YEAR(A11), MONTH(A11)+1, 1) ) -> 3095 | X11: =P11 + W11 -> 6545 | Y11: =SUMIFS( Clients!T:T, Clients!R:R, ">=" & DATE(YEAR(A11), MONTH(A11), 1), Clients!R:R, "<" & DATE(YEAR(A11), MONTH(A11)+1, 1) ) -> 10160 | Z11: =SUMIFS( Clients!$N:$N, Clients!$F:$F,">="&$A11, Clients!$F:$F,"<"&DATE(YEAR($A11),MONTH($A11)+1,1) ) -> 595 | AA11: =R11 * KPI!$C$2 + S11 * KPI!$C$3 + T11 * KPI!$C$4 -> 462.48 | AB11: =SUMIFS( Clients!$W:$W, Clients!$F:$F,">="&A11, Clients!$F:$F,"<"&DATE(YEAR(A11),MONTH(A11)+1,1) ) -> 36.5 | AC11: =AB11*14 -> 511 | AD11: =SUMIFS( Clients!$AA:$AA, Clients!$F:$F,">="&$A11, Clients!$F:$F,"<"&DATE(YEAR($A11),MONTH($A11)+1,1) ) -> 266.4 | AE11: =SUMIFS( Clients!$AC:$AC, Clients!$R:$R,">="&$A11, Clients!$R:$R,"<"&DATE(YEAR($A11),MONTH($A11)+1,1) ) -> 170 | AF11: =KPI!$B$29 -> 441.64 | AG11: =U11 - AA11 -> 3532.52 | AH11: =U11 - AA11 - AC11 - AD11 -> 2755.12 | AI11: =(P11 + W11 + Z11) - AA11 - AC11 - AD11 - AE11 -> 5730.12 | AJ11: =AI11 - C11 - AF11 -> 4315.05
A12: 45962 | B12: 194 | C12: 1019.49 | D12: =IF(B12=0, 0, C12/B12) -> 5.2551031 | E12: =COUNTIFS( Clients!$R:$R, ">="&A12, Clients!$R:$R, "<"&DATE(YEAR(A12), MONTH(A12)+1, 1) ) -> 19 | F12: =IF(B12=0, 0, E12/B12) -> 0.097938144 | G12: =IF(E12=0, 0, C12/E12) -> 53.657368 | I12: =IF(H12=0, 0, #REF!/H12) -> 0 | K12: =IF(H12=0, 0, J12/H12) -> 0 | L12: =IF(J12=0, 0, #REF!/J12) -> 0 | M12: =COUNTIFS( Clients!$R:$R, ">="&A12, Clients!$R:$R, "<"&DATE(YEAR(A12), MONTH(A12)+1, 1), Clients!$L:$L, "Découverte" ) -> 2 | N12: =COUNTIFS( Clients!$R:$R, ">="&A12, Clients!$R:$R, "<"&DATE(YEAR(A12), MONTH(A12)+1, 1), Clients!$L:$L, "Essentiel" ) -> 15 | O12: =COUNTIFS( Clients!$R:$R, ">="&A12, Clients!$R:$R, "<"&DATE(YEAR(A12), MONTH(A12)+1, 1), Clients!$L:$L, "Premium" ) -> 2 | P12: =SUMIFS( Clients!$S:$S, Clients!$R:$R, ">="&A12, Clients!$R:$R, "<"&DATE(YEAR(A12), MONTH(A12)+1, 1) ) -> 2850 | Q12: =COUNTIFS( Clients!$F:$F, ">="&A12, Clients!$F:$F, "<"&DATE(YEAR(A12), MONTH(A12)+1, 1) ) -> 6 | R12: =COUNTIFS( Clients!$F:$F, ">="&A12, Clients!$F:$F, "<"&DATE(YEAR(A12), MONTH(A12)+1, 1), Clients!$L:$L, "Découverte" ) -> 4 | S12: =COUNTIFS( Clients!$F:$F, ">="&A12, Clients!$F:$F, "<"&DATE(YEAR(A12), MONTH(A12)+1, 1), Clients!$L:$L, "Essentiel" ) -> 2 | T12: =COUNTIFS( Clients!$F:$F, ">="&A12, Clients!$F:$F, "<"&DATE(YEAR(A12), MONTH(A12)+1, 1), Clients!$L:$L, "Premium" ) -> 0 | U12: =SUMIFS( Clients!$T:$T, Clients!$F:$F, ">="&A12, Clients!$F:$F, "<"&DATE(YEAR(A12), MONTH(A12)+1, 1) ) -> 2223 | V12: =SUMIFS( Clients!$S:$S, Clients!$F:$F, ">="&A12, Clients!$F:$F, "<"&DATE(YEAR(A12), MONTH(A12)+1, 1) ) -> 750 | W12: =SUMIFS( Clients!$U:$U, Clients!$F:$F, ">="&A12, Clients!$F:$F, "<"&DATE(YEAR(A12), MONTH(A12)+1, 1) ) -> 1473 | X12: =P12 + W12 -> 4323 | Y12: =SUMIFS( Clients!T:T, Clients!R:R, ">=" & DATE(YEAR(A12), MONTH(A12), 1), Clients!R:R, "<" & DATE(YEAR(A12), MONTH(A12)+1, 1) ) -> 9050 | Z12: =SUMIFS( Clients!$N:$N, Clients!$F:$F,">="&$A12, Clients!$F:$F,"<"&DATE(YEAR($A12),MONTH($A12)+1,1) ) -> 370 | AA12: =R12 * KPI!$C$2 + S12 * KPI!$C$3 + T12 * KPI!$C$4 -> 184.98 | AB12: =SUMIFS( Clients!$W:$W, Clients!$F:$F,">="&A12, Clients!$F:$F,"<"&DATE(YEAR(A12),MONTH(A12)+1,1) ) -> 21 | AC12: =AB12*14 -> 294 | AD12: =SUMIFS( Clients!$AA:$AA, Clients!$F:$F,">="&$A12, Clients!$F:$F,"<"&DATE(YEAR($A12),MONTH($A12)+1,1) ) -> 128.4 | AE12: =SUMIFS( Clients!$AC:$AC, Clients!$R:$R,">="&$A12, Clients!$R:$R,"<"&DATE(YEAR($A12),MONTH($A12)+1,1) ) -> 270 | AF12: =KPI!$B$29 -> 441.64 | AG12: =U12 - AA12 -> 2038.02 | AH12: =U12 - AA12 - AC12 - AD12 -> 1615.62 | AI12: =(P12 + W12 + Z12) - AA12 - AC12 - AD12 - AE12 -> 3815.62 | AJ12: =AI12 - C12 - AF12 -> 2354.49
A13: 45992 | B13: 172 | C13: =812.41+98.53 -> 910.94 | D13: =IF(B13=0, 0, C13/B13) -> 5.2961628 | E13: =COUNTIFS( Clients!$R:$R, ">="&A13, Clients!$R:$R, "<"&DATE(YEAR(A13), MONTH(A13)+1, 1) ) -> 11 | F13: =IF(B13=0, 0, E13/B13) -> 0.063953488 | G13: =IF(E13=0, 0, C13/E13) -> 82.812727 | H13: 193 | I13: =IF(H13=0, 0, C13/H13) -> 4.7198964 | K13: =IF(H13=0, 0, J13/H13) -> 0 | L13: =IF(J13=0, 0, #REF!/J13) -> 0 | M13: =COUNTIFS( Clients!$R:$R, ">="&A13, Clients!$R:$R, "<"&DATE(YEAR(A13), MONTH(A13)+1, 1), Clients!$L:$L, "Découverte" ) -> 1 | N13: =COUNTIFS( Clients!$R:$R, ">="&A13, Clients!$R:$R, "<"&DATE(YEAR(A13), MONTH(A13)+1, 1), Clients!$L:$L, "Essentiel" ) -> 7 | O13: =COUNTIFS( Clients!$R:$R, ">="&A13, Clients!$R:$R, "<"&DATE(YEAR(A13), MONTH(A13)+1, 1), Clients!$L:$L, "Premium" ) -> 3 | P13: =SUMIFS( Clients!$S:$S, Clients!$R:$R, ">="&A13, Clients!$R:$R, "<"&DATE(YEAR(A13), MONTH(A13)+1, 1) ) -> 1977 | Q13: =COUNTIFS( Clients!$F:$F, ">="&A13, Clients!$F:$F, "<"&DATE(YEAR(A13), MONTH(A13)+1, 1) ) -> 7 | R13: =COUNTIFS( Clients!$F:$F, ">="&A13, Clients!$F:$F, "<"&DATE(YEAR(A13), MONTH(A13)+1, 1), Clients!$L:$L, "Découverte" ) -> 1 | S13: =COUNTIFS( Clients!$F:$F, ">="&A13, Clients!$F:$F, "<"&DATE(YEAR(A13), MONTH(A13)+1, 1), Clients!$L:$L, "Essentiel" ) -> 4 | T13: =COUNTIFS( Clients!$F:$F, ">="&A13, Clients!$F:$F, "<"&DATE(YEAR(A13), MONTH(A13)+1, 1), Clients!$L:$L, "Premium" ) -> 2 | U13: =SUMIFS( Clients!$T:$T, Clients!$F:$F, ">="&A13, Clients!$F:$F, "<"&DATE(YEAR(A13), MONTH(A13)+1, 1) ) -> 2969 | V13: =SUMIFS( Clients!$S:$S, Clients!$F:$F, ">="&A13, Clients!$F:$F, "<"&DATE(YEAR(A13), MONTH(A13)+1, 1) ) -> 600 | W13: =SUMIFS( Clients!$U:$U, Clients!$F:$F, ">="&A13, Clients!$F:$F, "<"&DATE(YEAR(A13), MONTH(A13)+1, 1) ) -> 2369 | X13: =P13 + W13 -> 4346 | Y13: =SUMIFS( Clients!T:T, Clients!R:R, ">=" & DATE(YEAR(A13), MONTH(A13), 1), Clients!R:R, "<" & DATE(YEAR(A13), MONTH(A13)+1, 1) ) -> 5566 | Z13: =SUMIFS( Clients!$N:$N, Clients!$F:$F,">="&$A13, Clients!$F:$F,"<"&DATE(YEAR($A13),MONTH($A13)+1,1) ) -> 310 | AA13: =R13 * KPI!$C$2 + S13 * KPI!$C$3 + T13 * KPI!$C$4 -> 393.12 | AB13: =SUMIFS( Clients!$W:$W, Clients!$F:$F,">="&A13, Clients!$F:$F,"<"&DATE(YEAR(A13),MONTH(A13)+1,1) ) -> 33.5 | AC13: =AB13*14 -> 469 | AD13: =SUMIFS( Clients!$AA:$AA, Clients!$F:$F,">="&$A13, Clients!$F:$F,"<"&DATE(YEAR($A13),MONTH($A13)+1,1) ) -> 225.9 | AE13: =SUMIFS( Clients!$AC:$AC, Clients!$R:$R,">="&$A13, Clients!$R:$R,"<"&DATE(YEAR($A13),MONTH($A13)+1,1) ) -> 100 | AF13: =KPI!$B$29 -> 441.64 | AG13: =U13 - AA13 -> 2575.88 | AH13: =U13 - AA13 - AC13 - AD13 -> 1880.98 | AI13: =(P13 + W13 + Z13) - AA13 - AC13 - AD13 - AE13 -> 3467.98 | AJ13: =AI13 - C13 - AF13 -> 2115.4
A15: 2025 | P15: =sum(P10:P13) -> 10527 | U15: =SUM(U2:U13) -> 34377 | V15: =SUM(V2:V13) -> 2400 | W15: =SUM(W2:W13) -> 31977 | X15: =SUM(X2:X13) -> 42504
X16: =SUM(P16:W16) -> 0
A17: 46023 | D17: =C17/B17 -> #DIV/0! | E17: =COUNTIFS(Clients!$R32:R$53,">="&DATE(2026,1,1), Clients!$R32:R$53,"<"&DATE(2026,2,1)) -> 4 | F17: =E17/B17 -> #DIV/0! | G17: =C17/E17 -> 0 | I17: =#REF!/H17 -> #REF! | J17: =COUNTIFS(Clients!$R32:X$53,">="&DATE(2026,1,1), Clients!$R32:X$53,"<"&DATE(2026,2,1)) -> 4 | K17: =J17/H17 -> #DIV/0! | L17: =#REF!/J17 -> #REF! | M17: =COUNTIFS(Clients!$L32:$L$53, "Découverte", Clients!$R32:$R$53, ">="&EOMONTH(Stats!$A17, -1)+1, Clients!$R32:$R$53, "<="&EOMONTH(Stats!$A17, 0)) -> 1 | N17: =COUNTIFS(Clients!$L32:$L$53, "Essentiel", Clients!$R32:$R$53, ">="&EOMONTH(Stats!$A17, -1)+1, Clients!$R32:$R$53, "<="&EOMONTH(Stats!$A17, 0)) -> 2 | O17: =COUNTIFS(Clients!$L32:$L$53, "Premium", Clients!$R32:$R$53, ">="&EOMONTH(Stats!$A17, -1)+1, Clients!$R32:$R$53, "<="&EOMONTH(Stats!$A17, 0)) -> 1 | P17: =SUMPRODUCT(Clients!$S32:$S$53 * (Clients!$R32:$R$53 >= EOMONTH(Stats!$A17, -1)+1) * (Clients!$R32:$R$53 <= EOMONTH(Stats!$A17, 0))) -> 690 | U17: =SUMPRODUCT(Clients!$T32:$T$53, (Clients!$F32:$F$53 >= EOMONTH(Stats!$A17, -1)+1) * (Clients!$F32:$F$53 <= EOMONTH(Stats!$A17, 0))) -> 4117.4 | V17: =SUMPRODUCT(Clients!$S32:$S$53, (Clients!$F32:$F$53 >= EOMONTH(Stats!$A17, -1)+1) * (Clients!$F32:$F$53 <= EOMONTH(Stats!$A17, 0))) -> 960 | W17: =SUMPRODUCT(Clients!$U32:$U$53, (Clients!$F32:$F$53 >= EOMONTH(Stats!$A17, -1)+1) * (Clients!$F32:$F$53 <= EOMONTH(Stats!$A17, 0))) -> 3157.4 | X17: =SUM(P17:W17) -> 8924.8
A18: 46054 | D18: =C18/B18 -> #DIV/0! | E18: =COUNTIFS(Clients!$R32:R$53,">="&DATE(2026,2,1), Clients!$R32:R$53,"<"&DATE(2026,3,1)) -> 0 | F18: =E18/B18 -> #DIV/0! | G18: =C18/E18 -> #DIV/0! | I18: =#REF!/H18 -> #REF! | J18: =COUNTIFS(Clients!$R32:X$53,">="&DATE(2026,2,1), Clients!$R32:X$53,"<"&DATE(2026,3,1)) -> 0 | K18: =J18/H18 -> #DIV/0! | L18: =#REF!/J18 -> #REF! | M18: =COUNTIFS(Clients!$L32:$L$53, "Découverte", Clients!$R32:$R$53, ">="&EOMONTH(Stats!$A18, -1)+1, Clients!$R32:$R$53, "<="&EOMONTH(Stats!$A18, 0)) -> 0 | N18: =COUNTIFS(Clients!$L32:$L$53, "Essentiel", Clients!$R32:$R$53, ">="&EOMONTH(Stats!$A18, -1)+1, Clients!$R32:$R$53, "<="&EOMONTH(Stats!$A18, 0)) -> 0 | O18: =COUNTIFS(Clients!$L32:$L$53, "Premium", Clients!$R32:$R$53, ">="&EOMONTH(Stats!$A18, -1)+1, Clients!$R32:$R$53, "<="&EOMONTH(Stats!$A18, 0)) -> 0 | P18: =SUMPRODUCT(Clients!$S32:$S$53 * (Clients!$R32:$R$53 >= EOMONTH(Stats!$A18, -1)+1) * (Clients!$R32:$R$53 <= EOMONTH(Stats!$A18, 0))) -> 0 | U18: =SUMPRODUCT(Clients!$T32:$T$53, (Clients!$F32:$F$53 >= EOMONTH(Stats!$A18, -1)+1) * (Clients!$F32:$F$53 <= EOMONTH(Stats!$A18, 0))) -> 548.9 | V18: =SUMPRODUCT(Clients!$S32:$S$53, (Clients!$F32:$F$53 >= EOMONTH(Stats!$A18, -1)+1) * (Clients!$F32:$F$53 <= EOMONTH(Stats!$A18, 0))) -> 190 | W18: =SUMPRODUCT(Clients!$U32:$U$53, (Clients!$F32:$F$53 >= EOMONTH(Stats!$A18, -1)+1) * (Clients!$F32:$F$53 <= EOMONTH(Stats!$A18, 0))) -> 358.9 | X18: =SUM(P18:W18) -> 1097.8
A19: 46082 | D19: =C19/B19 -> #DIV/0! | E19: =COUNTIFS(Clients!$R32:R$53,">="&DATE(2026,3,1), Clients!$R32:R$53,"<"&DATE(2026,4,1)) -> 0 | F19: =E19/B19 -> #DIV/0! | G19: =C19/E19 -> #DIV/0! | I19: =#REF!/H19 -> #REF! | J19: =COUNTIFS(Clients!$R32:X$53,">="&DATE(2026,3,1), Clients!$R32:X$53,"<"&DATE(2026,4,1)) -> 0 | K19: =J19/H19 -> #DIV/0! | L19: =#REF!/J19 -> #REF! | M19: =COUNTIFS(Clients!$L32:$L$53, "Découverte", Clients!$R32:$R$53, ">="&EOMONTH(Stats!$A19, -1)+1, Clients!$R32:$R$53, "<="&EOMONTH(Stats!$A19, 0)) -> 0 | N19: =COUNTIFS(Clients!$L32:$L$53, "Essentiel", Clients!$R32:$R$53, ">="&EOMONTH(Stats!$A19, -1)+1, Clients!$R32:$R$53, "<="&EOMONTH(Stats!$A19, 0)) -> 0 | O19: =COUNTIFS(Clients!$L32:$L$53, "Premium", Clients!$R32:$R$53, ">="&EOMONTH(Stats!$A19, -1)+1, Clients!$R32:$R$53, "<="&EOMONTH(Stats!$A19, 0)) -> 0 | P19: =SUMPRODUCT(Clients!$S32:$S$53 * (Clients!$R32:$R$53 >= EOMONTH(Stats!$A19, -1)+1) * (Clients!$R32:$R$53 <= EOMONTH(Stats!$A19, 0))) -> 0 | U19: =SUMPRODUCT(Clients!$T32:$T$53, (Clients!$F32:$F$53 >= EOMONTH(Stats!$A19, -1)+1) * (Clients!$F32:$F$53 <= EOMONTH(Stats!$A19, 0))) -> 1508 | V19: =SUMPRODUCT(Clients!$S32:$S$53, (Clients!$F32:$F$53 >= EOMONTH(Stats!$A19, -1)+1) * (Clients!$F32:$F$53 <= EOMONTH(Stats!$A19, 0))) -> 499 | W19: =SUMPRODUCT(Clients!$U32:$U$53, (Clients!$F32:$F$53 >= EOMONTH(Stats!$A19, -1)+1) * (Clients!$F32:$F$53 <= EOMONTH(Stats!$A19, 0))) -> 1009 | X19: =SUM(P19:W19) -> 3016
A20: 46113 | D20: =C20/B20 -> #DIV/0! | E20: =COUNTIFS(Clients!$R32:R$53,">="&DATE(2026,4,1), Clients!$R32:R$53,"<"&DATE(2026,5,1)) -> 0 | F20: =E20/B20 -> #DIV/0! | G20: =C20/E20 -> #DIV/0! | I20: =#REF!/H20 -> #REF! | J20: =COUNTIFS(Clients!$R32:X$53,">="&DATE(2026,4,1), Clients!$R32:X$53,"<"&DATE(2026,5,1)) -> 0 | K20: =J20/H20 -> #DIV/0! | L20: =#REF!/J20 -> #REF! | M20: =COUNTIFS(Clients!$L32:$L$53, "Découverte", Clients!$R32:$R$53, ">="&EOMONTH(Stats!$A20, -1)+1, Clients!$R32:$R$53, "<="&EOMONTH(Stats!$A20, 0)) -> 0 | N20: =COUNTIFS(Clients!$L32:$L$53, "Essentiel", Clients!$R32:$R$53, ">="&EOMONTH(Stats!$A20, -1)+1, Clients!$R32:$R$53, "<="&EOMONTH(Stats!$A20, 0)) -> 0 | O20: =COUNTIFS(Clients!$L32:$L$53, "Premium", Clients!$R32:$R$53, ">="&EOMONTH(Stats!$A20, -1)+1, Clients!$R32:$R$53, "<="&EOMONTH(Stats!$A20, 0)) -> 0 | P20: =SUMPRODUCT(Clients!$S32:$S$53 * (Clients!$R32:$R$53 >= EOMONTH(Stats!$A20, -1)+1) * (Clients!$R32:$R$53 <= EOMONTH(Stats!$A20, 0))) -> 0 | U20: =SUMPRODUCT(Clients!$T32:$T$53, (Clients!$F32:$F$53 >= EOMONTH(Stats!$A20, -1)+1) * (Clients!$F32:$F$53 <= EOMONTH(Stats!$A20, 0))) -> 1360 | V20: =SUMPRODUCT(Clients!$S32:$S$53, (Clients!$F32:$F$53 >= EOMONTH(Stats!$A20, -1)+1) * (Clients!$F32:$F$53 <= EOMONTH(Stats!$A20, 0))) -> 450 | W20: =SUMPRODUCT(Clients!$U32:$U$53, (Clients!$F32:$F$53 >= EOMONTH(Stats!$A20, -1)+1) * (Clients!$F32:$F$53 <= EOMONTH(Stats!$A20, 0))) -> 910 | X20: =SUM(P20:W20) -> 2720
A21: 46143 | D21: =C21/B21 -> #DIV/0! | E21: =COUNTIFS(Clients!$R32:R$53,">="&DATE(2026,5,1), Clients!$R32:R$53,"<"&DATE(2026,6,1)) -> 0 | F21: =E21/B21 -> #DIV/0! | G21: =C21/E21 -> #DIV/0! | I21: =#REF!/H21 -> #REF! | J21: =COUNTIFS(Clients!$R32:X$53,">="&DATE(2026,5,1), Clients!$R32:X$53,"<"&DATE(2026,6,1)) -> 0 | K21: =J21/H21 -> #DIV/0! | L21: =#REF!/J21 -> #REF! | M21: =COUNTIFS(Clients!$L32:$L$53, "Découverte", Clients!$R32:$R$53, ">="&EOMONTH(Stats!$A21, -1)+1, Clients!$R32:$R$53, "<="&EOMONTH(Stats!$A21, 0)) -> 0 | N21: =COUNTIFS(Clients!$L32:$L$53, "Essentiel", Clients!$R32:$R$53, ">="&EOMONTH(Stats!$A21, -1)+1, Clients!$R32:$R$53, "<="&EOMONTH(Stats!$A21, 0)) -> 0 | O21: =COUNTIFS(Clients!$L32:$L$53, "Premium", Clients!$R32:$R$53, ">="&EOMONTH(Stats!$A21, -1)+1, Clients!$R32:$R$53, "<="&EOMONTH(Stats!$A21, 0)) -> 0 | P21: =SUMPRODUCT(Clients!$S32:$S$53 * (Clients!$R32:$R$53 >= EOMONTH(Stats!$A21, -1)+1) * (Clients!$R32:$R$53 <= EOMONTH(Stats!$A21, 0))) -> 0 | U21: =SUMPRODUCT(Clients!$T32:$T$53, (Clients!$F32:$F$53 >= EOMONTH(Stats!$A21, -1)+1) * (Clients!$F32:$F$53 <= EOMONTH(Stats!$A21, 0))) -> 3120 | V21: =SUMPRODUCT(Clients!$S32:$S$53, (Clients!$F32:$F$53 >= EOMONTH(Stats!$A21, -1)+1) * (Clients!$F32:$F$53 <= EOMONTH(Stats!$A21, 0))) -> 1080 | W21: =SUMPRODUCT(Clients!$U32:$U$53, (Clients!$F32:$F$53 >= EOMONTH(Stats!$A21, -1)+1) * (Clients!$F32:$F$53 <= EOMONTH(Stats!$A21, 0))) -> 2190 | X21: =SUM(P21:W21) -> 6390
A22: 46174 | D22: =C22/B22 -> #DIV/0! | E22: =COUNTIFS(Clients!$R32:R$53,">="&DATE(2026,6,1), Clients!$R32:R$53,"<"&DATE(2026,7,1)) -> 0 | F22: =E22/B22 -> #DIV/0! | G22: =C22/E22 -> #DIV/0! | I22: =#REF!/H22 -> #REF! | J22: =COUNTIFS(Clients!$R32:X$53,">="&DATE(2026,6,1), Clients!$R32:X$53,"<"&DATE(2026,7,1)) -> 0 | K22: =J22/H22 -> #DIV/0! | L22: =#REF!/J22 -> #REF! | M22: =COUNTIFS(Clients!$L32:$L$53, "Découverte", Clients!$R32:$R$53, ">="&EOMONTH(Stats!$A22, -1)+1, Clients!$R32:$R$53, "<="&EOMONTH(Stats!$A22, 0)) -> 0 | N22: =COUNTIFS(Clients!$L32:$L$53, "Essentiel", Clients!$R32:$R$53, ">="&EOMONTH(Stats!$A22, -1)+1, Clients!$R32:$R$53, "<="&EOMONTH(Stats!$A22, 0)) -> 0 | O22: =COUNTIFS(Clients!$L32:$L$53, "Premium", Clients!$R32:$R$53, ">="&EOMONTH(Stats!$A22, -1)+1, Clients!$R32:$R$53, "<="&EOMONTH(Stats!$A22, 0)) -> 0 | P22: =SUMPRODUCT(Clients!$S32:$S$53 * (Clients!$R32:$R$53 >= EOMONTH(Stats!$A22, -1)+1) * (Clients!$R32:$R$53 <= EOMONTH(Stats!$A22, 0))) -> 0 | U22: =SUMPRODUCT(Clients!$T32:$T$53, (Clients!$F32:$F$53 >= EOMONTH(Stats!$A22, -1)+1) * (Clients!$F32:$F$53 <= EOMONTH(Stats!$A22, 0))) -> 5180 | V22: =SUMPRODUCT(Clients!$S32:$S$53, (Clients!$F32:$F$53 >= EOMONTH(Stats!$A22, -1)+1) * (Clients!$F32:$F$53 <= EOMONTH(Stats!$A22, 0))) -> 1680 | W22: =SUMPRODUCT(Clients!$U32:$U$53, (Clients!$F32:$F$53 >= EOMONTH(Stats!$A22, -1)+1) * (Clients!$F32:$F$53 <= EOMONTH(Stats!$A22, 0))) -> 3500 | X22: =SUM(P22:W22) -> 10360
A23: 46204 | D23: =C23/B23 -> #DIV/0! | E23: =COUNTIFS(Clients!$R32:R$53,">="&DATE(2026,7,1), Clients!$R32:R$53,"<"&DATE(2026,8,1)) -> 0 | F23: =E23/B23 -> #DIV/0! | G23: =C23/E23 -> #DIV/0! | I23: =#REF!/H23 -> #REF! | J23: =COUNTIFS(Clients!$R32:X$53,">="&DATE(2026,7,1), Clients!$R32:X$53,"<"&DATE(2026,8,1)) -> 0 | K23: =J23/H23 -> #DIV/0! | L23: =#REF!/J23 -> #REF! | M23: =COUNTIFS(Clients!$L32:$L$53, "Découverte", Clients!$R32:$R$53, ">="&EOMONTH(Stats!$A23, -1)+1, Clients!$R32:$R$53, "<="&EOMONTH(Stats!$A23, 0)) -> 0 | N23: =COUNTIFS(Clients!$L32:$L$53, "Essentiel", Clients!$R32:$R$53, ">="&EOMONTH(Stats!$A23, -1)+1, Clients!$R32:$R$53, "<="&EOMONTH(Stats!$A23, 0)) -> 0 | O23: =COUNTIFS(Clients!$L32:$L$53, "Premium", Clients!$R32:$R$53, ">="&EOMONTH(Stats!$A23, -1)+1, Clients!$R32:$R$53, "<="&EOMONTH(Stats!$A23, 0)) -> 0 | P23: =SUMPRODUCT(Clients!$S32:$S$53 * (Clients!$R32:$R$53 >= EOMONTH(Stats!$A23, -1)+1) * (Clients!$R32:$R$53 <= EOMONTH(Stats!$A23, 0))) -> 0 | U23: =SUMPRODUCT(Clients!$T32:$T$53, (Clients!$F32:$F$53 >= EOMONTH(Stats!$A23, -1)+1) * (Clients!$F32:$F$53 <= EOMONTH(Stats!$A23, 0))) -> 5690 | V23: =SUMPRODUCT(Clients!$S32:$S$53, (Clients!$F32:$F$53 >= EOMONTH(Stats!$A23, -1)+1) * (Clients!$F32:$F$53 <= EOMONTH(Stats!$A23, 0))) -> 1930 | W23: =SUMPRODUCT(Clients!$U32:$U$53, (Clients!$F32:$F$53 >= EOMONTH(Stats!$A23, -1)+1) * (Clients!$F32:$F$53 <= EOMONTH(Stats!$A23, 0))) -> 3910 | X23: =SUM(P23:W23) -> 11530
A24: 46235 | D24: =C24/B24 -> #DIV/0! | E24: =COUNTIFS(Clients!$R32:R$53,">="&DATE(2026,8,1), Clients!$R32:R$53,"<"&DATE(2026,9,1)) -> 0 | F24: =E24/B24 -> #DIV/0! | G24: =C24/E24 -> #DIV/0! | I24: =#REF!/H24 -> #REF! | J24: =COUNTIFS(Clients!$R32:X$53,">="&DATE(2026,8,1), Clients!$R32:X$53,"<"&DATE(2026,9,1)) -> 0 | K24: =J24/H24 -> #DIV/0! | L24: =#REF!/J24 -> #REF! | M24: =COUNTIFS(Clients!$L32:$L$53, "Découverte", Clients!$R32:$R$53, ">="&EOMONTH(Stats!$A24, -1)+1, Clients!$R32:$R$53, "<="&EOMONTH(Stats!$A24, 0)) -> 0 | N24: =COUNTIFS(Clients!$L32:$L$53, "Essentiel", Clients!$R32:$R$53, ">="&EOMONTH(Stats!$A24, -1)+1, Clients!$R32:$R$53, "<="&EOMONTH(Stats!$A24, 0)) -> 0 | O24: =COUNTIFS(Clients!$L32:$L$53, "Premium", Clients!$R32:$R$53, ">="&EOMONTH(Stats!$A24, -1)+1, Clients!$R32:$R$53, "<="&EOMONTH(Stats!$A24, 0)) -> 0 | P24: =SUMPRODUCT(Clients!$S32:$S$53 * (Clients!$R32:$R$53 >= EOMONTH(Stats!$A24, -1)+1) * (Clients!$R32:$R$53 <= EOMONTH(Stats!$A24, 0))) -> 0 | U24: =SUMPRODUCT(Clients!$T32:$T$53, (Clients!$F32:$F$53 >= EOMONTH(Stats!$A24, -1)+1) * (Clients!$F32:$F$53 <= EOMONTH(Stats!$A24, 0))) -> 4988 | V24: =SUMPRODUCT(Clients!$S32:$S$53, (Clients!$F32:$F$53 >= EOMONTH(Stats!$A24, -1)+1) * (Clients!$F32:$F$53 <= EOMONTH(Stats!$A24, 0))) -> 1578 | W24: =SUMPRODUCT(Clients!$U32:$U$53, (Clients!$F32:$F$53 >= EOMONTH(Stats!$A24, -1)+1) * (Clients!$F32:$F$53 <= EOMONTH(Stats!$A24, 0))) -> 3410 | X24: =SUM(P24:W24) -> 9976
A25: 46266 | D25: =C25/B25 -> #DIV/0! | E25: =COUNTIFS(Clients!$R32:R$53,">="&DATE(2026,9,1), Clients!$R32:R$53,"<"&DATE(2026,10,1)) -> 0 | F25: =E25/B25 -> #DIV/0! | G25: =C25/E25 -> #DIV/0! | I25: =#REF!/H25 -> #REF! | J25: =COUNTIFS(Clients!$R32:X$53,">="&DATE(2026,9,1), Clients!$R32:X$53,"<"&DATE(2026,10,1)) -> 0 | K25: =J25/H25 -> #DIV/0! | L25: =#REF!/J25 -> #REF! | M25: =COUNTIFS(Clients!$L32:$L$53, "Découverte", Clients!$R32:$R$53, ">="&EOMONTH(Stats!$A25, -1)+1, Clients!$R32:$R$53, "<="&EOMONTH(Stats!$A25, 0)) -> 0 | N25: =COUNTIFS(Clients!$L32:$L$53, "Essentiel", Clients!$R32:$R$53, ">="&EOMONTH(Stats!$A25, -1)+1, Clients!$R32:$R$53, "<="&EOMONTH(Stats!$A25, 0)) -> 0 | O25: =COUNTIFS(Clients!$L32:$L$53, "Premium", Clients!$R32:$R$53, ">="&EOMONTH(Stats!$A25, -1)+1, Clients!$R32:$R$53, "<="&EOMONTH(Stats!$A25, 0)) -> 0 | P25: =SUMPRODUCT(Clients!$S32:$S$53 * (Clients!$R32:$R$53 >= EOMONTH(Stats!$A25, -1)+1) * (Clients!$R32:$R$53 <= EOMONTH(Stats!$A25, 0))) -> 0 | U25: =SUMPRODUCT(Clients!$T32:$T$53, (Clients!$F32:$F$53 >= EOMONTH(Stats!$A25, -1)+1) * (Clients!$F32:$F$53 <= EOMONTH(Stats!$A25, 0))) -> 905 | V25: =SUMPRODUCT(Clients!$S32:$S$53, (Clients!$F32:$F$53 >= EOMONTH(Stats!$A25, -1)+1) * (Clients!$F32:$F$53 <= EOMONTH(Stats!$A25, 0))) -> 300 | W25: =SUMPRODUCT(Clients!$U32:$U$53, (Clients!$F32:$F$53 >= EOMONTH(Stats!$A25, -1)+1) * (Clients!$F32:$F$53 <= EOMONTH(Stats!$A25, 0))) -> 605 | X25: =SUM(P25:W25) -> 1810
A26: 46296 | D26: =C26/B26 -> #DIV/0! | E26: =COUNTIFS(Clients!$R32:R$53,">="&DATE(2026,10,1), Clients!$R32:R$53,"<"&DATE(2026,11,1)) -> 0 | F26: =E26/B26 -> #DIV/0! | G26: =C26/E26 -> #DIV/0! | I26: =#REF!/H26 -> #REF! | J26: =COUNTIFS(Clients!$R32:X$53,">="&DATE(2026,10,1), Clients!$R32:X$53,"<"&DATE(2026,11,1)) -> 0 | K26: =J26/H26 -> #DIV/0! | L26: =#REF!/J26 -> #REF! | M26: =COUNTIFS(Clients!$L32:$L$53, "Découverte", Clients!$R32:$R$53, ">="&EOMONTH(Stats!$A26, -1)+1, Clients!$R32:$R$53, "<="&EOMONTH(Stats!$A26, 0)) -> 0 | N26: =COUNTIFS(Clients!$L32:$L$53, "Essentiel", Clients!$R32:$R$53, ">="&EOMONTH(Stats!$A26, -1)+1, Clients!$R32:$R$53, "<="&EOMONTH(Stats!$A26, 0)) -> 0 | O26: =COUNTIFS(Clients!$L32:$L$53, "Premium", Clients!$R32:$R$53, ">="&EOMONTH(Stats!$A26, -1)+1, Clients!$R32:$R$53, "<="&EOMONTH(Stats!$A26, 0)) -> 0 | P26: =SUMPRODUCT(Clients!$S32:$S$53 * (Clients!$R32:$R$53 >= EOMONTH(Stats!$A26, -1)+1) * (Clients!$R32:$R$53 <= EOMONTH(Stats!$A26, 0))) -> 0 | U26: =SUMPRODUCT(Clients!$T32:$T$53, (Clients!$F32:$F$53 >= EOMONTH(Stats!$A26, -1)+1) * (Clients!$F32:$F$53 <= EOMONTH(Stats!$A26, 0))) -> 1540 | V26: =SUMPRODUCT(Clients!$S32:$S$53, (Clients!$F32:$F$53 >= EOMONTH(Stats!$A26, -1)+1) * (Clients!$F32:$F$53 <= EOMONTH(Stats!$A26, 0))) -> 450 | W26: =SUMPRODUCT(Clients!$U32:$U$53, (Clients!$F32:$F$53 >= EOMONTH(Stats!$A26, -1)+1) * (Clients!$F32:$F$53 <= EOMONTH(Stats!$A26, 0))) -> 1090 | X26: =SUM(P26:W26) -> 3080
A27: 46327 | D27: =C27/B27 -> #DIV/0! | E27: =COUNTIFS(Clients!$R32:R$53,">="&DATE(2026,11,1), Clients!$R32:R$53,"<"&DATE(2026,12,1)) -> 0 | F27: =E27/B27 -> #DIV/0! | G27: =C27/E27 -> #DIV/0! | I27: =#REF!/H27 -> #REF! | J27: =COUNTIFS(Clients!$R32:X$53,">="&DATE(2026,11,1), Clients!$R32:X$53,"<"&DATE(2026,12,1)) -> 0 | K27: =J27/H27 -> #DIV/0! | L27: =#REF!/J27 -> #REF! | M27: =COUNTIFS(Clients!$L32:$L$53, "Découverte", Clients!$R32:$R$53, ">="&EOMONTH(Stats!$A27, -1)+1, Clients!$R32:$R$53, "<="&EOMONTH(Stats!$A27, 0)) -> 0 | N27: =COUNTIFS(Clients!$L32:$L$53, "Essentiel", Clients!$R32:$R$53, ">="&EOMONTH(Stats!$A27, -1)+1, Clients!$R32:$R$53, "<="&EOMONTH(Stats!$A27, 0)) -> 0 | O27: =COUNTIFS(Clients!$L32:$L$53, "Premium", Clients!$R32:$R$53, ">="&EOMONTH(Stats!$A27, -1)+1, Clients!$R32:$R$53, "<="&EOMONTH(Stats!$A27, 0)) -> 0 | P27: =SUMPRODUCT(Clients!$S32:$S$53 * (Clients!$R32:$R$53 >= EOMONTH(Stats!$A27, -1)+1) * (Clients!$R32:$R$53 <= EOMONTH(Stats!$A27, 0))) -> 0 | U27: =SUMPRODUCT(Clients!$T32:$T$53, (Clients!$F32:$F$53 >= EOMONTH(Stats!$A27, -1)+1) * (Clients!$F32:$F$53 <= EOMONTH(Stats!$A27, 0))) -> 0 | V27: =SUMPRODUCT(Clients!$S32:$S$53, (Clients!$F32:$F$53 >= EOMONTH(Stats!$A27, -1)+1) * (Clients!$F32:$F$53 <= EOMONTH(Stats!$A27, 0))) -> 0 | W27: =SUMPRODUCT(Clients!$U32:$U$53, (Clients!$F32:$F$53 >= EOMONTH(Stats!$A27, -1)+1) * (Clients!$F32:$F$53 <= EOMONTH(Stats!$A27, 0))) -> 0 | X27: =SUM(P27:W27) -> 0
A28: 46357 | D28: =C28/B28 -> #DIV/0! | E28: =COUNTIFS(Clients!$R32:R$53,">="&DATE(2026,12,1), Clients!$R32:R$53,"<"&DATE(2027,1,1)) -> 0 | F28: =E28/B28 -> #DIV/0! | G28: =C28/E28 -> #DIV/0! | I28: =#REF!/H28 -> #REF! | J28: =COUNTIFS(Clients!$R32:X$53,">="&DATE(2026,12,1), Clients!$R32:X$53,"<"&DATE(2027,1,1)) -> 0 | K28: =J28/H28 -> #DIV/0! | L28: =#REF!/J28 -> #REF! | M28: =COUNTIFS(Clients!$L32:$L$53, "Découverte", Clients!$R32:$R$53, ">="&EOMONTH(Stats!$A28, -1)+1, Clients!$R32:$R$53, "<="&EOMONTH(Stats!$A28, 0)) -> 0 | N28: =COUNTIFS(Clients!$L32:$L$53, "Essentiel", Clients!$R32:$R$53, ">="&EOMONTH(Stats!$A28, -1)+1, Clients!$R32:$R$53, "<="&EOMONTH(Stats!$A28, 0)) -> 0 | O28: =COUNTIFS(Clients!$L32:$L$53, "Premium", Clients!$R32:$R$53, ">="&EOMONTH(Stats!$A28, -1)+1, Clients!$R32:$R$53, "<="&EOMONTH(Stats!$A28, 0)) -> 0 | P28: =SUMPRODUCT(Clients!$S32:$S$53 * (Clients!$R32:$R$53 >= EOMONTH(Stats!$A28, -1)+1) * (Clients!$R32:$R$53 <= EOMONTH(Stats!$A28, 0))) -> 0 | U28: =SUMPRODUCT(Clients!$T32:$T$53, (Clients!$F32:$F$53 >= EOMONTH(Stats!$A28, -1)+1) * (Clients!$F32:$F$53 <= EOMONTH(Stats!$A28, 0))) -> 540 | V28: =SUMPRODUCT(Clients!$S32:$S$53, (Clients!$F32:$F$53 >= EOMONTH(Stats!$A28, -1)+1) * (Clients!$F32:$F$53 <= EOMONTH(Stats!$A28, 0))) -> 150 | W28: =SUMPRODUCT(Clients!$U32:$U$53, (Clients!$F32:$F$53 >= EOMONTH(Stats!$A28, -1)+1) * (Clients!$F32:$F$53 <= EOMONTH(Stats!$A28, 0))) -> 390 | X28: =SUM(P28:W28) -> 1080
A31: 2026 | P31: =SUMPRODUCT(Clients!$S32:$S$53 * (YEAR(Clients!$R32:$R$53)=Stats!$A31)) -> 690 | U31: =SUM(U17:U28) -> 29497.3 | V31: =SUM(V17:V28) -> 9267 | W31: =SUM(W17:W28) -> 20530.3 | X31: =SUM(X17:X28) -> 59984.6
A32: 2027 | P32: =SUMPRODUCT(Clients!$S32:$S$53 * (YEAR(Clients!$R32:$R$53)=Stats!$A32)) -> 0 | U32: =SUMPRODUCT(Clients!$T32:$T$53 * (YEAR(Clients!$F32:$F$53)=Stats!$A32)) -> 1430 | V32: =SUMPRODUCT(Clients!$S32:$S$53 * (YEAR(Clients!$F32:$F$53)=Stats!$A32)) -> 330 | W32: =SUMPRODUCT(Clients!$U32:$U$53 * (YEAR(Clients!$F32:$F$53)=Stats!A32)) -> 1100

Sheet Students
A1: Date | B1: Etudiant | C1: Heures | D1: Heures corrigés | E1: Rémunération | G1: Total
A2: 45931 | B2: Mouad | C2: =IF(OR($A2="",$B2=""),"",SUMIFS( Clients!$W:$W, Clients!$V:$V, $B2, Clients!$F:$F, ">="&$A2, Clients!$F:$F, "<"&DATE(YEAR($A2), MONTH($A2)+1, 1) )) -> 11 | D2: 13 | E2: =IF(C2="","", D2 * 14) -> 182 | G2: =E2 -> 182
A3: 45962 | B3: Mouad | C3: =IF(OR($A3="",$B3=""),"",SUMIFS( Clients!$W:$W, Clients!$V:$V, $B3, Clients!$F:$F, ">="&$A3, Clients!$F:$F, "<"&DATE(YEAR($A3), MONTH($A3)+1, 1) )) -> 21 | D3: 24 | E3: =IF(C3="","", D3 * 14) -> 336 | G3: =E3 -> 336
A4: 45992 | B4: Mouad | C4: =IF(OR($A4="",$B4=""),"",SUMIFS( Clients!$W:$W, Clients!$V:$V, $B4, Clients!$F:$F, ">="&$A4, Clients!$F:$F, "<"&DATE(YEAR($A4), MONTH($A4)+1, 1) )) -> 33.5 | E4: =IF(C4="","", C4 * 14) -> 469 | G4: =E4 -> 469

Sheet Commercial
A1: Date | B1: Commercial | C1: Total Calls | D1: < 30 secs (no reply) | E1: > 30 secs | F1: > 1 min | G1: > 2 min | H1: > 5 min | I1: > 5 min (%) | J1: Bonus > 5 min | K1: Calls answered | L1: Closed | M1: Conversion (%) | N1: Commissions TVAC | O1: Bonus Conv (%) | P1: CB planifiés | Q1: CB réalisés | R1: CB réalisés (%) | S1: Bonus CB | T1: Total Bonus TVAC | U1: Total TVAC | V1: Total HTVA
A2: 45962 | B2: Nizar | C2: 438 | D2: 310 | E2: 128 | F2: 98 | G2: 51 | H2: 22 | I2: =IF(K2=0,0,H2/K2) -> 0.171875 | J2: =IF(I2="",0, IF(I2>=0.2,100, IF(I2>=0.15,75, IF(I2>=0.1,50, IF(I2>=0.08,25,0) ) ) )) -> 75 | K2: =E2 -> 128 | L2: =COUNTIFS( Clients!AB:AB, "Nizar", Clients!R:R, ">=" & DATE(YEAR(A2), MONTH(A2), 1), Clients!R:R, "<" & DATE(YEAR(A2), MONTH(A2)+1, 1) ) -> 6 | M2: =IF(E2=0,0,L2/E2) -> 0.046875 | N2: =SUMIFS( Clients!AC:AC, Clients!AB:AB, "Nizar", Clients!R:R, ">=" & DATE(YEAR(A2), MONTH(A2), 1), Clients!R:R, "<" & DATE(YEAR(A2), MONTH(A2)+1, 1) ) -> 270 | O2: =IF(M2="",0, IF(M2>=0.12,150, IF(M2>=0.1,100, IF(M2>=0.08,50, IF(M2>=0.05,25, 0) ) ) )) -> 0 | P2: 40 | Q2: 1 | R2: =IF(Q2=0,0,Q2/P2) -> 0.025 | S2: =IF(R2="",0, IF(R2>=1,75, IF(R2>=0.9,50, IF(R2>=0.8,25,0) ) ) ) -> 0 | T2: 150 | U2: =IF(N2="",0,N2+T2) -> 420 | V2: =IF(U2=0,0,U2/1.21) -> 347.10744
A3: 45992 | B3: Nizar | D3: 4 | E3: 2 | F3: 2 | I3: =IF(K3=0,0,H3/K3) -> 0 | J3: =IF(I3="",0, IF(I3>=0.2,100, IF(I3>=0.15,75, IF(I3>=0.1,50, IF(I3>=0.08,25,0) ) ) )) -> 0 | K3: =E3 -> 2 | L3: =COUNTIFS( Clients!AB:AB, "Nizar", Clients!R:R, ">=" & DATE(YEAR(A3), MONTH(A3), 1), Clients!R:R, "<" & DATE(YEAR(A3), MONTH(A3)+1, 1) ) -> 0 | M3: =IF(E3=0,0,L3/E3) -> 0 | N3: =SUMIFS( Clients!AC:AC, Clients!AB:AB, "Nizar", Clients!R:R, ">=" & DATE(YEAR(A3), MONTH(A3), 1), Clients!R:R, "<" & DATE(YEAR(A3), MONTH(A3)+1, 1) ) -> 0 | O3: =IF(M3="",0, IF(M3>=0.12,150, IF(M3>=0.1,100, IF(M3>=0.08,50, IF(M3>=0.05,25, 0) ) ) )) -> 0 | R3: =IF(Q3=0,0,Q3/P3) -> 0 | S3: =IF(R3="",0, IF(R3>=1,75, IF(R3>=0.9,50, IF(R3>=0.8,25,0) ) ) ) -> 0 | T3: =IF(SUM(J3,O3)=0,0,J3+O3) -> 0 | U3: =IF(N3="",0,N3+T3) -> 0 | V3: =IF(U3=0,0,U3/1.21) -> 0
A4: 45992 | B4: Lakhdar | D4: 2 | E4: 3 | F4: 3 | G4: 3 | H4: 3 | I4: =IF(K4=0,0,H4/K4) -> 1 | J4: =IF(I4="",0, IF(I4>=0.2,100, IF(I4>=0.15,75, IF(I4>=0.1,50, IF(I4>=0.08,25,0) ) ) )) -> 100 | K4: =E4 -> 3 | L4: =COUNTIFS( Clients!AB:AB, "Nizar", Clients!R:R, ">=" & DATE(YEAR(A4), MONTH(A4), 1), Clients!R:R, "<" & DATE(YEAR(A4), MONTH(A4)+1, 1) ) -> 0 | M4: =IF(E4=0,0,L4/E4) -> 0 | N4: =SUMIFS( Clients!AC:AC, Clients!AB:AB, "Nizar", Clients!R:R, ">=" & DATE(YEAR(A4), MONTH(A4), 1), Clients!R:R, "<" & DATE(YEAR(A4), MONTH(A4)+1, 1) ) -> 0 | O4: =IF(M4="",0, IF(M4>=0.12,150, IF(M4>=0.1,100, IF(M4>=0.08,50, IF(M4>=0.05,25, 0) ) ) )) -> 0 | R4: =IF(Q4=0,0,Q4/P4) -> 0 | S4: =IF(R4="",0, IF(R4>=1,75, IF(R4>=0.9,50, IF(R4>=0.8,25,0) ) ) ) -> 0 | T4: =IF(SUM(J4,O4)=0,0,J4+O4) -> 100 | U4: =IF(N4="",0,N4+T4) -> 100 | V4: =IF(U4=0,0,U4/1.21) -> 82.644628
A5: 45992 | B5: Yassine | I5: =IF(K5=0,0,H5/K5) -> 0 | J5: =IF(I5="",0, IF(I5>=0.2,100, IF(I5>=0.15,75, IF(I5>=0.1,50, IF(I5>=0.08,25,0) ) ) )) -> 0 | K5: =E5 | L5: =COUNTIFS( Clients!AB:AB, "Nizar", Clients!R:R, ">=" & DATE(YEAR(A5), MONTH(A5), 1), Clients!R:R, "<" & DATE(YEAR(A5), MONTH(A5)+1, 1) ) -> 0 | M5: =IF(E5=0,0,L5/E5) -> 0 | N5: =SUMIFS( Clients!AC:AC, Clients!AB:AB, "Nizar", Clients!R:R, ">=" & DATE(YEAR(A5), MONTH(A5), 1), Clients!R:R, "<" & DATE(YEAR(A5), MONTH(A5)+1, 1) ) -> 0 | O5: =IF(M5="",0, IF(M5>=0.12,150, IF(M5>=0.1,100, IF(M5>=0.08,50, IF(M5>=0.05,25, 0) ) ) )) -> 0
A6: 45992 | B6: Assiyaa | C6: 81 | D6: 47 | E6: 37 | F6: 25 | G6: 7 | H6: 3 | I6: =IF(K6=0,0,H6/K6) -> 0.081081081 | J6: =IF(I6="",0, IF(I6>=0.2,100, IF(I6>=0.15,75, IF(I6>=0.1,50, IF(I6>=0.08,25,0) ) ) )) -> 25 | K6: =E6 -> 37 | L6: =COUNTIFS( Clients!AB:AB, "Assiyaa", Clients!R:R, ">=" & DATE(YEAR(A6), MONTH(A6), 1), Clients!R:R, "<" & DATE(YEAR(A6), MONTH(A6)+1, 1) ) -> 2 | M6: =IF(E6=0,0,L6/E6) -> 0.054054054 | N6: =SUMIFS( Clients!AC:AC, Clients!AB:AB, "Assiyaa", Clients!R:R, ">=" & DATE(YEAR(A6), MONTH(A6), 1), Clients!R:R, "<" & DATE(YEAR(A6), MONTH(A6)+1, 1) ) -> 100 | O6: =IF(M6="",0, IF(M6>=0.12,150, IF(M6>=0.1,100, IF(M6>=0.08,50, IF(M6>=0.05,25, 0) ) ) )) -> 25

Sheet KPI
A1: Pack | B1: Prix | C1: Coût Variable | D1: Transport | E1: Marge Unitaire | F1: Commission | G1: Point Mort | H1: acompte | I1: Nbre de pack /mois | J1: Nbre d'acompte /mois | L1: Type de bonus | M1: Condition | N1: Paliers / Montants TVAC
A2: Pack Découverte | B2: =290/1.21 -> 239.66942 | C2: 23.12 | D2: =90/1.21 -> 74.380165 | E2: =IFERROR(B2 + D2 - C2 ,"") -> 290.92959 | F2: 35 | G2: =IF(E2<=0,"",ROUNDUP($B$29/E2,0)) -> 2 | H2: =150/1.21 -> 123.96694 | L2: Bonus Conversion (%) | M2: Taux de conversion >= 8% | N2: 8% = 50€
A3: Pack Essentiel | B3: =390/1.21 -> 322.31405 | C3: 46.25 | D3: =90/1.21 -> 74.380165 | E3: =IFERROR(B3 + D3 - C3 ,"") -> 350.44421 | F3: 45 | G3: =IF(E3<=0,"",ROUNDUP($B$29/E3,0)) -> 2 | H3: =150/1.21 -> 123.96694 | N3: 10% = 100€
A4: Pack Premium | B4: =490/1.21 -> 404.95868 | C4: 92.5 | D4: =90/1.21 -> 74.380165 | E4: =IFERROR(B4 + D4 - C4 ,"") -> 386.83884 | F4: 55 | G4: =IF(E4<=0,"",ROUNDUP($B$29/E4,0)) -> 2 | H4: =150/1.21 -> 123.96694 | N4: 12% = 150€
L5: Bonus Appels > 5 min | M5: % appels > 5min (sur appels répondus) | N5: >=10% = 50€
G6: =IF(E6<=0,"",ROUNDUP('Frais Fixes '!$B$17/E6,0)) | N6: >=15% = 75€
N7: >=20% = 100€
A8: Bénéfice du mois | B8: =SUMPRODUCT(I2:I4,E2:E4) + SUMPRODUCT(J2:J4,H2:H4) - B29 -> -441.64 | L8: Bonus Callbacks | M8: % de callbacks réalisés | N8: >=80% = 25€
N9: >=90% = 50€
N10: =100% = 75€
A15: Poste | B15: Montant
A18: Zen Facture | B18: 12
A19: Abonnement Gsm +Wifi | B19: 130.48
A20: Compta | B20: 150
A21: Garage | B21: 120
A22: Canva | B22: 9.16
A23: Chat gpt | B23: 20
A29: Total | B29: =SUM(B16:B28) -> 441.64

Sheet Compta
D1: Income | E1: Expenses
C3: YTD | D3: =IFERROR(__xludf.DUMMYFUNCTION("SUM(FILTER(ARRAYFORMULA(VALUE(SUBSTITUTE(SUBSTITUTE(E128:E287,""€"",""""),"" "",""""))), ARRAYFORMULA(VALUE(SUBSTITUTE(SUBSTITUTE(E128:E287,""€"",""""),"" "",""""))) > 0)) "),17462.9) -> 17462.9 | E3: =IFERROR(__xludf.DUMMYFUNCTION("SUM(FILTER(ARRAYFORMULA(VALUE(SUBSTITUTE(SUBSTITUTE(E128:E287,""€"",""""),"" "",""""))), ARRAYFORMULA(VALUE(SUBSTITUTE(SUBSTITUTE(E128:E287,""€"",""""),"" "",""""))) < 0)) "),-26503.76000000001) -> -26503.76
E5: =sum(D3:E3) -> -9040.86
C9: TOP 5 & 10
C10: =IFERROR(__xludf.DUMMYFUNCTION("ARRAY_CONSTRAIN(SORT(QUERY(FILTER({ARRAYFORMULA(UPPER(C128:C287)), ARRAYFORMULA(VALUE(SUBSTITUTE(SUBSTITUTE(E128:E287,""€"",""""),"" "","""")))}, ARRAYFORMULA(VALUE(SUBSTITUTE(SUBSTITUTE(E128:E287,""€"",""""),"" "",""""))) > 0), ""select Col1, sum(Col2) w"&"here Col1 is not null group by Col1 label sum(Col2) ''"", 0), 2, FALSE), 5, 2) "),"CASH") -> CASH | D10: =IFERROR(__xludf.DUMMYFUNCTION("""COMPUTED_VALUE"""),5570.0) -> 5570
C11: =IFERROR(__xludf.DUMMYFUNCTION("""COMPUTED_VALUE"""),"STICHTING MOLLIE PAYMENTS") -> STICHTING MOLLIE PAYMENTS | D11: =IFERROR(__xludf.DUMMYFUNCTION("""COMPUTED_VALUE"""),3864.1000000000004) -> 3864.1
C12: =IFERROR(__xludf.DUMMYFUNCTION("""COMPUTED_VALUE"""),"ADM,COM, FLEURUS") -> ADM,COM, FLEURUS | D12: =IFERROR(__xludf.DUMMYFUNCTION("""COMPUTED_VALUE"""),1240.0) -> 1240
C13: =IFERROR(__xludf.DUMMYFUNCTION("""COMPUTED_VALUE"""),"MIFRATEL NV") -> MIFRATEL NV | D13: =IFERROR(__xludf.DUMMYFUNCTION("""COMPUTED_VALUE"""),859.1) -> 859.1
C14: =IFERROR(__xludf.DUMMYFUNCTION("""COMPUTED_VALUE"""),"MISTERFLY SAS SUCCURSALE BELGIQUE") -> MISTERFLY SAS SUCCURSALE BELGIQUE | D14: =IFERROR(__xludf.DUMMYFUNCTION("""COMPUTED_VALUE"""),847.0) -> 847
C15: =IFERROR(__xludf.DUMMYFUNCTION("ARRAYFORMULA({ INDEX(ARRAY_CONSTRAIN(SORT( QUERY( FILTER({ARRAYFORMULA(UPPER(C128:C287)), ARRAYFORMULA(VALUE(SUBSTITUTE(SUBSTITUTE(E128:E287,""€"",""""),"" "","""")))}, ARRAYFORMULA(VALUE(SUBSTITUTE(SUBSTITUTE(E128:E287,""€"",""""),"" "",""""))) < 0), ""s"&"elect Col1, sum(Col2) where Col1 is not null group by Col1 label sum(Col2) ''"", 0 ), 2, TRUE ), 8, 2), , 1), IF(SEQUENCE(8,1), """"), INDEX(ARRAY_CONSTRAIN(SORT( QUERY( FILTER({ARRAYFORMULA(UPPER(C128:C287)), ARRAYFORMULA(VALUE(SUBSTITUTE(SUBSTITUTE(E128"&":E287,""€"",""""),"" "","""")))}, ARRAYFORMULA(VALUE(SUBSTITUTE(SUBSTITUTE(E128:E287,""€"",""""),"" "",""""))) < 0), ""select Col1, sum(Col2) where Col1 is not null group by Col1 label sum(Col2) ''"", 0 ), 2, TRUE ), 8, 2), , 2) }) "),"PAYPAL EUROPE S,A,R,L, ET CIE S,C,A") -> PAYPAL EUROPE S,A,R,L, ET CIE S,C,A | D15: =IFERROR(__xludf.DUMMYFUNCTION("""COMPUTED_VALUE"""),"") | E15: =IFERROR(__xludf.DUMMYFUNCTION("""COMPUTED_VALUE"""),-6016.699999999999) -> -6016.7
C16: =IFERROR(__xludf.DUMMYFUNCTION("""COMPUTED_VALUE"""),"RECETTES TVA") -> RECETTES TVA | D16: =IFERROR(__xludf.DUMMYFUNCTION("""COMPUTED_VALUE"""),"") | E16: =IFERROR(__xludf.DUMMYFUNCTION("""COMPUTED_VALUE"""),-2492.8100000000004) -> -2492.81
C17: =IFERROR(__xludf.DUMMYFUNCTION("""COMPUTED_VALUE"""),"EYE-T CONSULTING SRL") -> EYE-T CONSULTING SRL | D17: =IFERROR(__xludf.DUMMYFUNCTION("""COMPUTED_VALUE"""),"") | E17: =IFERROR(__xludf.DUMMYFUNCTION("""COMPUTED_VALUE"""),-2459.83) -> -2459.83
C18: =IFERROR(__xludf.DUMMYFUNCTION("""COMPUTED_VALUE"""),"M,B, TECH") -> M,B, TECH | D18: =IFERROR(__xludf.DUMMYFUNCTION("""COMPUTED_VALUE"""),"") | E18: =IFERROR(__xludf.DUMMYFUNCTION("""COMPUTED_VALUE"""),-2437.18) -> -2437.18
C19: =IFERROR(__xludf.DUMMYFUNCTION("""COMPUTED_VALUE"""),"DEDUORVA") -> DEDUORVA | D19: =IFERROR(__xludf.DUMMYFUNCTION("""COMPUTED_VALUE"""),"") | E19: =IFERROR(__xludf.DUMMYFUNCTION("""COMPUTED_VALUE"""),-2178.0) -> -2178
C20: =IFERROR(__xludf.DUMMYFUNCTION("""COMPUTED_VALUE"""),"ECOGESTION") -> ECOGESTION | D20: =IFERROR(__xludf.DUMMYFUNCTION("""COMPUTED_VALUE"""),"") | E20: =IFERROR(__xludf.DUMMYFUNCTION("""COMPUTED_VALUE"""),-2178.0) -> -2178
C21: =IFERROR(__xludf.DUMMYFUNCTION("""COMPUTED_VALUE"""),"MONIQUE DECLOEDT") -> MONIQUE DECLOEDT | D21: =IFERROR(__xludf.DUMMYFUNCTION("""COMPUTED_VALUE"""),"") | E21: =IFERROR(__xludf.DUMMYFUNCTION("""COMPUTED_VALUE"""),-1320.0) -> -1320
C22: =IFERROR(__xludf.DUMMYFUNCTION("""COMPUTED_VALUE"""),"PROXIMUS") -> PROXIMUS | D22: =IFERROR(__xludf.DUMMYFUNCTION("""COMPUTED_VALUE"""),"") | E22: =IFERROR(__xludf.DUMMYFUNCTION("""COMPUTED_VALUE"""),-970.45) -> -970.45
C27: TRIMESTRE 4 | D27: =IFERROR(__xludf.DUMMYFUNCTION("SUM(FILTER(ARRAYFORMULA(VALUE(SUBSTITUTE(SUBSTITUTE(E127:E166,""€"",""""),"" "",""""))), ARRAYFORMULA(VALUE(SUBSTITUTE(SUBSTITUTE(E127:E166,""€"",""""),"" "",""""))) > 0)) "),2387.7) -> 2387.7 | E27: =IFERROR(__xludf.DUMMYFUNCTION("SUM(FILTER(ARRAYFORMULA(VALUE(SUBSTITUTE(SUBSTITUTE(E127:E166,""€"",""""),"" "",""""))), ARRAYFORMULA(VALUE(SUBSTITUTE(SUBSTITUTE(E127:E166,""€"",""""),"" "",""""))) < 0)) "),-5390.31) -> -5390.31
E29: =sum(D27:E27) -> -3002.61
C33: TOP 5 & 10
C34: =IFERROR(__xludf.DUMMYFUNCTION("ARRAY_CONSTRAIN(SORT(QUERY(FILTER({ARRAYFORMULA(UPPER(C152:C311)), ARRAYFORMULA(VALUE(SUBSTITUTE(SUBSTITUTE(E152:E311,""€"",""""),"" "","""")))}, ARRAYFORMULA(VALUE(SUBSTITUTE(SUBSTITUTE(E152:E311,""€"",""""),"" "",""""))) > 0), ""select Col1, sum(Col2) w"&"here Col1 is not null group by Col1 label sum(Col2) ''"", 0), 2, FALSE), 5, 2) "),"CASH") -> CASH | D34: =IFERROR(__xludf.DUMMYFUNCTION("""COMPUTED_VALUE"""),5570.0) -> 5570
C35: =IFERROR(__xludf.DUMMYFUNCTION("""COMPUTED_VALUE"""),"STICHTING MOLLIE PAYMENTS") -> STICHTING MOLLIE PAYMENTS | D35: =IFERROR(__xludf.DUMMYFUNCTION("""COMPUTED_VALUE"""),3864.1000000000004) -> 3864.1
C36: =IFERROR(__xludf.DUMMYFUNCTION("""COMPUTED_VALUE"""),"ADM,COM, FLEURUS") -> ADM,COM, FLEURUS | D36: =IFERROR(__xludf.DUMMYFUNCTION("""COMPUTED_VALUE"""),1240.0) -> 1240
C37: =IFERROR(__xludf.DUMMYFUNCTION("""COMPUTED_VALUE"""),"MIFRATEL NV") -> MIFRATEL NV | D37: =IFERROR(__xludf.DUMMYFUNCTION("""COMPUTED_VALUE"""),859.1) -> 859.1
C38: =IFERROR(__xludf.DUMMYFUNCTION("""COMPUTED_VALUE"""),"MISTERFLY SAS SUCCURSALE BELGIQUE") -> MISTERFLY SAS SUCCURSALE BELGIQUE | D38: =IFERROR(__xludf.DUMMYFUNCTION("""COMPUTED_VALUE"""),847.0) -> 847
C39: =IFERROR(__xludf.DUMMYFUNCTION("ARRAYFORMULA({ INDEX(ARRAY_CONSTRAIN(SORT( QUERY( FILTER({ARRAYFORMULA(UPPER(C152:C311)), ARRAYFORMULA(VALUE(SUBSTITUTE(SUBSTITUTE(E152:E311,""€"",""""),"" "","""")))}, ARRAYFORMULA(VALUE(SUBSTITUTE(SUBSTITUTE(E152:E311,""€"",""""),"" "",""""))) < 0), ""s"&"elect Col1, sum(Col2) where Col1 is not null group by Col1 label sum(Col2) ''"", 0 ), 2, TRUE ), 8, 2), , 1), IF(SEQUENCE(8,1), """"), INDEX(ARRAY_CONSTRAIN(SORT( QUERY( FILTER({ARRAYFORMULA(UPPER(C152:C311)), ARRAYFORMULA(VALUE(SUBSTITUTE(SUBSTITUTE(E152"&":E311,""€"",""""),"" "","""")))}, ARRAYFORMULA(VALUE(SUBSTITUTE(SUBSTITUTE(E152:E311,""€"",""""),"" "",""""))) < 0), ""select Col1, sum(Col2) where Col1 is not null group by Col1 label sum(Col2) ''"", 0 ), 2, TRUE ), 8, 2), , 2) }) "),"PAYPAL EUROPE S,A,R,L, ET CIE S,C,A") -> PAYPAL EUROPE S,A,R,L, ET CIE S,C,A | D39: =IFERROR(__xludf.DUMMYFUNCTION("""COMPUTED_VALUE"""),"") | E39: =IFERROR(__xludf.DUMMYFUNCTION("""COMPUTED_VALUE"""),-4970.579999999999) -> -4970.58
C40: =IFERROR(__xludf.DUMMYFUNCTION("""COMPUTED_VALUE"""),"RECETTES TVA") -> RECETTES TVA | D40: =IFERROR(__xludf.DUMMYFUNCTION("""COMPUTED_VALUE"""),"") | E40: =IFERROR(__xludf.DUMMYFUNCTION("""COMPUTED_VALUE"""),-2492.8100000000004) -> -2492.81
C41: =IFERROR(__xludf.DUMMYFUNCTION("""COMPUTED_VALUE"""),"EYE-T CONSULTING SRL") -> EYE-T CONSULTING SRL | D41: =IFERROR(__xludf.DUMMYFUNCTION("""COMPUTED_VALUE"""),"") | E41: =IFERROR(__xludf.DUMMYFUNCTION("""COMPUTED_VALUE"""),-2459.83) -> -2459.83
C42: =IFERROR(__xludf.DUMMYFUNCTION("""COMPUTED_VALUE"""),"M,B, TECH") -> M,B, TECH | D42: =IFERROR(__xludf.DUMMYFUNCTION("""COMPUTED_VALUE"""),"") | E42: =IFERROR(__xludf.DUMMYFUNCTION("""COMPUTED_VALUE"""),-2437.18) -> -2437.18
C43: =IFERROR(__xludf.DUMMYFUNCTION("""COMPUTED_VALUE"""),"DEDUORVA") -> DEDUORVA | D43: =IFERROR(__xludf.DUMMYFUNCTION("""COMPUTED_VALUE"""),"") | E43: =IFERROR(__xludf.DUMMYFUNCTION("""COMPUTED_VALUE"""),-2178.0) -> -2178
C44: =IFERROR(__xludf.DUMMYFUNCTION("""COMPUTED_VALUE"""),"ECOGESTION") -> ECOGESTION | D44: =IFERROR(__xludf.DUMMYFUNCTION("""COMPUTED_VALUE"""),"") | E44: =IFERROR(__xludf.DUMMYFUNCTION("""COMPUTED_VALUE"""),-2178.0) -> -2178
C45: =IFERROR(__xludf.DUMMYFUNCTION("""COMPUTED_VALUE"""),"MONIQUE DECLOEDT") -> MONIQUE DECLOEDT | D45: =IFERROR(__xludf.DUMMYFUNCTION("""COMPUTED_VALUE"""),"") | E45: =IFERROR(__xludf.DUMMYFUNCTION("""COMPUTED_VALUE"""),-1200.0) -> -1200
C46: =IFERROR(__xludf.DUMMYFUNCTION("""COMPUTED_VALUE"""),"PROXIMUS") -> PROXIMUS | D46: =IFERROR(__xludf.DUMMYFUNCTION("""COMPUTED_VALUE"""),"") | E46: =IFERROR(__xludf.DUMMYFUNCTION("""COMPUTED_VALUE"""),-813.24) -> -813.24
C52: TRIMESTRE 3 | D52: =IFERROR(__xludf.DUMMYFUNCTION("SUM(FILTER(ARRAYFORMULA(VALUE(SUBSTITUTE(SUBSTITUTE(E167:E213,""€"",""""),"" "",""""))), ARRAYFORMULA(VALUE(SUBSTITUTE(SUBSTITUTE(E167:E213,""€"",""""),"" "",""""))) > 0)) "),9162.42) -> 9162.42 | E52: =IFERROR(__xludf.DUMMYFUNCTION("SUM(FILTER(ARRAYFORMULA(VALUE(SUBSTITUTE(SUBSTITUTE(E167:E213,""€"",""""),"" "",""""))), ARRAYFORMULA(VALUE(SUBSTITUTE(SUBSTITUTE(E167:E213,""€"",""""),"" "",""""))) < 0)) "),-5664.55) -> -5664.55
E54: =sum(D52:E52) -> 3497.87
C58: TOP 5 & 10
C59: =IFERROR(__xludf.DUMMYFUNCTION("ARRAY_CONSTRAIN(SORT(QUERY(FILTER({ARRAYFORMULA(UPPER(C177:C336)), ARRAYFORMULA(VALUE(SUBSTITUTE(SUBSTITUTE(E177:E336,""€"",""""),"" "","""")))}, ARRAYFORMULA(VALUE(SUBSTITUTE(SUBSTITUTE(E177:E336,""€"",""""),"" "",""""))) > 0), ""select Col1, sum(Col2) w"&"here Col1 is not null group by Col1 label sum(Col2) ''"", 0), 2, FALSE), 5, 2) "),"STICHTING MOLLIE PAYMENTS") -> STICHTING MOLLIE PAYMENTS | D59: =IFERROR(__xludf.DUMMYFUNCTION("""COMPUTED_VALUE"""),3864.1000000000004) -> 3864.1
C60: =IFERROR(__xludf.DUMMYFUNCTION("""COMPUTED_VALUE"""),"CASH") -> CASH | D60: =IFERROR(__xludf.DUMMYFUNCTION("""COMPUTED_VALUE"""),1600.0) -> 1600
C61: =IFERROR(__xludf.DUMMYFUNCTION("""COMPUTED_VALUE"""),"ADM,COM, FLEURUS") -> ADM,COM, FLEURUS | D61: =IFERROR(__xludf.DUMMYFUNCTION("""COMPUTED_VALUE"""),1240.0) -> 1240
C62: =IFERROR(__xludf.DUMMYFUNCTION("""COMPUTED_VALUE"""),"MIFRATEL NV") -> MIFRATEL NV | D62: =IFERROR(__xludf.DUMMYFUNCTION("""COMPUTED_VALUE"""),859.1) -> 859.1
C63: =IFERROR(__xludf.DUMMYFUNCTION("""COMPUTED_VALUE"""),"MISTERFLY SAS SUCCURSALE BELGIQUE") -> MISTERFLY SAS SUCCURSALE BELGIQUE | D63: =IFERROR(__xludf.DUMMYFUNCTION("""COMPUTED_VALUE"""),847.0) -> 847
C64: =IFERROR(__xludf.DUMMYFUNCTION("ARRAYFORMULA({ INDEX(ARRAY_CONSTRAIN(SORT( QUERY( FILTER({ARRAYFORMULA(UPPER(C177:C336)), ARRAYFORMULA(VALUE(SUBSTITUTE(SUBSTITUTE(E177:E336,""€"",""""),"" "","""")))}, ARRAYFORMULA(VALUE(SUBSTITUTE(SUBSTITUTE(E177:E336,""€"",""""),"" "",""""))) < 0), ""s"&"elect Col1, sum(Col2) where Col1 is not null group by Col1 label sum(Col2) ''"", 0 ), 2, TRUE ), 8, 2), , 1), IF(SEQUENCE(8,1), """"), INDEX(ARRAY_CONSTRAIN(SORT( QUERY( FILTER({ARRAYFORMULA(UPPER(C177:C336)), ARRAYFORMULA(VALUE(SUBSTITUTE(SUBSTITUTE(E177"&":E336,""€"",""""),"" "","""")))}, ARRAYFORMULA(VALUE(SUBSTITUTE(SUBSTITUTE(E177:E336,""€"",""""),"" "",""""))) < 0), ""select Col1, sum(Col2) where Col1 is not null group by Col1 label sum(Col2) ''"", 0 ), 2, TRUE ), 8, 2), , 2) }) "),"PAYPAL EUROPE S,A,R,L, ET CIE S,C,A") -> PAYPAL EUROPE S,A,R,L, ET CIE S,C,A | D64: =IFERROR(__xludf.DUMMYFUNCTION("""COMPUTED_VALUE"""),"") | E64: =IFERROR(__xludf.DUMMYFUNCTION("""COMPUTED_VALUE"""),-3838.23) -> -3838.23
C65: =IFERROR(__xludf.DUMMYFUNCTION("""COMPUTED_VALUE"""),"RECETTES TVA") -> RECETTES TVA | D65: =IFERROR(__xludf.DUMMYFUNCTION("""COMPUTED_VALUE"""),"") | E65: =IFERROR(__xludf.DUMMYFUNCTION("""COMPUTED_VALUE"""),-2492.8100000000004) -> -2492.81
C66: =IFERROR(__xludf.DUMMYFUNCTION("""COMPUTED_VALUE"""),"EYE-T CONSULTING SRL") -> EYE-T CONSULTING SRL | D66: =IFERROR(__xludf.DUMMYFUNCTION("""COMPUTED_VALUE"""),"") | E66: =IFERROR(__xludf.DUMMYFUNCTION("""COMPUTED_VALUE"""),-2459.83) -> -2459.83
C67: =IFERROR(__xludf.DUMMYFUNCTION("""COMPUTED_VALUE"""),"DEDUORVA") -> DEDUORVA | D67: =IFERROR(__xludf.DUMMYFUNCTION("""COMPUTED_VALUE"""),"") | E67: =IFERROR(__xludf.DUMMYFUNCTION("""COMPUTED_VALUE"""),-2178.0) -> -2178
C68: =IFERROR(__xludf.DUMMYFUNCTION("""COMPUTED_VALUE"""),"M,B, TECH") -> M,B, TECH | D68: =IFERROR(__xludf.DUMMYFUNCTION("""COMPUTED_VALUE"""),"") | E68: =IFERROR(__xludf.DUMMYFUNCTION("""COMPUTED_VALUE"""),-1697.1399999999999) -> -1697.14
C69: =IFERROR(__xludf.DUMMYFUNCTION("""COMPUTED_VALUE"""),"ECOGESTION") -> ECOGESTION | D69: =IFERROR(__xludf.DUMMYFUNCTION("""COMPUTED_VALUE"""),"") | E69: =IFERROR(__xludf.DUMMYFUNCTION("""COMPUTED_VALUE"""),-1089.0) -> -1089
C70: =IFERROR(__xludf.DUMMYFUNCTION("""COMPUTED_VALUE"""),"MONIQUE DECLOEDT") -> MONIQUE DECLOEDT | D70: =IFERROR(__xludf.DUMMYFUNCTION("""COMPUTED_VALUE"""),"") | E70: =IFERROR(__xludf.DUMMYFUNCTION("""COMPUTED_VALUE"""),-1080.0) -> -1080
C71: =IFERROR(__xludf.DUMMYFUNCTION("""COMPUTED_VALUE"""),"PROXIMUS") -> PROXIMUS | D71: =IFERROR(__xludf.DUMMYFUNCTION("""COMPUTED_VALUE"""),"") | E71: =IFERROR(__xludf.DUMMYFUNCTION("""COMPUTED_VALUE"""),-655.3599999999999) -> -655.36
C77: TRIMESTRE 2 | D77: =IFERROR(__xludf.DUMMYFUNCTION("SUM(FILTER(ARRAYFORMULA(VALUE(SUBSTITUTE(SUBSTITUTE(E214:E263,""€"",""""),"" "",""""))), ARRAYFORMULA(VALUE(SUBSTITUTE(SUBSTITUTE(E214:E263,""€"",""""),"" "",""""))) > 0)) "),4215.78) -> 4215.78 | E77: =IFERROR(__xludf.DUMMYFUNCTION("SUM(FILTER(ARRAYFORMULA(VALUE(SUBSTITUTE(SUBSTITUTE(E214:E263,""€"",""""),"" "",""""))), ARRAYFORMULA(VALUE(SUBSTITUTE(SUBSTITUTE(E214:E263,""€"",""""),"" "",""""))) < 0)) "),-8236.16) -> -8236.16
E79: =sum(D77:E77) -> -4020.38
C83: TOP 5 & 10
C84: =IFERROR(__xludf.DUMMYFUNCTION("ARRAY_CONSTRAIN(SORT(QUERY(FILTER({ARRAYFORMULA(UPPER(C202:C361)), ARRAYFORMULA(VALUE(SUBSTITUTE(SUBSTITUTE(E202:E361,""€"",""""),"" "","""")))}, ARRAYFORMULA(VALUE(SUBSTITUTE(SUBSTITUTE(E202:E361,""€"",""""),"" "",""""))) > 0), ""select Col1, sum(Col2) w"&"here Col1 is not null group by Col1 label sum(Col2) ''"", 0), 2, FALSE), 5, 2) "),"STICHTING MOLLIE PAYMENTS") -> STICHTING MOLLIE PAYMENTS | D84: =IFERROR(__xludf.DUMMYFUNCTION("""COMPUTED_VALUE"""),3270.7799999999997) -> 3270.78
C85: =IFERROR(__xludf.DUMMYFUNCTION("""COMPUTED_VALUE"""),"CASH") -> CASH | D85: =IFERROR(__xludf.DUMMYFUNCTION("""COMPUTED_VALUE"""),1600.0) -> 1600
C86: =IFERROR(__xludf.DUMMYFUNCTION("""COMPUTED_VALUE"""),"MISTERFLY SAS SUCCURSALE BELGIQUE") -> MISTERFLY SAS SUCCURSALE BELGIQUE | D86: =IFERROR(__xludf.DUMMYFUNCTION("""COMPUTED_VALUE"""),847.0) -> 847
C87: =IFERROR(__xludf.DUMMYFUNCTION("""COMPUTED_VALUE"""),"DERNELLE GEOFFROY") -> DERNELLE GEOFFROY | D87: =IFERROR(__xludf.DUMMYFUNCTION("""COMPUTED_VALUE"""),700.0) -> 700
C88: =IFERROR(__xludf.DUMMYFUNCTION("""COMPUTED_VALUE"""),"ZONE POLICE FLEURUS-LES") -> ZONE POLICE FLEURUS-LES | D88: =IFERROR(__xludf.DUMMYFUNCTION("""COMPUTED_VALUE"""),545.0) -> 545
C89: =IFERROR(__xludf.DUMMYFUNCTION("ARRAYFORMULA({ INDEX(ARRAY_CONSTRAIN(SORT( QUERY( FILTER({ARRAYFORMULA(UPPER(C202:C361)), ARRAYFORMULA(VALUE(SUBSTITUTE(SUBSTITUTE(E202:E361,""€"",""""),"" "","""")))}, ARRAYFORMULA(VALUE(SUBSTITUTE(SUBSTITUTE(E202:E361,""€"",""""),"" "",""""))) < 0), ""s"&"elect Col1, sum(Col2) where Col1 is not null group by Col1 label sum(Col2) ''"", 0 ), 2, TRUE ), 8, 2), , 1), IF(SEQUENCE(8,1), """"), INDEX(ARRAY_CONSTRAIN(SORT( QUERY( FILTER({ARRAYFORMULA(UPPER(C202:C361)), ARRAYFORMULA(VALUE(SUBSTITUTE(SUBSTITUTE(E202"&":E361,""€"",""""),"" "","""")))}, ARRAYFORMULA(VALUE(SUBSTITUTE(SUBSTITUTE(E202:E361,""€"",""""),"" "",""""))) < 0), ""select Col1, sum(Col2) where Col1 is not null group by Col1 label sum(Col2) ''"", 0 ), 2, TRUE ), 8, 2), , 2) }) "),"PAYPAL EUROPE S,A,R,L, ET CIE S,C,A") -> PAYPAL EUROPE S,A,R,L, ET CIE S,C,A | D89: =IFERROR(__xludf.DUMMYFUNCTION("""COMPUTED_VALUE"""),"") | E89: =IFERROR(__xludf.DUMMYFUNCTION("""COMPUTED_VALUE"""),-3171.9) -> -3171.9
C90: =IFERROR(__xludf.DUMMYFUNCTION("""COMPUTED_VALUE"""),"EYE-T CONSULTING SRL") -> EYE-T CONSULTING SRL | D90: =IFERROR(__xludf.DUMMYFUNCTION("""COMPUTED_VALUE"""),"") | E90: =IFERROR(__xludf.DUMMYFUNCTION("""COMPUTED_VALUE"""),-2459.83) -> -2459.83
C91: =IFERROR(__xludf.DUMMYFUNCTION("""COMPUTED_VALUE"""),"DEDUORVA") -> DEDUORVA | D91: =IFERROR(__xludf.DUMMYFUNCTION("""COMPUTED_VALUE"""),"") | E91: =IFERROR(__xludf.DUMMYFUNCTION("""COMPUTED_VALUE"""),-2178.0) -> -2178
C92: =IFERROR(__xludf.DUMMYFUNCTION("""COMPUTED_VALUE"""),"RECETTES TVA") -> RECETTES TVA | D92: =IFERROR(__xludf.DUMMYFUNCTION("""COMPUTED_VALUE"""),"") | E92: =IFERROR(__xludf.DUMMYFUNCTION("""COMPUTED_VALUE"""),-2101.88) -> -2101.88
C93: =IFERROR(__xludf.DUMMYFUNCTION("""COMPUTED_VALUE"""),"M,B, TECH") -> M,B, TECH | D93: =IFERROR(__xludf.DUMMYFUNCTION("""COMPUTED_VALUE"""),"") | E93: =IFERROR(__xludf.DUMMYFUNCTION("""COMPUTED_VALUE"""),-1109.1399999999999) -> -1109.14
C94: =IFERROR(__xludf.DUMMYFUNCTION("""COMPUTED_VALUE"""),"ECOGESTION") -> ECOGESTION | D94: =IFERROR(__xludf.DUMMYFUNCTION("""COMPUTED_VALUE"""),"") | E94: =IFERROR(__xludf.DUMMYFUNCTION("""COMPUTED_VALUE"""),-1089.0) -> -1089
C95: =IFERROR(__xludf.DUMMYFUNCTION("""COMPUTED_VALUE"""),"MONIQUE DECLOEDT") -> MONIQUE DECLOEDT | D95: =IFERROR(__xludf.DUMMYFUNCTION("""COMPUTED_VALUE"""),"") | E95: =IFERROR(__xludf.DUMMYFUNCTION("""COMPUTED_VALUE"""),-840.0) -> -840
C96: =IFERROR(__xludf.DUMMYFUNCTION("""COMPUTED_VALUE"""),"PROXIMUS ANDERLE BRUXELLES") -> PROXIMUS ANDERLE BRUXELLES | D96: =IFERROR(__xludf.DUMMYFUNCTION("""COMPUTED_VALUE"""),"") | E96: =IFERROR(__xludf.DUMMYFUNCTION("""COMPUTED_VALUE"""),-499.0) -> -499
C101: TRIMESTRE 1 | D101: =IFERROR(__xludf.DUMMYFUNCTION("SUM(FILTER(ARRAYFORMULA(VALUE(SUBSTITUTE(SUBSTITUTE(E264:E288,""€"",""""),"" "",""""))), ARRAYFORMULA(VALUE(SUBSTITUTE(SUBSTITUTE(E264:E288,""€"",""""),"" "",""""))) > 0)) "),1697.0) -> 1697 | E101: =IFERROR(__xludf.DUMMYFUNCTION("SUM(FILTER(ARRAYFORMULA(VALUE(SUBSTITUTE(SUBSTITUTE(E264:E288,""€"",""""),"" "",""""))), ARRAYFORMULA(VALUE(SUBSTITUTE(SUBSTITUTE(E264:E288,""€"",""""),"" "",""""))) < 0)) "),-7212.74) -> -7212.74
E103: =sum(D101:E101) -> -5515.74
C107: TOP 5 & 10
C108: =IFERROR(__xludf.DUMMYFUNCTION("ARRAY_CONSTRAIN(SORT(QUERY(FILTER({ARRAYFORMULA(UPPER(C264:C288)), ARRAYFORMULA(VALUE(SUBSTITUTE(SUBSTITUTE(E264:E288,""€"",""""),"" "","""")))}, ARRAYFORMULA(VALUE(SUBSTITUTE(SUBSTITUTE(E264:E288,""€"",""""),"" "",""""))) > 0), ""select Col1, sum(Col2) w"&"here Col1 is not null group by Col1 label sum(Col2) ''"", 0), 2, FALSE), 5, 2) "),"MISTERFLY SAS SUCCURSALE BELGIQUE") -> MISTERFLY SAS SUCCURSALE BELGIQUE | D108: =IFERROR(__xludf.DUMMYFUNCTION("""COMPUTED_VALUE"""),847.0) -> 847
C109: =IFERROR(__xludf.DUMMYFUNCTION("""COMPUTED_VALUE"""),"DERNELLE GEOFFROY") -> DERNELLE GEOFFROY | D109: =IFERROR(__xludf.DUMMYFUNCTION("""COMPUTED_VALUE"""),700.0) -> 700
C110: =IFERROR(__xludf.DUMMYFUNCTION("""COMPUTED_VALUE"""),"ANNICK ALLARD") -> ANNICK ALLARD | D110: =IFERROR(__xludf.DUMMYFUNCTION("""COMPUTED_VALUE"""),150.0) -> 150
C113: =IFERROR(__xludf.DUMMYFUNCTION("ARRAYFORMULA({ INDEX(ARRAY_CONSTRAIN(SORT( QUERY( FILTER({ARRAYFORMULA(UPPER(C264:C288)), ARRAYFORMULA(VALUE(SUBSTITUTE(SUBSTITUTE(E264:E288,""€"",""""),"" "","""")))}, ARRAYFORMULA(VALUE(SUBSTITUTE(SUBSTITUTE(E264:E288,""€"",""""),"" "",""""))) < 0), ""s"&"elect Col1, sum(Col2) where Col1 is not null group by Col1 label sum(Col2) ''"", 0 ), 2, TRUE ), 8, 2), , 1), IF(SEQUENCE(8,1), """"), INDEX(ARRAY_CONSTRAIN(SORT( QUERY( FILTER({ARRAYFORMULA(UPPER(C264:C288)), ARRAYFORMULA(VALUE(SUBSTITUTE(SUBSTITUTE(E264"&":E288,""€"",""""),"" "","""")))}, ARRAYFORMULA(VALUE(SUBSTITUTE(SUBSTITUTE(E264:E288,""€"",""""),"" "",""""))) < 0), ""select Col1, sum(Col2) where Col1 is not null group by Col1 label sum(Col2) ''"", 0 ), 2, TRUE ), 8, 2), , 2) }) "),"DEDUORVA") -> DEDUORVA | D113: =IFERROR(__xludf.DUMMYFUNCTION("""COMPUTED_VALUE"""),"") | E113: =IFERROR(__xludf.DUMMYFUNCTION("""COMPUTED_VALUE"""),-2178.0) -> -2178
C114: =IFERROR(__xludf.DUMMYFUNCTION("""COMPUTED_VALUE"""),"RECETTES TVA") -> RECETTES TVA | D114: =IFERROR(__xludf.DUMMYFUNCTION("""COMPUTED_VALUE"""),"") | E114: =IFERROR(__xludf.DUMMYFUNCTION("""COMPUTED_VALUE"""),-1668.5700000000002) -> -1668.57
C115: =IFERROR(__xludf.DUMMYFUNCTION("""COMPUTED_VALUE"""),"EYE-T CONSULTING SRL") -> EYE-T CONSULTING SRL | D115: =IFERROR(__xludf.DUMMYFUNCTION("""COMPUTED_VALUE"""),"") | E115: =IFERROR(__xludf.DUMMYFUNCTION("""COMPUTED_VALUE"""),-1326.83) -> -1326.83
C116: =IFERROR(__xludf.DUMMYFUNCTION("""COMPUTED_VALUE"""),"PAYPAL EUROPE S,A,R,L, ET CIE S,C,A") -> PAYPAL EUROPE S,A,R,L, ET CIE S,C,A | D116: =IFERROR(__xludf.DUMMYFUNCTION("""COMPUTED_VALUE"""),"") | E116: =IFERROR(__xludf.DUMMYFUNCTION("""COMPUTED_VALUE"""),-926.89) -> -926.89
C117: =IFERROR(__xludf.DUMMYFUNCTION("""COMPUTED_VALUE"""),"L8P SCHELLE") -> L8P SCHELLE | D117: =IFERROR(__xludf.DUMMYFUNCTION("""COMPUTED_VALUE"""),"") | E117: =IFERROR(__xludf.DUMMYFUNCTION("""COMPUTED_VALUE"""),-349.0) -> -349
C118: =IFERROR(__xludf.DUMMYFUNCTION("""COMPUTED_VALUE"""),"MONIQUE DECLOEDT") -> MONIQUE DECLOEDT | D118: =IFERROR(__xludf.DUMMYFUNCTION("""COMPUTED_VALUE"""),"") | E118: =IFERROR(__xludf.DUMMYFUNCTION("""COMPUTED_VALUE"""),-240.0) -> -240
C119: =IFERROR(__xludf.DUMMYFUNCTION("""COMPUTED_VALUE"""),"VAN WEZEL AUTOPA TIENEN") -> VAN WEZEL AUTOPA TIENEN | D119: =IFERROR(__xludf.DUMMYFUNCTION("""COMPUTED_VALUE"""),"") | E119: =IFERROR(__xludf.DUMMYFUNCTION("""COMPUTED_VALUE"""),-221.35000000000002) -> -221.35
C120: =IFERROR(__xludf.DUMMYFUNCTION("""COMPUTED_VALUE"""),"PROXIMUS") -> PROXIMUS | D120: =IFERROR(__xludf.DUMMYFUNCTION("""COMPUTED_VALUE"""),"") | E120: =IFERROR(__xludf.DUMMYFUNCTION("""COMPUTED_VALUE"""),-116.92) -> -116.92
B126: Date valeur | C126: Nom de la contrepartie | E126: Montant | F126: Envoyé chez le Comptable
B128: 45982 | C128: PayPal Europe S,a,r,l, et Cie S,C,A | E128: -142.86 | F128: FALSE
B129: 45982 | C129: Mouad Zhiri | E129: -177.06 | F129: FALSE
B130: 45980 | C130: GOOGLE*ADS2562841431 | E130: -10 | F130: FALSE
B131: 45979 | C131: PayPal Europe S,a,r,l, et Cie S,C,A | E131: -200 | F131: FALSE
B132: 45975 | C132: ATAL AF | E132: -4 | F132: FALSE
B133: 45975 | C133: SRL PRO SOCIAL | E133: -223.85 | F133: FALSE
B134: 45975 | C134: Whitworth Jonathan | E134: 4 | F134: FALSE
B135: 45971 | C135: SYSTEME STARTUP | E135: -17 | F135: FALSE
B136: 45972 | C136: DKV EURO SERVICE Gmb | E136: -179.24 | F136: FALSE
B137: 45972 | C137: PayPal Europe S,a,r,l, et Cie S,C,A | E137: -200 | F137: FALSE
B138: 45965 | C138: PayPal Europe S,a,r,l, et Cie S,C,A | E138: -200 | F138: FALSE
B139: 45965 | C139: ASSOCIATION SECTEUR 7 | E139: 726 | F139: FALSE
... B287: 45659 | C287: Monique Decloedt | E287: -120 | F287: TRUE
